Workbook

Sheet FieldBeat-Zendesk
A1: Ticket ID | B1: Asunto | C1: Estado | D1: Prioridad | E1: Tipo | F1: Fecha Creación (ZD) | G1: Fecha Última Actualización (ZD) | H1: Cliente (Nombre) | I1: Técnico (Nombre) | J1: Solicitante ID | K1: Tiene Visita? | L1: FB Task ID | M1: Inicio Trabajo (FB) | N1: Término Trabajo (FB) | O1: Máquina (FB) | P1: Es Inhábil? | Q1: Duración Trabajo (Minutos) | R1: Tags
A2: 9821 | B2: solicitud cambio de thyratron | C2: pending | D2: urgent | E2: incident | F2: 46042.448 | G2: 46042.484 | H2: INRAD | I2: Sin Asignar | J2: 38368479928987 | K2: SI | L2: 3479 | M2: 46042.584 | O2: Linac-201172 | P2: 0 | R2: Origen: Zendesk
A3: 9817 | B3: Solicitud de conexión para el TRM | C3: pending | D3: low | E3: incident | F3: 46041.52 | G3: 46041.522 | H3: Hospital Clinico de Magallanes | I3: Sin Asignar | J3: 26132276827035 | K3: NO | P3: 0 | R3: Origen: Zendesk
A4: 9816 | B4: Falla del tubo de rayos X | C4: new | D4: urgent | E4: incident | F4: 46037.638 | G4: 46037.642 | H4: Instituto Nacional del Cancer | I4: Sin Asignar | J4: 35062929091611 | K4: SI | L4: 3473 | M4: 46041.622 | O4: N/A | P4: 0 | R4: Origen: Zendesk
A5: 9812 | B5: Table long | C5: solved | D5: high | E5: incident | F5: 46036.584 | G5: 46037.668 | H5: Hospital Clinico de Magallanes | I5: Sin Asignar | J5: 26080982926747 | K5: NO | P5: 0 | R5: Origen: Zendesk
A6: 9811 | B6: Se solicita calibración de láseres de sala de equipo Versa | C6: new | D6: high | E6: incident | F6: 46036.544 | G6: 46036.544 | H6: Clinica Alemana | I6: Sin Asignar | J6: 36182421530907 | K6: SI | L6: 3491 | M6: 46048.45 | O6: N/A | P6: 0 | R6: Origen: Zendesk
A7: 9809 | B7: Panel iview | C7: open | D7: normal | E7: incident | F7: 46036.448 | G7: 46037.45 | H7: Hospital Clinico de Magallanes | I7: Sin Asignar | J7: 26080982926747 | K7: NO | P7: 0 | R7: Origen: Zendesk
A8: 9809 | B8: Panel iview | C8: open | D8: normal | E8: incident | F8: 46036.448 | G8: 46042.445 | H8: Hospital Clinico de Magallanes | I8: Sin Asignar | J8: 26080982926747 | K8: NO | P8: 0 | R8: Origen: Zendesk
A9: 9807 | B9: Equipo no logra iniciar | C9: solved | D9: high | E9: incident | F9: 46035.465 | G9: 46037.501 | H9: Clinica Alemana | I9: Sin Asignar | J9: 36182421530907 | K9: NO | P9: 0 | R9: Origen: Zendesk
A10: 9807 | B10: Equipo no logra iniciar | C10: closed | D10: high | E10: incident | F10: 46035.465 | G10: 46040.518 | H10: Clinica Alemana | I10: Sin Asignar | J10: 36182421530907 | K10: NO | P10: 0 | R10: Origen: Zendesk
A11: 9806 | B11: Interlock PRF En Chk | C11: pending | D11: high | E11: incident | F11: 46034.977 | G11: 46037.643 | H11: UC Christus SCA | I11: Sin Asignar | J11: 20254050952987 | K11: SI | L11: 3462 | M11: 46037.449 | O11: Linac-109256 | P11: 0 | R11: Origen: Zendesk
A12: 9805 | B12: System on water temp | C12: solved | D12: high | E12: incident | F12: 46034.468 | G12: 46036.751 | H12: Hospital Clinico de Magallanes | I12: Sin Asignar | J12: 26080982926747 | K12: NO | P12: 0 | R12: Origen: Zendesk
A13: 9804 | B13: Calibración hexapod | C13: solved | D13: high | E13: incident | F13: 46031.721 | G13: 46037.629 | H13: UC Christus SCA | I13: Sin Asignar | J13: 20254050952987 | K13: NO | P13: 0 | R13: Origen: Zendesk
A14: 9804 | B14: Calibración hexapod | C14: solved | D14: high | E14: incident | F14: 46031.721 | G14: 46039.656 | H14: UC Christus SCA | I14: Sin Asignar | J14: 20254050952987 | K14: NO | P14: 0 | R14: Origen: Zendesk
A15: 9801 | B15: Gantry Stop-Infinity detenido - se requiere atencion en terreno lo antes posible | C15: closed | D15: urgent | E15: incident | F15: 46030.804 | G15: 46035.561 | H15: Instituto Nacional del Cancer | I15: Sin Asignar | J15: 20254050947483 | K15: SI | L15: 3459 | M15: 46030.823 | O15: N/A | P15: 1 | R15: Origen: Zendesk
A16: 9800 | B16: Solicitud de actualizacion de licencias productos Sunnuclear | C16: new | D16: urgent | E16: incident | F16: 46030.601 | G16: 46030.601 | H16: Instituto Nacional del Cancer | I16: Sin Asignar | J16: 20254050948123 | K16: NO | P16: 0 | R16: Origen: Zendesk
A17: 9799 | B17: Interlocks MLC VERSA 1 | C17: solved | D17: high | E17: incident | F17: 46029.469 | G17: 46037.501 | H17: Clinica las Condes | I17: Sin Asignar | J17: 20254020292379 | K17: NO | P17: 0 | R17: Origen: Zendesk
A18: 9799 | B18: Interlocks MLC VERSA 1 | C18: closed | D18: high | E18: incident | F18: 46029.469 | G18: 46040.518 | H18: Clinica las Condes | I18: Sin Asignar | J18: 20254020292379 | K18: NO | P18: 0 | R18: Origen: Zendesk
A19: 9796 | B19: Gantry Stop aleatorio en CL2 Infinity | C19: closed | D19: urgent | E19: incident | F19: 46028.564 | G19: 46035.561 | H19: Instituto Nacional del Cancer | I19: Sin Asignar | J19: 20254050947483 | K19: NO | P19: 0 | R19: Origen: Zendesk
A20: 9795 | B20: Infinity se apaga solo | C20: new | D20: urgent | E20: incident | F20: 46028.478 | G20: 46028.478 | H20: Instituto Nacional del Cancer | I20: Sin Asignar | J20: 20254050947483 | K20: NO | P20: 0 | R20: Origen: Zendesk
A21: 9792 | B21: Perdida conexión Axesse | C21: new | D21: normal | E21: incident | F21: 46027.589 | G21: 46027.589 | H21: UC Christus CECA | I21: Sin Asignar | J21: 23562920769947 | K21: NO | P21: 0 | R21: Origen: Zendesk
A22: 9785 | B22: Maquina se reinicia sola | C22: closed | D22: normal | E22: incident | F22: 46021.599 | G22: 46032.691 | H22: Hospital Clinico de Magallanes | I22: Sin Asignar | J22: 26080982926747 | K22: NO | P22: 0 | R22: Origen: Zendesk
A23: 9783 | B23: advertencia Replace Filter - SunSCAN | C23: pending | D23: high | E23: incident | F23: 46021.533 | G23: 46029.793 | H23: Instituto Nacional del Cancer | I23: Sin Asignar | J23: 20254050947483 | K23: NO | P23: 0 | R23: Origen: Zendesk
A24: 9782 | B24: falla humidificador y AACC del bunker del Infinity | C24: closed | D24: low | E24: incident | F24: 46021.512 | G24: 46028.724 | H24: Instituto Nacional del Cancer | I24: Sin Asignar | J24: 20254050947483 | K24: NO | P24: 0 | R24: Origen: Zendesk
A25: 9781 | B25: Equipo detenido por Problema con "Tasa de dosis baja Canal A" y B | C25: solved | D25: urgent | E25: incident | F25: 46020.746 | G25: 46037.633 | H25: INRAD | I25: Sin Asignar | J25: 38368479928987 | K25: SI | L25: 3447 | M25: 46020.918 | O25: N/A | P25: 1 | R25: Origen: Zendesk
A26: 9778 | B26: Reaparición falla “Gantry Stop” – CL02 Infinity / Ticket 9774 | C26: closed | D26: urgent | E26: incident | F26: 46020.709 | G26: 46032.607 | H26: Instituto Nacional del Cancer | I26: Sin Asignar | J26: 20254050947483 | K26: SI | L26: 3449 | M26: 46024.434 | O26: INC-156473 | P26: 0 | R26: Origen: Zendesk
A27: 9775 | B27: DOSE RATE MON 6MeV INFINITY | C27: closed | D27: normal | E27: incident | F27: 46015.737 | G27: 46024.614 | H27: UC Christus CECA | I27: Sin Asignar | J27: 20254050952347 | K27: SI | L27: 3442 | M27: 46017.513 | O27: Linac-109374 | P27: 0 | R27: Origen: Zendesk
A28: 9774 | B28: falla Gantry Stop - no puedo hacer QA de paciente - Equipo detenido | C28: closed | D28: urgent | E28: incident | F28: 46015.736 | G28: 46019.908 | H28: Instituto Nacional del Cancer | I28: Sin Asignar | J28: 20254050947483 | K28: SI | L28: 3441 | M28: 46020.367 | O28: INC-156473 | P28: 0 | R28: Origen: Zendesk
A29: 9770 | B29: Water Temp | C29: closed | D29: urgent | E29: incident | F29: 46013.655 | G29: 46033.618 | H29: UC Christus SCA | I29: Sin Asignar | J29: 20254050953243 | K29: NO | P29: 0 | R29: Origen: Zendesk
A30: 9764 | B30: Multiples interlocks mas charco de agua en sala de maquinas de origen desconocido | C30: closed | D30: urgent | E30: incident | F30: 46010.494 | G30: 46017.642 | H30: Clinica las Condes | I30: Sin Asignar | J30: 20254020292379 | K30: SI | L30: 3438 | M30: 46010.641 | O30: CLC-1 | P30: 0 | R30: Origen: Zendesk
A31: 9762 | B31: Solicitud de MP Flexitro | C31: new | D31: normal | E31: incident | F31: 46009.542 | G31: 46036.634 | H31: UC Christus CECA | I31: Sin Asignar | J31: 20254050952347 | K31: NO | P31: 0 | R31: Origen: Zendesk
A32: 9751 | B32: Table long | C32: closed | E32: incident | F32: 46006.519 | G32: 46006.86 | H32: Hospital Clinico de Magallanes | I32: Sin Asignar | J32: 26080982926747 | K32: NO | P32: 0 | R32: Origen: Zendesk
A33: 9749 | B33: Dose rate mon | C33: closed | D33: urgent | E33: incident | F33: 46003.519 | G33: 46011.676 | H33: Hospital Carlos Van Buren | I33: Sin Asignar | J33: 20254020299291 | K33: SI | L33: 3431 | M33: 46003.575 | O33: N/A | P33: 0 | R33: Origen: Zendesk
A34: 9748 | B34: Importación plan respalado | C34: closed | D34: low | E34: incident | F34: 46003.493 | G34: 46017.514 | H34: Hospital Clinico de Magallanes | I34: Sin Asignar | J34: 40109334283675 | K34: NO | P34: 0 | R34: Origen: Zendesk
H35: Desconocido | I35: Sin Asignar | K35: NO | P35: 0 | R35: Origen: Zendesk
A36: 9746 | B36: Panel de control lateral de camilla está suelto | C36: closed | D36: normal | E36: incident | F36: 46002.736 | G36: 46007.663 | H36: Hospital Clinico de Magallanes | I36: Sin Asignar | J36: 26080969273499 | K36: SI | L36: 3428 | M36: 46003.65 | O36: Linac-109452 | P36: 0 | R36: Origen: Zendesk
A37: 9745 | B37: Interlock Table Long | C37: closed | D37: normal | E37: incident | F37: 46002.626 | G37: 46032.691 | H37: Hospital Clinico de Magallanes | I37: Sin Asignar | J37: 26080969273499 | K37: NO | P37: 0 | R37: Origen: Zendesk
A38: 9743 | B38: Switches sin luz | C38: closed | D38: low | E38: incident | F38: 46002.542 | G38: 46017.514 | H38: Hospital Clinico de Magallanes | I38: Sin Asignar | J38: 26080982926747 | K38: NO | P38: 0 | R38: Origen: Zendesk
A39: 9742 | B39: Conebeam presenta artefacto | C39: closed | D39: high | E39: incident | F39: 46001.851 | G39: 46012.742 | H39: Clinica Alemana | I39: Sin Asignar | J39: 36182421530907 | K39: NO | P39: 0 | R39: Origen: Zendesk
A40: 9740 | B40: verificacion configuracion del Baseline del test de Hancock MLC Suncheck del Infinity | C40: open | D40: urgent | E40: incident | F40: 46001.651 | G40: 46028.664 | H40: Instituto Nacional del Cancer | I40: Sin Asignar | J40: 20254050947483 | K40: NO | P40: 0 | R40: Origen: Zendesk
A41: 9740 | B41: verificacion configuracion del Baseline del test de Hancock MLC Suncheck del Infinity | C41: pending | D41: urgent | E41: incident | F41: 46001.651 | G41: 46041.501 | H41: Instituto Nacional del Cancer | I41: Sin Asignar | J41: 20254050947483 | K41: NO | P41: 0 | R41: Origen: Zendesk
A42: 9739 | B42: Pantalla de acelerador sin señal | C42: closed | D42: high | E42: incident | F42: 46001.623 | G42: 46005.656 | H42: Hospital Clinico de Magallanes | I42: Sin Asignar | J42: 26080969273499 | K42: NO | P42: 0 | R42: Origen: Zendesk
A43: 9737 | B43: Versa se apaga de forma espontanea | C43: closed | D43: urgent | E43: incident | F43: 46000.798 | G43: 46005.656 | H43: UC Christus SCA | I43: Sin Asignar | J43: 20254050953243 | K43: SI | L43: 3422 | M43: 46000.754 | O43: Linac-109256 | P43: 0 | R43: Origen: Zendesk
A44: 9734 | B44: Solicitud de colaboración para prueba de interruptores de emergencia del acelerador lineal | C44: closed | D44: normal | E44: incident | F44: 46000.727 | G44: 46007.663 | H44: Hospital Clinico de Magallanes | I44: Sin Asignar | J44: 26080969273499 | K44: SI | L44: 3429 | M44: 46003.65 | O44: Linac-109452 | P44: 0 | R44: Origen: Zendesk
A45: 9733 | B45: ruido muy fuerte al girar el gantry del Infinity - por favor investigar | C45: closed | D45: normal | E45: incident | F45: 46000.615 | G45: 46032.607 | H45: Instituto Nacional del Cancer | I45: Sin Asignar | J45: 20254050947483 | K45: NO | P45: 0 | R45: Origen: Zendesk
A46: 9732 | B46: Falla XVI - Fault 33 - despejada gracias a FM Camilo de la Barra | C46: closed | D46: high | E46: incident | F46: 46000.58 | G46: 46011.634 | H46: Instituto Nacional del Cancer | I46: Sin Asignar | J46: 20254050947483 | K46: NO | P46: 0 | R46: Origen: Zendesk
A47: 9731 | B47: Falla en panel iview | C47: open | D47: urgent | E47: incident | F47: 46000.529 | G47: 46021.854 | H47: Clinica Alemana | I47: Sin Asignar | J47: 36182421530907 | K47: SI | L47: 3497 | M47: 46050.38 | O47: Linac-152171 | P47: 0 | R47: Origen: Zendesk
A48: 9724 | B48: falla intermitente del sistema de audio que dificulta oir al paciente del CL02 Infinity | C48: pending | D48: high | E48: incident | F48: 45995.568 | G48: 46000.627 | H48: Instituto Nacional del Cancer | I48: Sin Asignar | J48: 20254050947483 | K48: NO | P48: 0 | R48: Origen: Zendesk
A49: 9723 | B49: Problemas MLC Infinity | C49: closed | D49: urgent | E49: incident | F49: 45995.465 | G49: 46011.676 | H49: UC Christus CECA | I49: Sin Asignar | J49: 23562920769947 | K49: SI | L49: 3415 | M49: 45995.438 | O49: Linac-109374 | P49: 0 | R49: Origen: Zendesk
A50: 9716 | B50: Notebook de qa no carga | C50: closed | D50: normal | E50: incident | F50: 45993.492 | G50: 46025.845 | H50: Hospital Clinico de Magallanes | I50: Sin Asignar | J50: 26080982926747 | K50: NO | P50: 0 | R50: Origen: Zendesk
A51: 9709 | B51: Asunto: Artefacto de anillo en el XVI del Axesee | C51: pending | D51: high | E51: incident | F51: 45992.489 | G51: 46000.543 | H51: UC Christus CECA | I51: Sin Asignar | J51: 20254050952475 | K51: NO | P51: 0 | R51: Origen: Zendesk
A52: 9706 | B52: Problemas en posicionamiento de Hexapod | C52: closed | D52: high | E52: incident | F52: 45988.83 | G52: 46012.742 | H52: Clinica Alemana | I52: Sin Asignar | J52: 36182421530907 | K52: SI | L52: 3425 | M52: 46007.504 | O52: Linac-109496 | P52: 0 | R52: Origen: Zendesk
A53: 9703 | B53: Maquina detenida por falla desconocida | C53: closed | D53: urgent | E53: incident | F53: 45988.477 | G53: 45993.708 | H53: INRAD | I53: Sin Asignar | J53: 38368479928987 | K53: NO | P53: 0 | R53: Origen: Zendesk
A54: 9696 | B54: equipo detenido por problemas con magnetron | C54: closed | D54: urgent | E54: incident | F54: 45987.579 | G54: 45993.708 | H54: INRAD | I54: Sin Asignar | J54: 38368479928987 | K54: NO | P54: 0 | R54: Origen: Zendesk
A55: 9695 | B55: Falla HEXAPOD VERSA 2 | C55: closed | D55: normal | E55: incident | F55: 45987.535 | G55: 46017.642 | H55: Clinica las Condes | I55: Sin Asignar | J55: 20254020292379 | K55: NO | P55: 0 | R55: Origen: Zendesk
A56: 9691 | B56: Interlock D1 | C56: closed | D56: high | E56: incident | F56: 45986.475 | G56: 45990.52 | H56: Hospital Carlos Van Buren | I56: Sin Asignar | J56: 20254020299547 | K56: NO | P56: 0 | R56: Origen: Zendesk
A57: 9690 | B57: 2T 15MeV electrones | C57: closed | D57: normal | E57: incident | F57: 45986.452 | G57: 46024.614 | H57: UC Christus CECA | I57: Sin Asignar | J57: 23562920769947 | K57: SI | L57: 3443 | M57: 46017.517 | O57: Linac-153935 | P57: 0 | R57: Origen: Zendesk
A58: 9689 | B58: Inestabilidad de los haces de fotones VERSA 1 | C58: closed | D58: urgent | E58: incident | F58: 45985.648 | G58: 46011.676 | H58: Clinica las Condes | I58: Sin Asignar | J58: 20254020292379 | K58: NO | P58: 0 | R58: Origen: Zendesk
A59: 9688 | B59: Falla telemetro VERSA 2 | C59: pending | D59: normal | E59: incident | F59: 45985.645 | G59: 45990.751 | H59: Clinica las Condes | I59: Sin Asignar | J59: 20254020292379 | K59: NO | P59: 0 | R59: Origen: Zendesk
A60: 9685 | B60: Interlock Low Water Pressure VERSA 1 | C60: closed | D60: urgent | E60: incident | F60: 45985.511 | G60: 46011.676 | H60: Clinica las Condes | I60: Sin Asignar | J60: 20254020292379 | K60: NO | P60: 0 | R60: Origen: Zendesk
A61: 9684 | B61: Interlock Memoria Acelerador Axesse | C61: closed | D61: normal | E61: incident | F61: 45985.478 | G61: 45991.663 | H61: UC Christus CECA | I61: Sin Asignar | J61: 20254050952347 | K61: NO | P61: 0 | R61: Origen: Zendesk
A62: 9680 | B62: Interlock 10. Trp G | C62: closed | D62: high | E62: incident | F62: 45981.475 | G62: 45991.579 | H62: UC Christus CECA | I62: Sin Asignar | J62: 20254050952603 | K62: NO | P62: 0 | R62: Origen: Zendesk
A63: 9677 | B63: Problema Mosaiq | C63: closed | D63: normal | E63: incident | F63: 45980.807 | G63: 46025.845 | H63: Hospital Clinico de Magallanes | I63: Sin Asignar | J63: 40109334283675 | K63: NO | P63: 0 | R63: Origen: Zendesk
A64: 9672 | B64: continua falla isocentro kV vs isocentro reticulo (luz de campo) y falla MLC test de hancock, post reparacion | C64: new | D64: urgent | E64: incident | F64: 45978.761 | G64: 45978.761 | H64: Instituto Nacional del Cancer | I64: Sin Asignar | J64: 20254050947483 | K64: NO | P64: 0 | R64: Origen: Zendesk
A65: 9670 | B65: Dose Rate Mon 10FFF | C65: closed | D65: high | E65: incident | F65: 45975.685 | G65: 45991.579 | H65: UC Christus SCA | I65: Sin Asignar | J65: 20254050953243 | K65: NO | P65: 0 | R65: Origen: Zendesk
A66: 9668 | B66: Falla MLC VERSA 1 | C66: closed | D66: urgent | E66: incident | F66: 45975.585 | G66: 45982.504 | H66: Clinica las Condes | I66: Sin Asignar | J66: 20254020292379 | K66: NO | P66: 0 | R66: Origen: Zendesk
A67: 9664 | B67: Audio funciona mal | C67: closed | D67: normal | E67: incident | F67: 45974.58 | G67: 45982.887 | H67: Hospital Clinico de Magallanes | I67: Sin Asignar | J67: 26080982926747 | K67: NO | P67: 0 | R67: Origen: Zendesk
A68: 9663 | B68: Comando se camilla suelto | C68: closed | D68: normal | E68: incident | F68: 45974.58 | G68: 45982.887 | H68: Hospital Clinico de Magallanes | I68: Sin Asignar | J68: 26080982926747 | K68: NO | P68: 0 | R68: Origen: Zendesk
A69: 9661 | B69: Interlock reflector MLC VERSA 1 | C69: closed | D69: high | E69: incident | F69: 45973.838 | G69: 46011.634 | H69: Clinica las Condes | I69: Sin Asignar | J69: 20254020292379 | K69: NO | P69: 0 | R69: Origen: Zendesk
... A84: 9598 | B84: Upgrade Monaco 6.2.3 Oncorad | C84: closed | D84: normal | E84: incident | F84: 45946.646 | G84: 45968.538 | H84: Oncorad | I84: Sin Asignar | J84: 20254050950939 | K84: NO | P84: 0 | R84: Origen: Zendesk
A85: 9592 | B85: Interlock Table Long | C85: closed | D85: normal | E85: incident | F85: 45945.485 | G85: 46004.81 | H85: Hospital Clinico de Magallanes | I85: Sin Asignar | J85: 26080969273499 | K85: SI | L85: 3419 | M85: 45996.619 | O85: Linac-109452 | P85: 0 | R85: Origen: Zendesk
A86: 9590 | B86: Derrame fluido sobre gantry | C86: closed | D86: normal | E86: incident | F86: 45944.588 | G86: 45948.84 | H86: Hospital Clinico de Magallanes | I86: Sin Asignar | J86: 26080969273499 | K86: NO | P86: 0 | R86: Origen: Zendesk
A87: 9589 | B87: Equipo con error dose rate mon | C87: closed | D87: urgent | E87: incident | F87: 45944.578 | G87: 45950.906 | H87: Clinica Alemana | I87: Sin Asignar | J87: 36182421530907 | K87: NO | P87: 0 | R87: Origen: Zendesk
A88: 9583 | B88: "Virtual Memory Threshold Exceeded" en Pantalla del Integrity | C88: closed | D88: urgent | E88: incident | F88: 45943.468 | G88: 45947.569 | H88: Instituto Nacional del Cancer | I88: Sin Asignar | J88: 20254050947483 | K88: NO | P88: 0 | R88: Origen: Zendesk
A89: 9582 | B89: falla detección del panel de kV. Equipo No Operativo | C89: closed | D89: urgent | E89: incident | F89: 45943.46 | G89: 45947.569 | H89: Instituto Nacional del Cancer | I89: Sin Asignar | J89: 20254050947483 | K89: NO | P89: 0 | R89: Origen: Zendesk
A90: 9581 | B90: Problema medicion paciente especifico | C90: closed | D90: urgent | E90: incident | F90: 45941.6 | G90: 45948.542 | H90: Instituto Nacional del Cancer | I90: Sin Asignar | J90: 35063016361243 | K90: NO | P90: 0 | R90: Origen: Zendesk
A91: 9576 | B91: Solicitud manejo de cables en sala de comando | C91: closed | D91: urgent | E91: incident | F91: 45940.534 | G91: 45989.708 | H91: INRAD | I91: Sin Asignar | J91: 38368479928987 | K91: NO | P91: 0 | R91: Origen: Zendesk
A92: 9569 | B92: Ghosting Calibration -XVI | C92: closed | D92: normal | E92: incident | F92: 45937.706 | G92: 45943.933 | H92: UC Christus SCA | I92: Sin Asignar | J92: 20254050953243 | K92: NO | P92: 0 | R92: Origen: Zendesk
A93: 9568 | B93: Sonido en el cabezal al girar el colimador | C93: closed | D93: high | E93: incident | F93: 45937.689 | G93: 45943.933 | H93: UC Christus SCA | I93: Sin Asignar | J93: 20254050953243 | K93: NO | P93: 0 | R93: Origen: Zendesk
A94: 9567 | B94: Revisión de bomba de agua del equipo SunScan Reservoir | C94: closed | D94: normal | E94: incident | F94: 45937.601 | G94: 46006.803 | H94: Hospital Clinico de Magallanes | I94: Sin Asignar | J94: 26080969273499 | K94: NO | P94: 0 | R94: Origen: Zendesk
A95: 9566 | B95: FALLA EN IMPRESORA ZEBRA | C95: solved | D95: normal | E95: incident | F95: 45936.682 | G95: 46036.543 | H95: Hospital Clinico de Magallanes | I95: Sin Asignar | J95: 27800736907291 | K95: NO | P95: 0 | R95: Origen: Zendesk
A96: 9566 | B96: FALLA EN IMPRESORA ZEBRA | C96: closed | D96: normal | E96: incident | F96: 45936.682 | G96: 46039.543 | H96: Hospital Clinico de Magallanes | I96: Sin Asignar | J96: 27800736907291 | K96: NO | P96: 0 | R96: Origen: Zendesk
A97: 9565 | B97: Ayuda ajustando láser | C97: closed | D97: normal | E97: incident | F97: 45933.619 | G97: 45954.707 | H97: INRAD | I97: Sin Asignar | J97: 38368479928987 | K97: NO | P97: 0 | R97: Origen: Zendesk
... A116: 9498 | B116: Problemas en 10fff | C116: closed | D116: normal | E116: incident | F116: 45905.585 | G116: 45933.83 | H116: Hospital Clinico de Magallanes | I116: Sin Asignar | J116: 26080982926747 | K116: NO | P116: 0 | R116: Origen: Zendesk
A117: 9496 | B117: otro apagado automático de consola | C117: open | D117: urgent | E117: incident | F117: 45905.536 | G117: 45952.029 | H117: Instituto Nacional del Cancer | I117: Sin Asignar | J117: 20254050947483 | K117: SI | L117: 3518 | M117: 46059.759 | O117: INC-156473 | P117: 0 | R117: Origen: Zendesk
A118: 9484 | B118: Error en mosaiq repositorio temporal | C118: closed | D118: normal | E118: incident | F118: 45902.577 | G118: 45916.669 | H118: Hospital Clinico de Magallanes | I118: Sin Asignar | J118: 26080982926747 | K118: NO | P118: 0 | R118: Origen: Zendesk
A119: 9482 | B119: Conebeam no funciona | C119: closed | D119: urgent | E119: incident | F119: 45902.073 | G119: 45915.669 | H119: Clinica Alemana | I119: Sin Asignar | J119: 36182421530907 | K119: NO | P119: 0 | R119: Origen: Zendesk
A120: 9480 | B120: Cambio de Hora equipos APOTECA. | C120: closed | D120: low | E120: incident | F120: 45901.893 | G120: 45912.793 | H120: Fundación Arturo López Pérez QF | I120: Sin Asignar | J120: 20254020295195 | K120: NO | P120: 0 | R120: Origen: Zendesk
A121: 9476 | B121: Table long | C121: closed | D121: high | E121: incident | F121: 45898.666 | G121: 45948.84 | H121: Hospital Clinico de Magallanes | I121: Sin Asignar | J121: 26080982926747 | K121: NO | P121: 0 | R121: Origen: Zendesk
A122: 9473 | B122: Problemas con láminas en Suragility | C122: closed | D122: high | E122: incident | F122: 45897.972 | G122: 45947.569 | H122: Clinica Alemana | I122: Sin Asignar | J122: 36182421530907 | K122: NO | P122: 0 | R122: Origen: Zendesk
A123: 9471 | B123: Coordinación cambio de hora sábado 06 de Septiembre | C123: closed | D123: normal | E123: incident | F123: 45897.629 | G123: 46007.576 | H123: Fundación Arturo López Perez RT | I123: Sin Asignar | J123: 20254020297371 | K123: NO | P123: 0 | R123: Origen: Zendesk
A124: 9468 | B124: Falla en panel iview | C124: closed | D124: high | E124: incident | F124: 45895.708 | G124: 45899.751 | H124: Clinica Alemana | I124: Sin Asignar | J124: 36182421530907 | K124: NO | P124: 0 | R124: Origen: Zendesk
A125: 9461 | B125: Desplazamiento de Tablero Principal del Detector de Area Ludlum - Braquiterapia | C125: closed | D125: low | E125: incident | F125: 45891.683 | G125: 45900.585 | H125: Oncorad | I125: Sin Asignar | J125: 20254050950939 | K125: NO | P125: 0 | R125: Origen: Zendesk
A126: 9451 | B126: Intermitencia de operación del Suargility | C126: closed | D126: high | E126: incident | F126: 45888.536 | G126: 45895.71 | H126: Clinica Alemana | I126: Sin Asignar | J126: 20254011642523 | K126: NO | P126: 0 | R126: Origen: Zendesk
A127: 9448 | B127: Falla intermitente en adquisición de imágenes CBCT (XVI) | C127: closed | E127: incident | F127: 45887.645 | G127: 45887.648 | H127: Hospital Clinico de Magallanes | I127: Sin Asignar | J127: 40109334283675 | K127: NO | P127: 0 | R127: Origen: Zendesk
A128: 9447 | B128: RE: Falla intermitente en adquisición de imágenes CBCT (XVI) | C128: closed | D128: normal | E128: incident | F128: 45887.635 | G128: 45914.668 | H128: Hospital Clinico de Magallanes | I128: Sin Asignar | J128: 26080969273499 | K128: NO | P128: 0 | R128: Origen: Zendesk
A129: 9444 | B129: Dose rate mon | C129: closed | D129: high | E129: incident | F129: 45883.904 | G129: 45895.71 | H129: UC Christus SCA | I129: Sin Asignar | J129: 20254050952987 | K129: NO | P129: 0 | R129: Origen: Zendesk
A130: 9442 | B130: Alta frecuencia de falla MLC VERSA 1 | C130: closed | D130: high | E130: incident | F130: 45883.852 | G130: 45908.877 | H130: Clinica las Condes | I130: Sin Asignar | J130: 20254020292379 | K130: NO | P130: 0 | R130: Origen: Zendesk
A131: 9435 | B131: Procedimiento para aumentar presion de SF6 | C131: closed | D131: normal | E131: incident | F131: 45881.66 | G131: 45908.668 | H131: INRAD | I131: Sin Asignar | J131: 38368479928987 | K131: NO | P131: 0 | R131: Origen: Zendesk
A132: 9433 | B132: Solicitud de Gestión de cables en Sala de Mando INRAD Elekta Compact | C132: new | D132: high | E132: incident | F132: 45881.658 | G132: 45989.708 | H132: INRAD | I132: Sin Asignar | J132: 38368479928987 | K132: NO | P132: 0 | R132: Origen: Zendesk
...

Sheet Reporte_Tickets_Detallado
A1: Timestamp | B1: Id FB | C1: Id Ticket | D1: Status | E1: Cliente | F1: Maquina | G1: Descripcion | H1: MailLink
A2: 46049.888 | B2: 3498 | C2: 9841 | D2: FINISHED | E2: UC CHRISTUS - SCA | F2: Linac-109256 | G2: Se efectua optimizacion de energias 10mv y 10FFF en donde se mantuvo en espera de chequeo dosimetrico por parte de Fisico Medico | H2: https://mail.google.com/mail?extsrc=sync&client=docs&plid=ACUX6DPlGjlflgzT6j_wvNolFqfhh2Wr2yDb0LM
A3: 46049.768 | B3: 3496 | C3: 9867 | D3: FINISHED | E3: UC CHRISTUS - CECA | F3: Linac-109374 | G3: Se efectuo optimizacion de energía de 6MV vía remota con resultados conforme. | H3: https://mail.google.com/mail?extsrc=sync&client=docs&plid=ACUX6DP5bxtS8PPAcUm57-Ldgkhdza2HbJN3S68
A4: 46049.806 | B4: 3495 | C4: 9833 | D4: FINISHED | E4: RADIO ONCOLOGÍA DEL SUR | F4: Linac-156187 | G4: Se reemplaza tarjeta PCB reguladora de Voltaje. Telémetro no funciona con el voltaje nominal de operación (11 vac). Se procede a bajar voltaje de alimentación a 6 vac, logrando una activación aleatoria. | H4: https://mail.google.com/mail?extsrc=sync&client=docs&plid=ACUX6DNNnNaepmv_UQMrG9h9TdAd-CfC4wh_lQc
A5: 46049.748 | B5: 3493 | C5: Tarea Sin Ticket | D5: FINISHED | E5: CLÍNICA LAS CONDES | F5: N/A | G5: prueba | H5: https://mail.google.com/mail?extsrc=sync&client=docs&plid=ACUX6DP954RE8YWKsXedwQLtzQZQhmALy-8_xfc
A6: 46049.899 | B6: 3492 | C6: 9784 | D6: FINISHED | E6: CLINICA ALEMANA DE SANTIAGO | F6: Linac-152171 | G6: se realiza instalacion de vm intellimax en nss del suragility, adicionalmente se revisa backup de integrity verificando que los backup se estan almacenando correctamente en el sequencer | H6: https://mail.google.com/mail?extsrc=sync&client=docs&plid=ACUX6DPK1xW-mmd02VCwrjQKdl-EfplAkfp3zdI
A7: 46048.45 | B7: 3491 | C7: 9811 | D7: FINISHED | E7: CLINICA ALEMANA DE SANTIAGO | F7: N/A | G7: se asiste al inicio del linac, el suragility sin problemas durante la partida y los controles de fisica medica dieron positivamente, el fisico medico me indica que no se esta realizando el back up del equipo de manera automatica, le comente que lo conversare con el grupo de TI de eyg para buscar solucion, en el versa norte se esta presentando un desalineamiento de los laser con respecto a frame de la hexapod lo cual se realizara su respectiva correccion. | H7: https://mail.google.com/mail?extsrc=sync&client=docs&plid=ACUX6DPnoEirxcbN7hu2jbXqiJLa-ExNps6bpoM
A8: 46048.382 | B8: 3490 | C8: Tarea Sin Ticket | D8: FINISHED | E8: HOSPITAL CARLOS VAN BUREN (SSVSA) | F8: Linac-154325 | G8: Se efectua chequeo de equipo posterior a mantenimiento Preventivo de Chiller y Convertidor, AA de sala de equipos conforme | H8: https://mail.google.com/mail?extsrc=sync&client=docs&plid=ACUX6DMoHLiST6pFDdSqE8NIaGisqZA8hSixp8c
A9: 46048.357 | B9: 3488 | C9: Tarea Sin Ticket | D9: FINISHED | E9: HOSPITAL CARLOS VAN BUREN (SSVSA) | F9: Linac-154325 | G9: Se efectuo mantenimiento Preventivo a Chiller , Convertidor y Aire Acondicionado. | H9: https://mail.google.com/mail?extsrc=sync&client=docs&plid=ACUX6DN8VSAmKM3_x_AQLv2_6YQLokoWPUYj1uI
A10: 46046.606 | B10: 3487 | C10: Tarea Sin Ticket | D10: FINISHED | E10: UC CHRISTUS - CECA | F10: N/A | G10: Mantenimiento preventivo Flexitron UC | H10: https://mail.google.com/mail?extsrc=sync&client=docs&plid=ACUX6DMwyYt83kTv7Z4KvO9QCwLCmCWv56DU31Q
A11: 46046.559 | B11: 3486 | C11: 9819 | D11: FINISHED | E11: UC CHRISTUS - CECA | F11: N/A | G11: mantencion completa de rack ccp y perifericos de ambos linac, se realiza backup mediante acronis de xvi e iview (infinity y axesse) limpieza profunda de estaciones Monaco y Mosaiq ubicadas en dosimetria y sala fisica | H11: https://mail.google.com/mail?extsrc=sync&client=docs&plid=ACUX6DO7fUFGu0eZZfNNAaZO_TQk9mOBGF9PGSw
A12: 46045.855 | B12: 3485 | C12: 9835 | D12: FINISHED | E12: Instituto Nacional del Cáncer (INC) | F12: INC-156473 | G12: Se asiste a sitio a hora acordada y se espera a termino de pacientes, se verifica e inspecciona movimiento del panel encontrandose que a mitad de camino pierde el middle position para retraer, se calibra mediante software y sin resultados positivos, se revisa cadena de switch encontrandose activo al momento de retraer (posicion normal) al retraer pierde posicion y entra en loop de busqueda, se graba video de falla y se consultara a elekta. | H12: https://mail.google.com/mail?extsrc=sync&client=docs&plid=ACUX6DNIUwThTUHE0reAC6nTH8zOdXTI887E-Aw
A13: 46045.68 | B13: 3484 | C13: Tarea Sin Ticket | D13: FINISHED | E13: CLÍNICA SANATORIO ALEMÁN (ONCORAD) | F13: Linac-201110 | G13: Ajuste Centrado Mesa Compact | H13: https://mail.google.com/mail?extsrc=sync&client=docs&plid=ACUX6DOZwMPNGNCDW-DLAh4PV7Vhr1L592sIu6M
A14: 46043.929 | B14: 3483 | C14: 9819 | D14: FINISHED | E14: UC CHRISTUS - SCA | F14: N/A | G14: mantencion rack ccp, iview, xvi, tps | H14: https://mail.google.com/mail?extsrc=sync&client=docs&plid=ACUX6DM3uG8sZMb7Htqg32buYSB6gJbHBbQChg4
A15: 46044.615 | B15: 3482 | C15: 9822 | D15: FINISHED | E15: Instituto Nacional del Cáncer (INC) | F15: N/A | G15: se realiza inspeccion de lo reportado por fisica medica, se puede observar una incrogruencia con lo irradiado y el campo corformado, se realiza la investigacion correspondiente y se determina que el equipo requiere calibracion de los perfiles del haz de luz para buscar la mejor manera de centrar el haz de radiacion y poder ajustar los perfiles del campo. | H15: https://mail.google.com/mail?extsrc=sync&client=docs&plid=ACUX6DOjrVlfp0ZzZMmXDNQRw9UDOVZZtTD7lwg
A16: 46045.383 | B16: 3481 | C16: 9822 | D16: FINISHED | E16: Instituto Nacional del Cáncer (INC) | F16: INC-156473 | G16: Ajuste de perfiles energéticos | H16: https://mail.google.com/mail?extsrc=sync&client=docs&plid=ACUX6DMFQY8PjCdtSoVoFrJ_mho5bWrodgdct1U
A17: 46042.584 | B17: 3479 | C17: 9821 | D17: FINISHED | E17: INRAD | F17: Linac-201172 | G17: Se reemplazó Thyratron, por estar esta en préstamo. Se realiza acondicionamiento. Se realiza QA por físico, con resultados satisfactorios. | H17: https://mail.google.com/mail?extsrc=sync&client=docs&plid=ACUX6DOgQJKFITh2prbntKvElDBwMjsFAO-etvA
A18: 46041.536 | B18: 3477 | C18: Tarea Sin Ticket | D18: FINISHED | E18: UC CHRISTUS - CECA | F18: Linac-109374 | G18: se realiza MP linac | H18: https://mail.google.com/mail?extsrc=sync&client=docs&plid=ACUX6DOcTRB-3hroNs8wv9wO7ETTJEdQQDdQ5to
A19: 46043.356 | B19: 3476 | C19: Tarea Sin Ticket | D19: FINISHED | E19: UC CHRISTUS - CECA | F19: Linac-109374 | G19: Asistencia remota por Dose Rate Mon | H19: https://mail.google.com/mail?extsrc=sync&client=docs&plid=ACUX6DOt0HoW-8xzZBxfy_Skk05e2VQCcDg-UIQ
A20: 46041.459 | B20: 3475 | C20: Tarea Sin Ticket | D20: FINISHED | E20: CLINICA ALEMANA DE SANTIAGO | F20: Linac-152171 | G20: Se asiste al sitio para brindar apoyo en la puesta en marcha del equipo. FM realiza controles de QA en horario AM de forma normal. Posteriormente, al volver a revisar el equipo, este se encontraba fuera de servicio debido a un inhibit de "Water Temp", asociada directamente a un problema en el chiller, el cual estaba siendo revisado al momento de la falla. Tras unos minutos, el equipo recupera su funcionamiento normal y se da inicio al tratamiento de pacientes. | H20: https://mail.google.com/mail?extsrc=sync&client=docs&plid=ACUX6DPul1hdND3DzLpwkKc7xk7koSXGDk6zg2k
A21: 46041.356 | B21: 3474 | C21: Tarea Sin Ticket | D21: FINISHED | E21: HOSPITAL CARLOS VAN BUREN (SSVSA) | F21: Linac-154325 | G21: Se efectua chequeo de equipo en conjunto de en conjunto de Fisico Medico, conforme | H21: https://mail.google.com/mail?extsrc=sync&client=docs&plid=ACUX6DPrSOhb6XTBZnu0tSFMMEwvWL1QQnxSIJY
A22: 46041.622 | B22: 3473 | C22: 9816 | D22: FINISHED | E22: Instituto Nacional del Cáncer (INC) | F22: N/A | G22: se realiza inspeccion del sistema xvi por lo reportado por el cliente, al llegar el sistema xvi arroja error 40, se verifica en el manual tecnico de servicio el error y se realiza la investigacion correspondiente del caso, despues de un analisis y seguimiento de falla se logra observar que la tarjeta de control del generador se encontraba dañada, ese corto en la tarjeta tambien ocaciono daño en el filamento del tubo razon por la cual se realizo el cambio, durante el cambio del tubo de Rx se pudo observar una fisura en el cable de HT del catodo del tubo de Rx y por precaucion se realiza el cambio de los cables de HT del tubo de Rx. | H22: https://mail.google.com/mail?extsrc=sync&client=docs&plid=ACUX6DMGooRmPx_q4KtKBevTkiup70hIbVImp2o
A23: 46038.909 | B23: 3472 | C23: 9754 | D23: FINISHED | E23: HOSPITAL CARLOS VAN BUREN (SSVSA) | F23: N/A | G23: traslado de repuesto linac, mantenimiento, cambio de ups y cambio de disco a rtp99. | H23: https://mail.google.com/mail?extsrc=sync&client=docs&plid=ACUX6DO7dmoQHZA0SQU17x8AdbgMzTnzPenCs6o
A24: 46041.361 | B24: 3471 | C24: Tarea Sin Ticket | D24: FINISHED | E24: HOSPITAL CARLOS VAN BUREN (SSVSA) | F24: Linac-154325 | G24: Cambio de GUN | H24: https://mail.google.com/mail?extsrc=sync&client=docs&plid=ACUX6DP2QIe5dj1h1CN3UYsa6cHseXWg-uhqM7s
A25: 46039.644 | B25: 3470 | C25: Tarea Sin Ticket | D25: FINISHED | E25: UC CHRISTUS - CECA | F25: Linac-109374 | G25: MP XVI y iviewGT Se asiste el dia sabado para recalibracion del sistema XVI, se veriica junto a FM y realizando sus pruebas con resultados satisfactorios. | H25: https://mail.google.com/mail?extsrc=sync&client=docs&plid=ACUX6DNn4y35wrRxU1TupT7VImt_RxZNcsghMd0
A26: 46039.644 | B26: 3469 | C26: Tarea Sin Ticket | D26: FINISHED | E26: UC CHRISTUS - CECA | F26: Linac-109374 | G26: Se realiza MP Linac | H26: https://mail.google.com/mail?extsrc=sync&client=docs&plid=ACUX6DMWkHX0jx07TZSnGGOX4sW5MJA-TQGiydY
A27: 46041.361 | B27: 3467 | C27: Tarea Sin Ticket | D27: FINISHED | E27: HOSPITAL CARLOS VAN BUREN (SSVSA) | F27: Linac-154325 | G27: Mantenimiento Preventivo | H27: https://mail.google.com/mail?extsrc=sync&client=docs&plid=ACUX6DOg4lj4ggiQ_ySUjJRNw1jQQgZqo0W-C-I
A28: 46037.847 | B28: 3464 | C28: 9813 | D28: FINISHED | E28: Instituto Nacional del Cáncer (INC) | F28: INC-156473 | G28: Se asiste a sitio por inhibit Gantry stop, una vez entregado el equipo se efectuan pruebas notando perdida de fuerza en sentido de giro CCW, se revisa ajuste de correas y tension, lo cual se corrije, se verifica gearbox con nivel y se ajusta. Se realizan pruebas con resultados satisfactorios, se entrega equipo a FM el cual realiza sus pruebas correspondientes con resultados ok | H28: https://mail.google.com/mail?extsrc=sync&client=docs&plid=ACUX6DMcRfWLHPslhWTseuvSutsuT-O3rYLplG4
A29: 46036.763 | B29: 3463 | C29: 9810 | D29: FINISHED | E29: CLÍNICA SANATORIO ALEMÁN (ONCORAD) | F29: Linac-201110 | G29: FALLA REVERSE CURRENT EQUIPO COMPACT | H29: https://mail.google.com/mail?extsrc=sync&client=docs&plid=ACUX6DPT0Mfz29PCO4VJ1SRBJwr7qJ0mej0Eaew
A30: 46037.449 | B30: 3462 | C30: 9806 | D30: FINISHED | E30: UC CHRISTUS - SCA | F30: Linac-109256 | G30: Calibración Exapod y Limpieza Agility | H30: https://mail.google.com/mail?extsrc=sync&client=docs&plid=ACUX6DMCvouHBjyCM36_7UNK8KGM2KXeJerlRIM
A31: 46034.44 | B31: 3461 | C31: Tarea Sin Ticket | D31: FINISHED | E31: CLÍNICA SANATORIO ALEMÁN (ONCORAD) | F31: N/A | G31: Eliminación de Usuarios Equipo Compact | H31: https://mail.google.com/mail?extsrc=sync&client=docs&plid=ACUX6DPBIrgjXKBE1Xjdpa2e2dGLZRNdXsPCQWc
A32: 46034.378 | B32: 3460 | C32: Tarea Sin Ticket | D32: FINISHED | E32: CLINICA ALEMANA DE SANTIAGO | F32: Linac-152171 | G32: se acompaña a FM en puesta en marcha estando todo ok en el equipo, ademas, se realizan pruebas diarias estando todo ok | H32: https://mail.google.com/mail?extsrc=sync&client=docs&plid=ACUX6DMkgyhadZUSGnk1_j_miSoaHrYPtpP232U
A33: 46030.823 | B33: 3459 | C33: 9801 | D33: FINISHED | E33: Instituto Nacional del Cáncer (INC) | F33: N/A | G33: se realiza verificacion de los motores pancake, se logra observar que las correas de los motores se encuentran un poco floja, se realiza el ajuste y tension de la correa, se realiza un learning del sitema de posicionamiento y se realiza pruebas de tratamientos VMAT en modo servicio | H33: https://mail.google.com/mail?extsrc=sync&client=docs&plid=ACUX6DN3IAkvAuJWE0qp5uO0D-Com7vtUFHRGQk
A34: 46030.734 | B34: 3458 | C34: 9790 | D34: FINISHED | E34: CLÍNICA SANATORIO ALEMÁN (ONCORAD) | F34: Linac-201110 | G34: Ajuste Telemetro Equipo Compact | H34: https://mail.google.com/mail?extsrc=sync&client=docs&plid=ACUX6DMp9Et7b6gjfaV5STHEQwbXKT4oWJqY7Kg
A35: 46029.48 | B35: 3457 | C35: Tarea Sin Ticket | D35: FINISHED | E35: HOSPITAL CARLOS VAN BUREN (SSVSA) | F35: Linac-154325 | G35: Se efectua Optimizacion de energía 6FFF , vía remota, posteriormente FM efectua control dosimetrico con resultados conforme. | H35: https://mail.google.com/mail?extsrc=sync&client=docs&plid=ACUX6DN6m8WMAr-VmJm444cVDRv95aEW2Nf1M-Q
A36: 46029.631 | B36: 3456 | C36: 9694 | D36: FINISHED | E36: CLINICA ALEMANA DE SANTIAGO | F36: N/A | G36: se realiza el cambio del cable XVI del versa norte ya que presentaba fallas de reconstruccion cuando se realizaba un cbct,la falla se debia a uncabke cortado el cual fue sustituido por uno nuevo. | H36: https://mail.google.com/mail?extsrc=sync&client=docs&plid=ACUX6DMiDny5GVJMqs1IZbDUgtRwZ14fpZ6BblQ
A37: 46027.745 | B37: 3455 | C37: 9793 | D37: FINISHED | E37: CLÍNICA SANATORIO ALEMÁN (ONCORAD) | F37: Linac-201110 | G37: Revisión conexión Cámara Iview Compact | H37: https://mail.google.com/mail?extsrc=sync&client=docs&plid=ACUX6DP3-0uF3xKbsV4zByxTNwl-OrFdaR7JXPs
A38: 46029.479 | B38: 3454 | C38: 9789 | D38: FINISHED | E38: CLINICA ALEMANA DE SANTIAGO | F38: Linac-152171 | G38: Se realizó cambio de 8 fuentes de poder de los KVM del TCS por corto circuito | H38: https://mail.google.com/mail?extsrc=sync&client=docs&plid=ACUX6DOR_V3v2vu7SXc4FwRr_eGfWtozCglpoOo
A39: 46027.518 | B39: 3453 | C39: 9781 | D39: FINISHED | E39: INRAD | F39: N/A | G39: Se realiza el cambio de Thyratron. Thyratron usado (Oncorad). Se realiza ajustes de frecuencias ok. Se efectúa QA conforme. | H39: https://mail.google.com/mail?extsrc=sync&client=docs&plid=ACUX6DMJWJDVqkgv3UvnN-c1Qz1_gFeqvvowAOA
A40: 46027.417 | B40: 3452 | C40: 9790 | D40: FINISHED | E40: CLÍNICA SANATORIO ALEMÁN (ONCORAD) | F40: Linac-201110 | G40: Cambio de Ampolleta Telemetro Compact | H40: https://mail.google.com/mail?extsrc=sync&client=docs&plid=ACUX6DPLLvYEnXE-bSV6fEQQF9K8McPqwCfDVjs
A41: 46024.988 | B41: 3451 | C41: 9778 | D41: FINISHED | E41: Instituto Nacional del Cáncer (INC) | F41: INC-156473 | G41: Se asiste al sitio en la fecha y hora previamente acordadas para realizar el cambio del motor pancake, debido a la activación recurrente del inhibit gantry stop y al ruido anómalo que presentaba. El reemplazo se realiza de manera satisfactoria y se llevan a cabo las pruebas de funcionamiento correspondientes, verificando la correcta operación del sistema. | H41: https://mail.google.com/mail?extsrc=sync&client=docs&plid=ACUX6DO4nkHxJQ12k7C0sA70q-6oRicKHQYPiY4
A42: 46024.646 | B42: 3450 | C42: Tarea Sin Ticket | D42: FINISHED | E42: FUNDACION ARTURO LOPEZ PEREZ | F42: APOTECA-CHEMO | G42: Se realizó ajuste de cierre puerta derecha Robot Apoteca Chemo. Se realuzó cambio de soporte jeringa 50ml roto sector numero 2 del carrusel. | H42: https://mail.google.com/mail?extsrc=sync&client=docs&plid=ACUX6DNsXMMB_Q0_pCoQcfX3JOcrbWAgqKYaT_4
A43: 46024.434 | B43: 3449 | C43: 9778 | D43: FINISHED | E43: Instituto Nacional del Cáncer (INC) | F43: INC-156473 | G43: se realiza la sustitucion de los motores pancake ya que uno de ellos se encontraba quemado y sin movimiento, el otro motor al queda expuesto a trabajar solo se considera el desgaste por lo que se requiere el cambio lo mas rapido posible para evitar que se dañe el otro motor pancake nuevo, para realizar el cambio se requiere tiempo de maquina | H43: https://mail.google.com/mail?extsrc=sync&client=docs&plid=ACUX6DPS4mWTzOJSz0m0sz-Lu4u7upncsueGxqQ
A44: 46022.474 | B44: 3448 | C44: 9781 | D44: FINISHED | E44: INRAD | F44: Linac-201172 | G44: Se realizó visita a sitio para verificar problemas de baja tasa de dosis en los canales A y B. Durante la intervención se efectuaron mediciones del thyratron, las cuales arrojaron valores elevados que indican la necesidad de su reemplazo. | H44: https://mail.google.com/mail?extsrc=sync&client=docs&plid=ACUX6DNHvQM4xI_cOCY-NjiuGydVGhLUWkBiY38
A45: 46020.918 | B45: 3447 | C45: 9781 | D45: FINISHED | E45: INRAD | F45: N/A | G45: Vía telefónica se asiste, ajustando parámetro de la PRF de 200 MU, logrando anular interlock de baja tasa. Físico efectúa QA conforme. | H45: https://mail.google.com/mail?extsrc=sync&client=docs&plid=ACUX6DOuuOPHR9kI5M9Ljtz4IFzL2xvn1H-t-FM
A46: 46020.444 | B46: 3446 | C46: Tarea Sin Ticket | D46: FINISHED | E46: CLINICA ALEMANA DE SANTIAGO | F46: Linac-152171 | G46: se asiste al bunker a realizar el acopañamiento del inicio del linac, se realiza el inicio de la maquina y se observa una mala comunicacion con el central backup sistem el cual se debe coordinar para reañizar verificacion con tiempo de maquina, se coordinara para realizar dicha maniobra. | H46: https://mail.google.com/mail?extsrc=sync&client=docs&plid=ACUX6DN0TyRfCa0oXAaj_IGUlpk1gFDwQbYVdV0
A47: 46020.361 | B47: 3444 | C47: 9731 | D47: FINISHED | E47: CLINICA ALEMANA DE SANTIAGO | F47: Linac-152171 | G47: se realiza verificacion de la falla, se realiza la calibracion del movimiento longitudinal del panel, se realiza calibracion del movimiento de posicion S, M, L, se verifica la tension y se realiza ajuste para que el movimiento sea fluido, se realizan pruebas pero sigue apareciendo la misma intermitencia de la falla. | H47: https://mail.google.com/mail?extsrc=sync&client=docs&plid=ACUX6DNBve0-uhnVAcQ6ujl2ypCeqshOuW05pn4
A48: 46017.517 | B48: 3443 | C48: 9690 | D48: FINISHED | E48: UC CHRISTUS - CECA | F48: Linac-153935 | G48: se realiza optimizacion de la energia de 15 MeV por presentar 2T | H48: https://mail.google.com/mail?extsrc=sync&client=docs&plid=ACUX6DNWPuHMgPZoEFSKelmeoqhCMtkN4bRxh6Q
A49: 46017.513 | B49: 3442 | C49: 9775 | D49: FINISHED | E49: UC CHRISTUS - CECA | F49: Linac-109374 | G49: se realiza optimizacion de la energia de 6MeV por presentar dose rate mon, se realiza optimizacion de energia de 6 MV por presentar 2R , se realiza el back up de los datos de linac ya que en la partida en las mañanas apatece problemas de back up. | H49: https://mail.google.com/mail?extsrc=sync&client=docs&plid=ACUX6DN_ikwBuRrmCShsryNk11jA9uBg_BGHO5o
A50: 46020.367 | B50: 3441 | C50: 9774 | D50: FINISHED | E50: Instituto Nacional del Cáncer (INC) | F50: INC-156473 | G50: Verificación del estado del Gantry | H50: https://mail.google.com/mail?extsrc=sync&client=docs&plid=ACUX6DOZfRg6YIKqp6GmTHYAI3EPc5FzdZnCehM
A51: 46013.453 | B51: 3439 | C51: Tarea Sin Ticket | D51: FINISHED | E51: CLINICA ALEMANA DE SANTIAGO | F51: Linac-152171 | G51: Se realiza acompañamiento y verificación de parámetros de funcionamiento durante tratamientos AM para asistir en caso que se presente algún contratiempo en la jornada de tratamiento de pacientes. El equipo funcionando con normalidad en tratamiento y parámetros dentro de rango: Water Press: 10 PSI Temperature: 28°C Sf6 Press: 0.75 Bar | H51: https://mail.google.com/mail?extsrc=sync&client=docs&plid=ACUX6DMZoFpVpzagdxKtU4db5FD3ZSPnQrN3S1g
A52: 46010.641 | B52: 3438 | C52: 9764 | D52: FINISHED | E52: CLÍNICA LAS CONDES | F52: CLC-1 | G52: se realiza visita de inspeccion para verificar lo reportado, presencia de agua en la sala de maquina y multiples interlot del linac, se realiza la verificacion del sistema y se consigue un conector en el intercambiador por donde se fugaba el agua, se realiza apriete correspondiente para eliminar la fuga y poder solucionar, se realiza inspeccion de la zona donde se encontro la fuga y se procedio a realizar limpieza y secado del transformado principal de la LVPSU, secado de toda la parte trasera del gantry, comprobacion del sistema de alimentacion, se pudo observar que las ruedas del gantry al mojarse presentaban oxidacion por la combinacion de grasa y agua, se realiza limpieza y lubricacion de las ruedas del gantry. | H52: https://mail.google.com/mail?extsrc=sync&client=docs&plid=ACUX6DM2AdFiG_1rDBLaMrvdGIefJQJUPV-zV-Y
A53: 46009.488 | B53: 3437 | C53: Tarea Sin Ticket | D53: FINISHED | E53: CLÍNICA LAS CONDES | F53: CLC-2 | G53: se realiza calibracion de los flexmap, fisica medica ajusta los laseres, se realiza calibracion de la hexapod con fantoma MIMI, se verifica posicion de laser con crosswire, se realiza controles de pruebas en movimiento, se verifica el funcionamiemto del telemetro del linac. | H53: https://mail.google.com/mail?extsrc=sync&client=docs&plid=ACUX6DMGhzyuXEhEeJ0ZzrmkBJIRGvvft-R0e5Q
A54: 46008.6 | B54: 3436 | C54: 9758 | D54: FINISHED | E54: CLÍNICA SANATORIO ALEMÁN (ONCORAD) | F54: Linac-201110 | G54: Cambio de Carbones motor Z Camilla Compact | H54: https://mail.google.com/mail?extsrc=sync&client=docs&plid=ACUX6DNeHM2YR79xDFikrWt7w-Z05IPhi9yzzr4
A55: 46006.705 | B55: 3435 | C55: Tarea Sin Ticket | D55: FINISHED | E55: CLINICA ALEMANA DE SANTIAGO | F55: Linac-152171 | G55: Se asiste a puesta en marcha edtando todo ok | H55: https://mail.google.com/mail?extsrc=sync&client=docs&plid=ACUX6DOsknwDwNNdyxFlI8fidfOs3j2A2ef9AT8
A56: 46007.431 | B56: 3434 | C56: 9753 | D56: FINISHED | E56: CLÍNICA LAS CONDES | F56: CLC-1 | G56: se asiste al equipo para verificar y corregir la falla reportada por la posicion de la MLC la cual pierde la referencia de los reflecores de posicion, se realiza la investigacion encontrandose los valores preestablecidos estaban fuera de lugar, se realiza la correccion de valores de los reflectores de referencia y se realiza la calibracion completa del agility, la cual pudo corregir los valores establecidos dejando todo en tolerancia, se realiza la verificacion e inspeccion del movimiento vertical de la mesa de tratamiento encontrandose un pendal de la camilla con cierta falla en uno de sus potenciometros lo cual se requiere un cambio de la pieza ya que la que posee presenta desgaste, se enviara cotizacion para su aprobacion previa y luego se agendara para proceder a su sustitucion, se realiza verificacion visual de los tamaños de campos y se realizan ajustes (optimizacion) de las energias de fotones y electrones. | H56: https://mail.google.com/mail?extsrc=sync&client=docs&plid=ACUX6DOy1-uGM_AFadNEm9Xn0N22xrbdT9jOdwE
A57: 46006.532 | B57: 3433 | C57: Tarea Sin Ticket | D57: FINISHED | E57: CLÍNICA SANATORIO ALEMÁN (ONCORAD) | F57: Linac-201110 | G57: Ajuste engranaje de motor del BLD Compact | H57: https://mail.google.com/mail?extsrc=sync&client=docs&plid=ACUX6DOknW-binimK9oMRe41u6vsOKyeJSSfSxE
A58: 46003.575 | B58: 3431 | C58: 9749 | D58: FINISHED | E58: HOSPITAL CARLOS VAN BUREN (SSVSA) | F58: N/A | G58: Recibido el llamado se procedió a efectuar ajuste de tasa vía remota, de energía 6 FFF, conforme, se mantendrá en observación durante el día. | H58: https://mail.google.com/mail?extsrc=sync&client=docs&plid=ACUX6DNyt99Sp19ov98jhCnj8H_RdwB-BOkB_uQ
A59: 46003.535 | B59: 3430 | C59: Tarea Sin Ticket | D59: FINISHED | E59: FUNDACION ARTURO LOPEZ PEREZ | F59: APOTECA-CHEMO | G59: Se realizó el Mantenimiento Semestral del robot Apoteca Chemo. Actividades: *Ajuste y limpieza de sector de carga, sector de preparación. *Ajuste y limpieza de puertas de sector de carga y preparación. *Revisíon de funcionamiento sensores de seguridad, capacitivos y laser. *revisión y ajuste de brazo de robot. *revisión y ajuste de sector de dosificación. *revisión, ajuste y limpieza de estacionamientos de viales. *revisión y calibración de sensores laser altura de viales. *revisión y limpieza sector de contenedor de desechos. *Revisión y ajuste de Clamps Viaflex. (7) uno con detalles. *Revisión de lamparas UV (Cambio en Mtto. Anual. *Revisión de Voltaje en L1/L2/L3, sin novedad. *Revisión, ajuste y limpieza de puertas frontales, sector de carga y preparación. *Limpieza de rejillas superiores sector de preparación. *Limpieza sector de balanza. *Revisión de presión robot (Estable) *Revisión y limpieza de impresoras. *Revisión de lectores códigos de barras, pistola y lector interno. | H59: https://mail.google.com/mail?extsrc=sync&client=docs&plid=ACUX6DO507lAldc5EApYq32MXY3-9Q1iaX67pi8
A60: 46003.65 | B60: 3429 | C60: 9734 | D60: FINISHED | E60: SERVICIO DE SALUD DE MAGALLANES | F60: Linac-109452 | G60: Se asiste a sitio para realizar pruebas de Botones de emergencia del Acelerador, solicitado por cliente. | H60: https://mail.google.com/mail?extsrc=sync&client=docs&plid=ACUX6DMVObgL_GoXqwN_xiU0xkvZ9_fYsuPcHQs
A61: 46003.65 | B61: 3428 | C61: 9746 | D61: FINISHED | E61: SERVICIO DE SALUD DE MAGALLANES | F61: Linac-109452 | G61: Se asiste a sitio para realizar apriete del User Interface del lado A de la camilla, quedando resuelto y funcionando correctamente control. | H61: https://mail.google.com/mail?extsrc=sync&client=docs&plid=ACUX6DNTh-Wo3Pu7jbFcBEuGfi-MJZiDUlWIlIc
A62: 46003.405 | B62: 3427 | C62: 938 | D62: FINISHED | E62: RADIO ONCOLOGÍA DEL SUR | F62: Linac-156187 | G62: Cambio PCB Leaf Motor Drive | H62: https://mail.google.com/mail?extsrc=sync&client=docs&plid=ACUX6DOn9SMTgKiJ0DoLq7pGQFf9kTO3lr_OPbc
A63: 46002.44 | B63: 3426 | C63: Tarea Sin Ticket | D63: FINISHED | E63: FUNDACION ARTURO LOPEZ PEREZ | F63: N/A | G63: Se realizó toma de datos viales: *PEMGEM 500mg (Dr. Reddy's) *Varitrinox 10mg (VARIFARMA) *Lippod 20 20mg (CELON LABS) | H63: https://mail.google.com/mail?extsrc=sync&client=docs&plid=ACUX6DN26AAsy8Z1jckNpGj7YU-CX6NgKY7SXn0
A64: 46007.504 | B64: 3425 | C64: 9706 | D64: FINISHED | E64: CLINICA ALEMANA DE SANTIAGO | F64: Linac-109496 | G64: Claibraciones y reinstalacion | H64: https://mail.google.com/mail?extsrc=sync&client=docs&plid=ACUX6DNfwO7QEP__Vwcbz2Y9-zFmV1JDiYzMJ5s
A65: 46001.658 | B65: 3424 | C65: Tarea Sin Ticket | D65: FINISHED | E65: FUNDACION ARTURO LOPEZ PEREZ | F65: N/A | G65: Se realizó instalación de Apoteca Manager y M@A en CPU oficina upo y CPU en oficina 1. | H65: https://mail.google.com/mail?extsrc=sync&client=docs&plid=ACUX6DNnmVqKlFdU3LYAprxzuzngQiHjlyLZLo8
A66: 46001.416 | B66: 3423 | C66: 9723 | D66: FINISHED | E66: UC CHRISTUS - CECA | F66: Linac-109374 | G66: se realiza inspeccion del sistema mlc en el cual se verifica que las laminas par no poseen movimiento, se verifica las tarjetas LMD y se encuentra con una tarjeta dañada | H66: https://mail.google.com/mail?extsrc=sync&client=docs&plid=ACUX6DPxHrh041OFIepycDbWjGpGQ6LlzVv0aGo
A67: 46000.754 | B67: 3422 | C67: 9737 | D67: FINISHED | E67: UC CHRISTUS - SCA | F67: Linac-109256 | G67: se asiste a verificar lo reportado y no se inicia en equipo quedando en no inicializado y no se puede realizar los tratamientos en los pacientes, al verificar la cadena de alimentacion y control de equipo, midiendo voltaje y verificando funcionamiento, se pudo encontrar un boton de emergencia activado. | H67: https://mail.google.com/mail?extsrc=sync&client=docs&plid=ACUX6DPeczGsMTcytFmV056mais40tJtCYRJprg
A68: 45996.752 | B68: 3421 | C68: 9726 | D68: FINISHED | E68: RADIO ONCOLOGÍA DEL SUR | F68: Linac-156187 | G68: OPTIMIZACION GUN EQUIPO INFINITY | H68: https://mail.google.com/mail?extsrc=sync&client=docs&plid=ACUX6DOh1-j3ShEdtKXf_hJ25Bzh8O8zW6SxMAk
A69: 46000.545 | B69: 3420 | C69: Tarea Sin Ticket | D69: FINISHED | E69: Instituto Nacional del Cáncer (INC) | F69: INC-156473 | G69: Reemplazo de partes preventivamente | H69: https://mail.google.com/mail?extsrc=sync&client=docs&plid=ACUX6DMf0imOX7Y6cBDxNov7lcfh4CGwW08ptXs
A70: 45996.619 | B70: 3419 | C70: 9592 | D70: FINISHED | E70: SERVICIO DE SALUD DE MAGALLANES | F70: Linac-109452 | G70: Se asiste a sitio para realizar el cambio del conjunto completo del eje longitudinal que produce presencia de interlock Table Long. posteriormente al cambio se realizan pruebas de stress, calibraciones y aprendizajes de la mesa, quedando operativo y funcionando correctamente. | H70: https://mail.google.com/mail?extsrc=sync&client=docs&plid=ACUX6DN1R8cehm8wwvPq4xsD_XNTPApJX8qgR00
A71: 45997.605 | B71: 3418 | C71: Tarea Sin Ticket | D71: FINISHED | E71: Instituto Nacional del Cáncer (INC) | F71: INC-156473 | G71: mantencion preventiva del linac | H71: https://mail.google.com/mail?extsrc=sync&client=docs&plid=ACUX6DNHS4QxcM2d-9KhQV3mSmFuYGuPHZF0KGs
A72: 45995.734 | B72: 3417 | C72: 0 | D72: FINISHED | E72: FUNDACION ARTURO LOPEZ PEREZ | F72: HDR-FT07026 | G72: mantención preventiva anual equipo de braquiterapia Flexitron | H72: https://mail.google.com/mail?extsrc=sync&client=docs&plid=ACUX6DPxqUBGVaMwSpqYSfjiALoLVBQhe5MmyhI
A73: 45995.417 | B73: 3416 | C73: 9722 | D73: FINISHED | E73: UC CHRISTUS - SCA | F73: Linac-109256 | G73: Se asiste de forma remota para poder optimizar y ajustar energias 6 MV y 6 FFF, se realizan ajustes corredpondientes junto a FM con resultados ok y se entrega en equipo. FM realiza pruebas con resultados satisfactorios. | H73: https://mail.google.com/mail?extsrc=sync&client=docs&plid=ACUX6DNUmTFWgwJR2G7G3utO6746m2u5WabNWs4
A74: 45995.438 | B74: 3415 | C74: 9723 | D74: FINISHED | E74: UC CHRISTUS - CECA | F74: Linac-109374 | G74: Se asiste al sitio para verificar el problema de conformación de campos. Al llegar, se observa el interlock “... Serial Comms”, indicando posibles intermitencias en las conexiones seriales. Se realiza el reajuste correspondiente y se verifica la intensidad de luz de los reflectores, constatando que todo se encuentra dentro de los parámetros. Finalmente, se ejecutan pruebas de ciclaje para comprobar el movimiento, sin detectarse anomalías. | H74: https://mail.google.com/mail?extsrc=sync&client=docs&plid=ACUX6DM5nx2PHwzEmgIJjH00dI5eGYfXLDsEtAU
A75: 45994.834 | B75: 3414 | C75: 9720 | D75: FINISHED | E75: CLÍNICA SANATORIO ALEMÁN (ONCORAD) | F75: Linac-201110 | G75: OPTIMIZACION OPTICA MLC2 | H75: https://mail.google.com/mail?extsrc=sync&client=docs&plid=ACUX6DOQgeyIerWhIoDLcJ0vkDjSjgHPjSDQQLg
A76: 45994.673 | B76: 3413 | C76: 9712 | D76: FINISHED | E76: UC CHRISTUS - SCA | F76: N/A | G76: se revisa configuracion de impresora zebra instalada por TI de UC Chritus, detectando un exceso de oscuridad en configuracion de impresora. parametro oscuridad se observa en 27, se realizan pruebas disminuyendo hasta 13 puntos oscuridad. hecho esto pistola de codigo de barra lee sin problemas a los pacientes | H76: https://mail.google.com/mail?extsrc=sync&client=docs&plid=ACUX6DPH4SnBaE1sWpOzBnjwkLW9tGSSyTwK9Vo
A77: 45996.691 | B77: 3411 | C77: Tarea Sin Ticket | D77: FINISHED | E77: CLINICA ALEMANA DE SANTIAGO | F77: Linac-152171 | H77: https://mail.google.com/mail?extsrc=sync&client=docs&plid=ACUX6DNO7HaefuIlBMwu2AZjqTF6AQpB0_f8PK4
A78: 46050.411 | B78: 3478 | C78: Tarea Sin Ticket | D78: FINISHED | E78: CLÍNICA LAS CONDES | F78: CLC-1 | G78: mantencion preventiva a versa hd CLC1 (9166) | H78: https://mail.google.com/mail?extsrc=sync&client=docs&plid=ACUX6DPqFbuGwxPxDrUqCKF0nTEVzDAs4EBQddQ
A79: 46050.411 | B79: 3494 | C79: Tarea Sin Ticket | D79: FINISHED | E79: CLÍNICA LAS CONDES | F79: CLC-2 | G79: se realiza mantencion del acelerador lineal Versa HD CLC2 | H79: https://mail.google.com/mail?extsrc=sync&client=docs&plid=ACUX6DNGnd9z4Mp0heYc9rmKh9Rq86-SgwHAEwU
A80: 46050.38 | B80: 3497 | C80: 9731 | D80: FINISHED | E80: CLINICA ALEMANA DE SANTIAGO | F80: Linac-152171 | G80: Se asiste a sitio para reemplazar el cable del movimiento longitudinal (PL9), para solventar el problema de detencion aleatoria del panel y mala retraccion del mismo, ademas, se volvio a calibrar las posiciones mecanicas del panel tanto longitudinal y lateralmente, a pesar de todo esto mencionado persiste la intermitencia del movimiento longitudinal tanto para retraer y extender el panel. | H80: https://mail.google.com/mail?extsrc=sync&client=docs&plid=ACUX6DMwY2PLAUyaKRjtx5Y43eAb4EmTP45JiOo
A81: 46050.909 | B81: 3499 | C81: 9852 | D81: FINISHED | E81: UC CHRISTUS - SCA | F81: N/A | G81: Se asiste a sitio por problemas en lamina 38 Y2, se reemplaza motor, nuez y tornillo y se realiza limpieza y lubricacion de la lamina , se realiza prueba de paciente en servicio estando todo ok, se entrega a FM la cual realiza pruebas con resultados satisfactorios. | H81: https://mail.google.com/mail?extsrc=sync&client=docs&plid=ACUX6DMTXy7makagMSk3_LGQOhiJNGQ1HPfMtBw
A82: 46050.908 | B82: 3500 | C82: 9851 | D82: FINISHED | E82: HOSPITAL CARLOS VAN BUREN (SSVSA) | F82: Linac-154325 | G82: se efectua diagnostico inicial, en donde se detecto lamina 37 se desprendió el rubi, por lo que se efectuo plan de reemplazo de ruby. Posteriormente se efectuo pruebas de ciclaje y de un VMAT con pacientes grabados a servicio con resultados satisfactorios, se informa vía wsp de los resultados a FM Isabella liedtke. | H82: https://mail.google.com/mail?extsrc=sync&client=docs&plid=ACUX6DMAGHGC8hQM49L7DiSPoKnreMWYpjzWZ1E
A83: 46051.659 | B83: 3505 | C83: 9855 | D83: FINISHED | E83: INRAD | F83: N/A | G83: se reinicia conexion entre xio a iview logrando exportar paciente correctamente | H83: https://mail.google.com/mail?extsrc=sync&client=docs&plid=ACUX6DP6AcZb1Hs-5pbxx9KzzXQdXsS710-_zKc
A84: 46051.612 | B84: 3503 | C84: 9858 | D84: FINISHED | E84: INRAD | F84: Linac-201172 | G84: Problemas con Touchgard | H84: https://mail.google.com/mail?extsrc=sync&client=docs&plid=ACUX6DMohW02KefFWV0lJqhE6cMBuVJXAbDFB4s
A85: 46051.597 | B85: 3504 | C85: Tarea Sin Ticket | D85: FINISHED | E85: SERVICIO DE SALUD DE MAGALLANES | F85: TPS-HCM, OIS-HCM | H85: https://mail.google.com/mail?extsrc=sync&client=docs&plid=ACUX6DP_DNRbEwyNgh_7dJBAezQuLx1FNmm5TdE
A86: 46051.584 | B86: 3501 | C86: Tarea Sin Ticket | D86: FINISHED | E86: INSTITUTO DE SALUD PUBLICA (ISP) | F86: PANASONIC-ISP | G86: Se asiste al Instituto de Salud Pública de Chile (ISP) para la ejecución de mantenimiento preventivo a equipo marca Panasonic, modelo UD-716. Se realiza desarme parcial del equipo, limpieza general y verificación de componentes electrónicos internos. Asimismo, se efectúan mediciones de voltajes de entrada y salida, encontrándose dentro de los rangos establecidos por el fabricante. Posteriormente, se realizan pruebas funcionales para verificar el correcto funcionamiento del equipo, sin detectarse anomalías. Equipo se mantiene operativo y conforme. | H86: https://mail.google.com/mail?extsrc=sync&client=docs&plid=ACUX6DOeexs2AJ2VS7I9LgEENYX866rBaTYHhEo
A87: 46051.515 | B87: 3489 | C87: Tarea Sin Ticket | D87: FINISHED | E87: CLINICA ALEMANA DE SANTIAGO | F87: Linac-152171 | H87: https://mail.google.com/mail?extsrc=sync&client=docs&plid=ACUX6DPtrHNBmddWYsYQrQMtkRkT2vQoptsJrvU
A88: 46051.392 | B88: 3502 | C88: 9854 | D88: FINISHED | E88: UC CHRISTUS - CECA | F88: N/A | G88: se reporta dose rate mon en energia de 6MV en el equipo infinity, se coordina asistencia presencial y remota, Jose Echeverria se conecta remotamente mirntras se asiste de manera presencial de mi parte, se realiza los ajustes cotrespondiente y se deja operativo el equipo | H88: https://mail.google.com/mail?extsrc=sync&client=docs&plid=ACUX6DP48jb5OYjvEr2aM1kORE6yOwpRT09ORK0
A89: 46052.528 | B89: 3506 | C89: 9429 | D89: FINISHED | E89: CLÍNICA SANATORIO ALEMÁN (ONCORAD) | F89: Linac-201110 | G89: Diafragma Y2 se mueve aleatoriamente, por gravedad, se manifiesta mayoritariamente con gantry 90 y 270, BLD 0. Se investiga la anomalía y se detecta la correa qué mueve el diafragma, con poca tensión por fatiga de esta por el uso. Se ajusta lo mejor posible, corrigiendo esta anomalía. | H89: https://mail.google.com/mail?extsrc=sync&client=docs&plid=ACUX6DPTXvPBsmH7X6kDte0nYQfbwyPlkYhLdqA
A90: 46052.871 | B90: 3507 | C90: 9859 | D90: FINISHED | E90: Instituto Nacional del Cáncer (INC) | F90: INC-156473 | G90: Revisión diagnóstico de MLC en conjunto con físico médico, para revisar los planes reportados y ver parámetros involucrados respecto a las tolerancias establecidas y configuradas en Mosaiq. Se copiaron planes a servicio, se realizó registro fotográfico para entregar en caso abierto con Elekta y queda en observación. Se realizó igualmente un ciclaje de láminas (x5). | H90: https://mail.google.com/mail?extsrc=sync&client=docs&plid=ACUX6DMUvlQc9tlaYfZSaeTr31xsNNorLbYkta4
A91: 46056.035 | B91: 3512 | C91: 9864 | D91: FINISHED | E91: CLINICA ALEMANA DE SANTIAGO | F91: Linac-152171 | G91: se revisa sequenciador del suragility por problema de inicialization ATM. se revisan configuraciones de controlador de red. puntos de control anteriores archivo impac de sequencer dominio sequencer | H91: https://mail.google.com/mail?extsrc=sync&client=docs&plid=ACUX6DOWSlmnm_XJKiy4DyEwyUOx1lj1T_MIEHo
A92: 46056.623 | B92: 3508 | C92: Tarea Sin Ticket | D92: FINISHED | E92: CLINICA ALEMANA DE SANTIAGO | F92: Linac-152171 | G92: Se asiste a sitio para realizar mantenimiento preventivo por calendario. | H92: https://mail.google.com/mail?extsrc=sync&client=docs&plid=ACUX6DM9pJCecVTFvdvSTQ8ENsfDUL5KaGlU6Q0
A93: 46056.623 | B93: 3513 | C93: 9865 | D93: FINISHED | E93: Instituto Nacional del Cáncer (INC) | F93: INC-156473 | G93: Se asiste a sitio para acompañar a Hans en la reparación del Chiller. Luego de verificar circuito interno, válvulas y presiones de agua se procede a reparar y verificar nuevamente el funcionamiento, encontrándose todo en orden. | H93: https://mail.google.com/mail?extsrc=sync&client=docs&plid=ACUX6DPIMT6TQ2urZG7Q6hcoLZt1J3K1-qnwa6g
A94: 46056.709 | B94: 3514 | C94: 9864 | D94: FINISHED | E94: CLINICA ALEMANA DE SANTIAGO | F94: N/A | G94: Elekta se conecta directamente al servidor mosaiq para tratar problema de caracterizacion de maquina. en paralelo se resuelve falla de deteccion de laminas en sequencer del suragility | H94: https://mail.google.com/mail?extsrc=sync&client=docs&plid=ACUX6DP-yCGH2dx4sWQEZa-BFO87WXKJGWkKd3w
A95: 46057.382 | B95: 3515 | C95: Tarea Sin Ticket | D95: FINISHED | E95: UC CHRISTUS - CECA | F95: Linac-109374 | G95: Se realiza cambio predictivo por peticion de elekta de bracket & fan en el banco Y2 | H95: https://mail.google.com/mail?extsrc=sync&client=docs&plid=ACUX6DMqbJgbXcgxrpMPVwEGAKkgO7vFLrTAI9Y
A96: 46057.518 | B96: 3511 | C96: Tarea Sin Ticket | D96: FINISHED | E96: CLINICA ALEMANA DE SANTIAGO | F96: Linac-152171 | H96: https://mail.google.com/mail?extsrc=sync&client=docs&plid=ACUX6DNxx4GJqao3PjkKTMLfFe3oV_RR3Xc8pqo
A97: 46057.518 | B97: 3510 | C97: Tarea Sin Ticket | D97: FINISHED | E97: CLINICA ALEMANA DE SANTIAGO | F97: Linac-152171 | G97: Mantenimiento preventivo Mesa Precise | H97: https://mail.google.com/mail?extsrc=sync&client=docs&plid=ACUX6DNRPxYMGbBtB-6iXQNRJygX75x8HEPH9a8
A98: 46057.598 | B98: 3516 | C98: 9862 | D98: FINISHED | E98: UC CHRISTUS - CECA | F98: Linac-109374 | G98: Cambio de Target Driver y Ion Pump | H98: https://mail.google.com/mail?extsrc=sync&client=docs&plid=ACUX6DOrOkZogwauey2HBXp97HLy6Y1qjUMFxTk
A99: 46059.789 | B99: 3517 | C99: Tarea Sin Ticket | D99: FINISHED | E99: Instituto Nacional del Cáncer (INC) | F99: INC-156473 | G99: Se realiza MP Linac | H99: https://mail.google.com/mail?extsrc=sync&client=docs&plid=ACUX6DNYAiWXoI9IkhsMnOBSHXXPm_BBp46Wt34
A100: 46059.759 | B100: 3518 | C100: 9496 | D100: FINISHED | E100: Instituto Nacional del Cáncer (INC) | F100: INC-156473 | G100: se realizan las siguientes tareas -cambio de ups de rack ccp por apagados automatico de integrity -limpieza de perifericos xvi e iview -respaldo mediante acronis (imagen de sistema) xvi e iview -chequeo de cables rack ccp -actualizacion de sistema citrix cmsda2 -limpieza servidores rack elekta -chequeo de cables rack elekta. -limpieza de monacosim ubicados en sala de dosimetria | H100: https://mail.google.com/mail?extsrc=sync&client=docs&plid=ACUX6DM-gHrej9QzMAhRUWIpIMttcYtSETgk7tE
...

Sheet DB_Tickets_Zendesk
A1: Ticket ID | B1: Asunto | C1: Estado | D1: Prioridad | E1: Tipo | F1: Creado (Fecha) | G1: Actualizado (Fecha) | H1: ID Organización | I1: ID Solicitante | J1: ID Técnico | K1: Tags | L1: Custom Fields (JSON Dump)
A2: 9821 | B2: solicitud cambio de thyratron | C2: pending | D2: urgent | E2: incident | F2: 46042.448 | G2: 46042.484 | H2: 14742026913435 | I2: 38368479928987 | K2: acelerador_lineal, braquiterapia, compact, elekta, hardware_y_software, monaco, monacosim, mosaiq, no, requerimiento, tcs, xio | L2: [{"id":22950764862363,"value":null},{"id":22951106310811,"value":"acelerador_lineal"},{"id":22986688179995,"value":"no"},{"id":23570126394907,"value":"requerimiento"},{"id":34267608050075,"value":"tcs"},{"id":39065204608155,"value":null},{"id":40011436329115,"value":"01K2MXCF9WW205P1YQ3PCD50A9"},{"id":43011722643739,"value":null},{"id":43806479792155,"value":null},{"id":43806495652507,"value":null}]
A3: 9817 | B3: Solicitud de conexión para el TRM | C3: pending | D3: low | E3: incident | F3: 46041.52 | G3: 46041.522 | H3: 14741543428379 | I3: 26132276827035 | J3: 14481448391451 | K3: elekta, hardware_y_software, hexapod, iview, linac, monaco, mosaiq, no, platform, requerimiento, suncheck, suncheck_machine, sunnuclear, tens, versahd, xvi | L3: [{"id":22950764862363,"value":null},{"id":22951106310811,"value":"suncheck"},{"id":22986688179995,"value":"no"},{"id":23570126394907,"value":"requerimiento"},{"id":34267608050075,"value":null},{"id":39065204608155,"value":null},{"id":40011436329115,"value":"01K2MWPZ0X0DMAW9P42PW6X6V4"},{"id":43011722643739,"value":null},{"id":43806479792155,"value":null},{"id":43806495652507,"value":null}]
A4: 9816 | B4: Falla del tubo de rayos X | C4: new | D4: urgent | E4: incident | F4: 46037.638 | G4: 46037.642 | H4: 14741593614363 | I4: 35062929091611 | K4: citrix, elekta, hardware_y_software, infinity, integrity, iview, linac, media, monaco, mosaiq, problema, si, storage, suncheck_machine, sunnuclear, xvi | L4: [{"id":22950764862363,"value":null},{"id":22951106310811,"value":"integrity"},{"id":22986688179995,"value":"si"},{"id":23570126394907,"value":"problema"},{"id":34267608050075,"value":null},{"id":39065204608155,"value":null},{"id":40011436329115,"value":"01K2MWR2KCZK72HY0ZV2CSMFTN"},{"id":43011722643739,"value":null},{"id":43806479792155,"value":null},{"id":43806495652507,"value":null}]
A5: 9812 | B5: Table long | C5: solved | D5: high | E5: incident | F5: 46036.584 | G5: 46037.668 | H5: 14741543428379 | I5: 26080982926747 | J5: 19579468718875 | K5: elekta, físico, hardware_y_software, hexapod, iview, linac, monaco, mosaiq, no, platform, problema, sistema_camilla_precise, suncheck_machine, sunnuclear, versahd, xvi | L5: [{"id":22950764862363,"value":null},{"id":22951106310811,"value":"sistema_camilla_precise"},{"id":22986688179995,"value":"no"},{"id":23570126394907,"value":"problema"},{"id":34267608050075,"value":null},{"id":39065204608155,"value":null},{"id":40011436329115,"value":"01K2MWPZ0X0DMAW9P42PW6X6V4"},{"id":43011722643739,"value":null},{"id":43806479792155,"value":null},{"id":43806495652507,"value":null}]
A6: 9811 | B6: Se solicita calibración de láseres de sala de equipo Versa | C6: new | D6: high | E6: incident | F6: 46036.544 | G6: 46036.544 | H6: 14741318546075 | I6: 36182421530907 | K6: agility, elekta, hardware_y_software, monaco, mosaiq, no, requerimiento, sinergy, suncheck, suncheck_machine, sunnuclear, supervisor_de_equipo_médicos, versahd | L6: [{"id":22950764862363,"value":null},{"id":22951106310811,"value":"suncheck"},{"id":22986688179995,"value":"no"},{"id":23570126394907,"value":"requerimiento"},{"id":34267608050075,"value":null},{"id":39065204608155,"value":null},{"id":40011436329115,"value":"01K2MWKNK7SBBFQAXJYFH5C7RR"},{"id":43011722643739,"value":null},{"id":43806479792155,"value":null},{"id":43806495652507,"value":null}]
A7: 9809 | B7: Panel iview | C7: open | D7: normal | E7: incident | F7: 46036.448 | G7: 46037.45 | H7: 14741543428379 | I7: 26080982926747 | K7: elekta, físico, hardware_y_software, hexapod, iview, linac, monaco, mosaiq, no, platform, problema, sistema_de_imagen_portal_iview, suncheck_machine, sunnuclear, versahd, xvi | L7: [{"id":22950764862363,"value":null},{"id":22951106310811,"value":"sistema_de_imagen_portal_iview"},{"id":22986688179995,"value":"no"},{"id":23570126394907,"value":"problema"},{"id":34267608050075,"value":null},{"id":39065204608155,"value":null},{"id":40011436329115,"value":"01K2MWPZ0X0DMAW9P42PW6X6V4"},{"id":43011722643739,"value":null},{"id":43806479792155,"value":null},{"id":43806495652507,"value":null}]
A8: 9809 | B8: Panel iview | C8: open | D8: normal | E8: incident | F8: 46036.448 | G8: 46042.445 | H8: 14741543428379 | I8: 26080982926747 | K8: elekta, físico, hardware_y_software, hexapod, iview, linac, monaco, mosaiq, no, platform, problema, sistema_de_imagen_portal_iview, suncheck_machine, sunnuclear, versahd, xvi | L8: [{"id":22950764862363,"value":null},{"id":22951106310811,"value":"sistema_de_imagen_portal_iview"},{"id":22986688179995,"value":"no"},{"id":23570126394907,"value":"problema"},{"id":34267608050075,"value":null},{"id":39065204608155,"value":null},{"id":40011436329115,"value":"01K2MWPZ0X0DMAW9P42PW6X6V4"},{"id":43011722643739,"value":null},{"id":43806479792155,"value":null},{"id":43806495652507,"value":null}]
A9: 9807 | B9: Equipo no logra iniciar | C9: solved | D9: high | E9: incident | F9: 46035.465 | G9: 46037.501 | H9: 14741318546075 | I9: 36182421530907 | J9: 22297930568347 | K9: agility, elekta, hardware_y_software, monaco, mosaiq, problema, si, sinergy, suncheck, suncheck_machine, sunnuclear, supervisor_de_equipo_médicos, versahd | L9: [{"id":22950764862363,"value":null},{"id":22951106310811,"value":"suncheck"},{"id":22986688179995,"value":"si"},{"id":23570126394907,"value":"problema"},{"id":34267608050075,"value":null},{"id":39065204608155,"value":null},{"id":40011436329115,"value":"01K2MWKNK7SBBFQAXJYFH5C7RR"},{"id":43011722643739,"value":null},{"id":43806479792155,"value":null},{"id":43806495652507,"value":null}]
A10: 9807 | B10: Equipo no logra iniciar | C10: closed | D10: high | E10: incident | F10: 46035.465 | G10: 46040.518 | H10: 14741318546075 | I10: 36182421530907 | J10: 22297930568347 | K10: agility, elekta, hardware_y_software, monaco, mosaiq, problema, si, sinergy, suncheck, suncheck_machine, sunnuclear, supervisor_de_equipo_médicos, versahd | L10: [{"id":22950764862363,"value":null},{"id":22951106310811,"value":"suncheck"},{"id":22986688179995,"value":"si"},{"id":23570126394907,"value":"problema"},{"id":34267608050075,"value":null},{"id":39065204608155,"value":null},{"id":40011436329115,"value":"01K2MWKNK7SBBFQAXJYFH5C7RR"},{"id":43011722643739,"value":null},{"id":43806479792155,"value":null},{"id":43806495652507,"value":null}]
A11: 9806 | B11: Interlock PRF En Chk | C11: pending | D11: high | E11: incident | F11: 46034.977 | G11: 46037.643 | H11: 20265216319003 | I11: 20254050952987 | K11: axesse, barcoding, braquiterapia, dosisoft, elekta, físico, hardware_y_software, infinity, iview, linac, monaco, monacosim, mosaiq, no, problema, storage, versahd, xvi | L11: [{"id":22950764862363,"value":null},{"id":22951106310811,"value":"dosisoft"},{"id":22986688179995,"value":"no"},{"id":23570126394907,"value":"problema"},{"id":34267608050075,"value":null},{"id":39065204608155,"value":null},{"id":40011436329115,"value":"01K2MWGQVK5P8BZ4P54MS8055Q"},{"id":43011722643739,"value":null},{"id":43806479792155,"value":null},{"id":43806495652507,"value":null}]
A12: 9805 | B12: System on water temp | C12: solved | D12: high | E12: incident | F12: 46034.468 | G12: 46036.751 | H12: 14741543428379 | I12: 26080982926747 | J12: 19579468718875 | K12: elekta, físico, hardware_y_software, hexapod, iview, linac, monaco, mosaiq, no, platform, problema, suncheck, suncheck_machine, sunnuclear, versahd, xvi | L12: [{"id":22950764862363,"value":null},{"id":22951106310811,"value":"suncheck"},{"id":22986688179995,"value":"no"},{"id":23570126394907,"value":"problema"},{"id":34267608050075,"value":null},{"id":39065204608155,"value":null},{"id":40011436329115,"value":"01K2MWPZ0X0DMAW9P42PW6X6V4"},{"id":43011722643739,"value":null},{"id":43806479792155,"value":null},{"id":43806495652507,"value":null}]
A13: 9804 | B13: Calibración hexapod | C13: solved | D13: high | E13: incident | F13: 46031.721 | G13: 46037.629 | H13: 20265216319003 | I13: 20254050952987 | J13: 22297930568347 | K13: axesse, barcoding, braquiterapia, dosisoft, elekta, físico, hardware_y_software, infinity, iview, linac, monaco, monacosim, mosaiq, no, problema, storage, versahd, xvi | L13: [{"id":22950764862363,"value":null},{"id":22951106310811,"value":"dosisoft"},{"id":22986688179995,"value":"no"},{"id":23570126394907,"value":"problema"},{"id":34267608050075,"value":null},{"id":39065204608155,"value":null},{"id":40011436329115,"value":"01K2MWGQVK5P8BZ4P54MS8055Q"},{"id":43011722643739,"value":null},{"id":43806479792155,"value":null},{"id":43806495652507,"value":null}]
A14: 9804 | B14: Calibración hexapod | C14: solved | D14: high | E14: incident | F14: 46031.721 | G14: 46039.656 | H14: 20265216319003 | I14: 20254050952987 | J14: 22297930568347 | K14: axesse, barcoding, braquiterapia, dosisoft, elekta, físico, hardware_y_software, infinity, iview, linac, monaco, monacosim, mosaiq, no, problema, storage, versahd, xvi | L14: [{"id":22950764862363,"value":null},{"id":22951106310811,"value":"dosisoft"},{"id":22986688179995,"value":"no"},{"id":23570126394907,"value":"problema"},{"id":34267608050075,"value":null},{"id":39065204608155,"value":null},{"id":40011436329115,"value":"01K2MWGQVK5P8BZ4P54MS8055Q"},{"id":43011722643739,"value":null},{"id":43806479792155,"value":null},{"id":43806495652507,"value":null}]
A15: 9801 | B15: Gantry Stop-Infinity detenido - se requiere atencion en terreno lo antes posible | C15: closed | D15: urgent | E15: incident | F15: 46030.804 | G15: 46035.561 | H15: 14741593614363 | I15: 20254050947483 | J15: 22297930568347 | K15: citrix, elekta, físico, hardware_y_software, infinity, integrity, iview, linac, media, monaco, mosaiq, problema, si, storage, suncheck_machine, sunnuclear, xvi | L15: [{"id":22950764862363,"value":null},{"id":22951106310811,"value":"integrity"},{"id":22986688179995,"value":"si"},{"id":23570126394907,"value":"problema"},{"id":34267608050075,"value":null},{"id":39065204608155,"value":null},{"id":40011436329115,"value":"01K2MWR2KCZK72HY0ZV2CSMFTN"},{"id":43011722643739,"value":null},{"id":43806479792155,"value":null},{"id":43806495652507,"value":null}]
A16: 9800 | B16: Solicitud de actualizacion de licencias productos Sunnuclear | C16: new | D16: urgent | E16: incident | F16: 46030.601 | G16: 46030.601 | H16: 14741593614363 | I16: 20254050948123 | K16: citrix, elekta, físico, hardware_y_software, infinity, integrity, iview, linac, media, monaco, mosaiq, no, problema, storage, suncheck_machine, sunnuclear, xvi | L16: [{"id":22950764862363,"value":null},{"id":22951106310811,"value":"integrity"},{"id":22986688179995,"value":"no"},{"id":23570126394907,"value":"problema"},{"id":34267608050075,"value":null},{"id":39065204608155,"value":null},{"id":40011436329115,"value":"01K2MWR2KCZK72HY0ZV2CSMFTN"},{"id":43011722643739,"value":null},{"id":43806479792155,"value":null},{"id":43806495652507,"value":null}]
A17: 9799 | B17: Interlocks MLC VERSA 1 | C17: solved | D17: high | E17: incident | F17: 46029.469 | G17: 46037.501 | H17: 14741389938587 | I17: 20254020292379 | J17: 22297930568347 | K17: abc, elekta, físico, hardware_y_software, hexapod, media, monaco, mosaiq, no, problema, versahd | L17: [{"id":22950764862363,"value":null},{"id":22951106310811,"value":"abc"},{"id":22986688179995,"value":"no"},{"id":23570126394907,"value":"problema"},{"id":34267608050075,"value":null},{"id":39065204608155,"value":null},{"id":40011436329115,"value":"01K2MWVQJ3DHXN1BYF1WF54DC4"},{"id":43011722643739,"value":null},{"id":43806479792155,"value":null},{"id":43806495652507,"value":null}]
A18: 9799 | B18: Interlocks MLC VERSA 1 | C18: closed | D18: high | E18: incident | F18: 46029.469 | G18: 46040.518 | H18: 14741389938587 | I18: 20254020292379 | J18: 22297930568347 | K18: abc, elekta, físico, hardware_y_software, hexapod, media, monaco, mosaiq, no, problema, versahd | L18: [{"id":22950764862363,"value":null},{"id":22951106310811,"value":"abc"},{"id":22986688179995,"value":"no"},{"id":23570126394907,"value":"problema"},{"id":34267608050075,"value":null},{"id":39065204608155,"value":null},{"id":40011436329115,"value":"01K2MWVQJ3DHXN1BYF1WF54DC4"},{"id":43011722643739,"value":null},{"id":43806479792155,"value":null},{"id":43806495652507,"value":null}]
A19: 9796 | B19: Gantry Stop aleatorio en CL2 Infinity | C19: closed | D19: urgent | E19: incident | F19: 46028.564 | G19: 46035.561 | H19: 14741593614363 | I19: 20254050947483 | J19: 22297930568347 | K19: citrix, elekta, físico, hardware_y_software, infinity, integrity, iview, linac, media, monaco, mosaiq, no, problema, storage, suncheck_machine, sunnuclear, xvi | L19: [{"id":22950764862363,"value":null},{"id":22951106310811,"value":"integrity"},{"id":22986688179995,"value":"no"},{"id":23570126394907,"value":"problema"},{"id":34267608050075,"value":null},{"id":39065204608155,"value":null},{"id":40011436329115,"value":"01K2MWR2KCZK72HY0ZV2CSMFTN"},{"id":43011722643739,"value":null},{"id":43806479792155,"value":null},{"id":43806495652507,"value":null}]
A20: 9795 | B20: Infinity se apaga solo | C20: new | D20: urgent | E20: incident | F20: 46028.478 | G20: 46028.478 | H20: 14741593614363 | I20: 20254050947483 | K20: citrix, elekta, físico, hardware_y_software, infinity, integrity, iview, linac, media, monaco, mosaiq, no, problema, storage, suncheck_machine, sunnuclear, xvi | L20: [{"id":22950764862363,"value":null},{"id":22951106310811,"value":"integrity"},{"id":22986688179995,"value":"no"},{"id":23570126394907,"value":"problema"},{"id":34267608050075,"value":null},{"id":39065204608155,"value":null},{"id":40011436329115,"value":"01K2MWR2KCZK72HY0ZV2CSMFTN"},{"id":43011722643739,"value":null},{"id":43806479792155,"value":null},{"id":43806495652507,"value":null}]
A21: 9792 | B21: Perdida conexión Axesse | C21: new | D21: normal | E21: incident | F21: 46027.589 | G21: 46027.589 | H21: 14741297259931 | I21: 23562920769947 | K21: axesse, braquiterapia, clarity, elekta, físico, hardware_y_software, infinity, monaco, mosaiq, no, problema | L21: [{"id":22950764862363,"value":null},{"id":22951106310811,"value":"clarity"},{"id":22986688179995,"value":"no"},{"id":23570126394907,"value":"problema"},{"id":34267608050075,"value":null},{"id":39065204608155,"value":null},{"id":40011436329115,"value":"01K2MVY8Y64ADSZN89S82WQWXZ"},{"id":43011722643739,"value":null},{"id":43806479792155,"value":null},{"id":43806495652507,"value":null}]
A22: 9785 | B22: Maquina se reinicia sola | C22: closed | D22: normal | E22: incident | F22: 46021.599 | G22: 46032.691 | H22: 14741543428379 | I22: 26080982926747 | J22: 19579468718875 | K22: acelerador_lineal, elekta, físico, hardware_y_software, hexapod, iview, linac, monaco, mosaiq, no, platform, problema, suncheck_machine, sunnuclear, versahd, xvi | L22: [{"id":22950764862363,"value":null},{"id":22951106310811,"value":"acelerador_lineal"},{"id":22986688179995,"value":"no"},{"id":23570126394907,"value":"problema"},{"id":34267608050075,"value":null},{"id":39065204608155,"value":null},{"id":40011436329115,"value":"01K2MWPZ0X0DMAW9P42PW6X6V4"},{"id":43011722643739,"value":null},{"id":43806479792155,"value":null},{"id":43806495652507,"value":null}]
A23: 9783 | B23: advertencia Replace Filter - SunSCAN | C23: pending | D23: high | E23: incident | F23: 46021.533 | G23: 46029.793 | H23: 14741593614363 | I23: 20254050947483 | J23: 14734559344539 | K23: citrix, elekta, físico, hardware_y_software, infinity, iview, linac, media, monaco, mosaiq, no, on_hold_1h, problema, storage, suncheck, suncheck_machine, sunnuclear, xvi | L23: [{"id":22950764862363,"value":null},{"id":22951106310811,"value":"suncheck"},{"id":22986688179995,"value":"no"},{"id":23570126394907,"value":"problema"},{"id":34267608050075,"value":null},{"id":39065204608155,"value":null},{"id":40011436329115,"value":"01K2MWR2KCZK72HY0ZV2CSMFTN"},{"id":43011722643739,"value":null},{"id":43806479792155,"value":null},{"id":43806495652507,"value":null}]
A24: 9782 | B24: falla humidificador y AACC del bunker del Infinity | C24: closed | D24: low | E24: incident | F24: 46021.512 | G24: 46028.724 | H24: 14741593614363 | I24: 20254050947483 | J24: 19579474867355 | K24: acelerador_lineal, elekta, físico, linac, no, problema | L24: [{"id":22950764862363,"value":null},{"id":22951106310811,"value":"acelerador_lineal"},{"id":22986688179995,"value":"no"},{"id":23570126394907,"value":"problema"},{"id":34267608050075,"value":null},{"id":39065204608155,"value":null},{"id":40011436329115,"value":"01K2MWR2KCZK72HY0ZV2CSMFTN"},{"id":43011722643739,"value":null},{"id":43806479792155,"value":null},{"id":43806495652507,"value":null}]
A25: 9781 | B25: Equipo detenido por Problema con "Tasa de dosis baja Canal A" y B | C25: solved | D25: urgent | E25: incident | F25: 46020.746 | G25: 46037.633 | H25: 14742026913435 | I25: 38368479928987 | J25: 22297930568347 | K25: acelerador_lineal, braquiterapia, compact, elekta, hardware_y_software, monaco, monacosim, mosaiq, requerimiento, si, tcs, xio | L25: [{"id":22950764862363,"value":null},{"id":22951106310811,"value":"acelerador_lineal"},{"id":22986688179995,"value":"si"},{"id":23570126394907,"value":"requerimiento"},{"id":34267608050075,"value":"tcs"},{"id":39065204608155,"value":null},{"id":40011436329115,"value":"01K2MXCF9WW205P1YQ3PCD50A9"},{"id":43011722643739,"value":null},{"id":43806479792155,"value":null},{"id":43806495652507,"value":null}]
A26: 9778 | B26: Reaparición falla “Gantry Stop” – CL02 Infinity / Ticket 9774 | C26: closed | D26: urgent | E26: incident | F26: 46020.709 | G26: 46032.607 | H26: 14741593614363 | I26: 20254050947483 | J26: 19579474867355 | K26: acelerador_lineal, elekta, físico, hardware_y_software, infinity, linac, no, problema | L26: [{"id":22950764862363,"value":null},{"id":22951106310811,"value":"acelerador_lineal"},{"id":22986688179995,"value":"no"},{"id":23570126394907,"value":"problema"},{"id":34267608050075,"value":null},{"id":39065204608155,"value":null},{"id":40011436329115,"value":"01K2MWR2KCZK72HY0ZV2CSMFTN"},{"id":43011722643739,"value":null},{"id":43806479792155,"value":null},{"id":43806495652507,"value":null}]
A27: 9775 | B27: DOSE RATE MON 6MeV INFINITY | C27: closed | D27: normal | E27: incident | F27: 46015.737 | G27: 46024.614 | H27: 14741297259931 | I27: 20254050952347 | J27: 19579474867355 | K27: acelerador_lineal, elekta, físico, infinity, no, problema | L27: [{"id":22950764862363,"value":null},{"id":22951106310811,"value":"acelerador_lineal"},{"id":22986688179995,"value":"no"},{"id":23570126394907,"value":"problema"},{"id":34267608050075,"value":null},{"id":39065204608155,"value":null},{"id":40011436329115,"value":"01K2MWEACAGHS4HXG14TE1Y3QE"},{"id":43011722643739,"value":null},{"id":43806479792155,"value":null},{"id":43806495652507,"value":null}]
A28: 9774 | B28: falla Gantry Stop - no puedo hacer QA de paciente - Equipo detenido | C28: closed | D28: urgent | E28: incident | F28: 46015.736 | G28: 46019.908 | H28: 14741593614363 | I28: 20254050947483 | J28: 20210900681499 | K28: citrix, elekta, físico, hardware_y_software, infinity, integrity, iview, linac, media, monaco, mosaiq, problema, si, storage, suncheck_machine, sunnuclear, xvi | L28: [{"id":22950764862363,"value":null},{"id":22951106310811,"value":"integrity"},{"id":22986688179995,"value":"si"},{"id":23570126394907,"value":"problema"},{"id":34267608050075,"value":null},{"id":39065204608155,"value":null},{"id":40011436329115,"value":"01K2MWR2KCZK72HY0ZV2CSMFTN"},{"id":43011722643739,"value":null},{"id":43806479792155,"value":null},{"id":43806495652507,"value":null}]
A29: 9770 | B29: Water Temp | C29: closed | D29: urgent | E29: incident | F29: 46013.655 | G29: 46033.618 | H29: 20265216319003 | I29: 20254050953243 | J29: 20210900681499 | K29: axesse, barcoding, braquiterapia, dosisoft, elekta, físico, hardware_y_software, infinity, iview, linac, monaco, monacosim, mosaiq, problema, si, storage, versahd, xvi | L29: [{"id":22950764862363,"value":null},{"id":22951106310811,"value":"dosisoft"},{"id":22986688179995,"value":"si"},{"id":23570126394907,"value":"problema"},{"id":34267608050075,"value":null},{"id":39065204608155,"value":null},{"id":40011436329115,"value":"01K2MWGQVK5P8BZ4P54MS8055Q"},{"id":43011722643739,"value":null},{"id":43806479792155,"value":null},{"id":43806495652507,"value":null}]
A30: 9764 | B30: Multiples interlocks mas charco de agua en sala de maquinas de origen desconocido | C30: closed | D30: urgent | E30: incident | F30: 46010.494 | G30: 46017.642 | H30: 14741389938587 | I30: 20254020292379 | J30: 19579474867355 | K30: acelerador_lineal, elekta, físico, hexapod, problema, si, versahd | L30: [{"id":22950764862363,"value":null},{"id":22951106310811,"value":"acelerador_lineal"},{"id":22986688179995,"value":"si"},{"id":23570126394907,"value":"problema"},{"id":34267608050075,"value":null},{"id":39065204608155,"value":null},{"id":40011436329115,"value":"01K2MWVQJ3DHXN1BYF1WF54DC4"},{"id":43011722643739,"value":null},{"id":43806479792155,"value":null},{"id":43806495652507,"value":null}]
A31: 9762 | B31: Solicitud de MP Flexitro | C31: new | D31: normal | E31: incident | F31: 46009.542 | G31: 46036.634 | H31: 14741297259931 | I31: 20254050952347 | K31: axesse, braquiterapia, clarity, elekta, flexitron, físico, hardware_y_software, infinity, monaco, mosaiq, no, requerimiento | L31: [{"id":22950764862363,"value":null},{"id":22951106310811,"value":"clarity"},{"id":22986688179995,"value":"no"},{"id":23570126394907,"value":"requerimiento"},{"id":34267608050075,"value":"flexitron"},{"id":39065204608155,"value":null},{"id":40011436329115,"value":null},{"id":43011722643739,"value":null},{"id":43806479792155,"value":null},{"id":43806495652507,"value":null}]
A32: 9751 | B32: Table long | C32: closed | E32: incident | F32: 46006.519 | G32: 46006.86 | H32: 14741543428379 | I32: 26080982926747 | J32: 19579468718875 | K32: closed_by_merge, elekta, físico, hardware_y_software, hexapod, iview, linac, monaco, mosaiq, platform, suncheck, suncheck_machine, sunnuclear, versahd, xvi | L32: [{"id":22950764862363,"value":null},{"id":22951106310811,"value":"suncheck"},{"id":22986688179995,"value":null},{"id":23570126394907,"value":null},{"id":34267608050075,"value":null},{"id":39065204608155,"value":null},{"id":40011436329115,"value":null},{"id":43011722643739,"value":null},{"id":43806479792155,"value":null},{"id":43806495652507,"value":null}]
A33: 9749 | B33: Dose rate mon | C33: closed | D33: urgent | E33: incident | F33: 46003.519 | G33: 46011.676 | H33: 14741597726619 | I33: 20254020299291 | J33: 22297930568347 | K33: acelerador_lineal, elekta, físico, hexapod, iview, no, problema, versahd, xvi | L33: [{"id":22950764862363,"value":null},{"id":22951106310811,"value":"acelerador_lineal"},{"id":22986688179995,"value":"no"},{"id":23570126394907,"value":"problema"},{"id":34267608050075,"value":""},{"id":39065204608155,"value":null},{"id":40011436329115,"value":"01K2MWN8SVJSHMJQM7F39XXN01"},{"id":43011722643739,"value":null},{"id":43806479792155,"value":null},{"id":43806495652507,"value":null}]
A34: 9748 | B34: Importación plan respalado | C34: closed | D34: low | E34: incident | F34: 46003.493 | G34: 46017.514 | H34: 14741543428379 | I34: 40109334283675 | J34: 14481448391451 | K34: elekta, hardware_y_software, hexapod, iview, linac, monaco, monaco_tps, mosaiq, no, platform, requerimiento, suncheck_machine, sunnuclear, versahd, xvi | L34: [{"id":22950764862363,"value":null},{"id":22951106310811,"value":"monaco_tps"},{"id":22986688179995,"value":"no"},{"id":23570126394907,"value":"requerimiento"},{"id":34267608050075,"value":null},{"id":39065204608155,"value":null},{"id":40011436329115,"value":"01K2MWPZ0X0DMAW9P42PW6X6V4"},{"id":43011722643739,"value":null},{"id":43806479792155,"value":null},{"id":43806495652507,"value":null}]
A36: 9746 | B36: Panel de control lateral de camilla está suelto | C36: closed | D36: normal | E36: incident | F36: 46002.736 | G36: 46007.663 | H36: 14741543428379 | I36: 26080969273499 | J36: 19579468718875 | K36: elekta, físico, hardware_y_software, hexapod, iview, linac, monaco, mosaiq, no, platform, requerimiento, sistema_camilla_precise, suncheck_machine, sunnuclear, versahd, xvi | L36: [{"id":22950764862363,"value":null},{"id":22951106310811,"value":"sistema_camilla_precise"},{"id":22986688179995,"value":"no"},{"id":23570126394907,"value":"requerimiento"},{"id":34267608050075,"value":null},{"id":39065204608155,"value":null},{"id":40011436329115,"value":"01K2MWPZ0X0DMAW9P42PW6X6V4"},{"id":43011722643739,"value":null},{"id":43806479792155,"value":null},{"id":43806495652507,"value":null}]
A37: 9745 | B37: Interlock Table Long | C37: closed | D37: normal | E37: incident | F37: 46002.626 | G37: 46032.691 | H37: 14741543428379 | I37: 26080969273499 | J37: 19579468718875 | K37: elekta, físico, hardware_y_software, hexapod, iview, linac, monaco, mosaiq, no, platform, problema, sistema_camilla_precise, suncheck_machine, sunnuclear, versahd, xvi | L37: [{"id":22950764862363,"value":null},{"id":22951106310811,"value":"sistema_camilla_precise"},{"id":22986688179995,"value":"no"},{"id":23570126394907,"value":"problema"},{"id":34267608050075,"value":null},{"id":39065204608155,"value":null},{"id":40011436329115,"value":"01K2MWPZ0X0DMAW9P42PW6X6V4"},{"id":43011722643739,"value":null},{"id":43806479792155,"value":null},{"id":43806495652507,"value":null}]
A38: 9743 | B38: Switches sin luz | C38: closed | D38: low | E38: incident | F38: 46002.542 | G38: 46017.514 | H38: 14741543428379 | I38: 26080982926747 | J38: 14481448391451 | K38: elekta, físico, hardware_y_software, hexapod, incidente, iview, linac, monaco, mosaiq, mosaiq_workstation, no, platform, suncheck_machine, sunnuclear, versahd, xvi | L38: [{"id":22950764862363,"value":null},{"id":22951106310811,"value":"mosaiq_workstation"},{"id":22986688179995,"value":"no"},{"id":23570126394907,"value":"incidente"},{"id":34267608050075,"value":null},{"id":39065204608155,"value":null},{"id":40011436329115,"value":"01K2MWPZ0X0DMAW9P42PW6X6V4"},{"id":43011722643739,"value":null},{"id":43806479792155,"value":null},{"id":43806495652507,"value":null}]
A39: 9742 | B39: Conebeam presenta artefacto | C39: closed | D39: high | E39: incident | F39: 46001.851 | G39: 46012.742 | H39: 14741318546075 | I39: 36182421530907 | J39: 20210900681499 | K39: agility, elekta, hardware_y_software, monaco, mosaiq, no, problema, sinergy, suncheck, suncheck_machine, sunnuclear, supervisor_de_equipo_médicos, versahd | L39: [{"id":22950764862363,"value":null},{"id":22951106310811,"value":"suncheck"},{"id":22986688179995,"value":"no"},{"id":23570126394907,"value":"problema"},{"id":34267608050075,"value":null},{"id":39065204608155,"value":null},{"id":40011436329115,"value":"01K2MWKNK7SBBFQAXJYFH5C7RR"},{"id":43011722643739,"value":null},{"id":43806479792155,"value":null},{"id":43806495652507,"value":null}]
A40: 9740 | B40: verificacion configuracion del Baseline del test de Hancock MLC Suncheck del Infinity | C40: open | D40: urgent | E40: incident | F40: 46001.651 | G40: 46028.664 | H40: 14741593614363 | I40: 20254050947483 | J40: 19579474867355 | K40: citrix, elekta, físico, hardware_y_software, infinity, iview, linac, media, monaco, mosaiq, no, on_hold_1h, requerimiento, storage, suncheck_machine, sunnuclear, xvi | L40: [{"id":22950764862363,"value":null},{"id":22951106310811,"value":""},{"id":22986688179995,"value":"no"},{"id":23570126394907,"value":"requerimiento"},{"id":34267608050075,"value":null},{"id":39065204608155,"value":null},{"id":40011436329115,"value":"01K2MWR2KCZK72HY0ZV2CSMFTN"},{"id":43011722643739,"value":null},{"id":43806479792155,"value":null},{"id":43806495652507,"value":null}]
A41: 9740 | B41: verificacion configuracion del Baseline del test de Hancock MLC Suncheck del Infinity | C41: pending | D41: urgent | E41: incident | F41: 46001.651 | G41: 46041.501 | H41: 14741593614363 | I41: 20254050947483 | J41: 19579474867355 | K41: citrix, elekta, físico, hardware_y_software, infinity, iview, linac, media, monaco, mosaiq, no, on_hold_1h, requerimiento, storage, suncheck_machine, sunnuclear, xvi | L41: [{"id":22950764862363,"value":null},{"id":22951106310811,"value":""},{"id":22986688179995,"value":"no"},{"id":23570126394907,"value":"requerimiento"},{"id":34267608050075,"value":null},{"id":39065204608155,"value":null},{"id":40011436329115,"value":"01K2MWR2KCZK72HY0ZV2CSMFTN"},{"id":43011722643739,"value":null},{"id":43806479792155,"value":null},{"id":43806495652507,"value":null}]
A42: 9739 | B42: Pantalla de acelerador sin señal | C42: closed | D42: high | E42: incident | F42: 46001.623 | G42: 46005.656 | H42: 14741543428379 | I42: 26080969273499 | J42: 19579468718875 | K42: elekta, físico, hardware_y_software, hexapod, iview, linac, monaco, mosaiq, no, platform, problema, sistema_ccp, suncheck_machine, sunnuclear, versahd, xvi | L42: [{"id":22950764862363,"value":null},{"id":22951106310811,"value":"sistema_ccp"},{"id":22986688179995,"value":"no"},{"id":23570126394907,"value":"problema"},{"id":34267608050075,"value":null},{"id":39065204608155,"value":null},{"id":40011436329115,"value":"01K2MWPZ0X0DMAW9P42PW6X6V4"},{"id":43011722643739,"value":null},{"id":43806479792155,"value":null},{"id":43806495652507,"value":null}]
A43: 9737 | B43: Versa se apaga de forma espontanea | C43: closed | D43: urgent | E43: incident | F43: 46000.798 | G43: 46005.656 | H43: 20265216319003 | I43: 20254050953243 | J43: 19579474867355 | K43: acelerador_lineal, elekta, físico, linac, problema, si, versahd | L43: [{"id":22950764862363,"value":null},{"id":22951106310811,"value":"acelerador_lineal"},{"id":22986688179995,"value":"si"},{"id":23570126394907,"value":"problema"},{"id":34267608050075,"value":null},{"id":39065204608155,"value":null},{"id":40011436329115,"value":"01K2MWGQVK5P8BZ4P54MS8055Q"},{"id":43011722643739,"value":null},{"id":43806479792155,"value":null},{"id":43806495652507,"value":null}]
A44: 9734 | B44: Solicitud de colaboración para prueba de interruptores de emergencia del acelerador lineal | C44: closed | D44: normal | E44: incident | F44: 46000.727 | G44: 46007.663 | H44: 14741543428379 | I44: 26080969273499 | J44: 19579468718875 | K44: acelerador_lineal, elekta, físico, hardware_y_software, hexapod, iview, linac, monaco, mosaiq, no, platform, requerimiento, suncheck_machine, sunnuclear, versahd, xvi | L44: [{"id":22950764862363,"value":null},{"id":22951106310811,"value":"acelerador_lineal"},{"id":22986688179995,"value":"no"},{"id":23570126394907,"value":"requerimiento"},{"id":34267608050075,"value":null},{"id":39065204608155,"value":null},{"id":40011436329115,"value":"01K2MWPZ0X0DMAW9P42PW6X6V4"},{"id":43011722643739,"value":null},{"id":43806479792155,"value":null},{"id":43806495652507,"value":null}]
A45: 9733 | B45: ruido muy fuerte al girar el gantry del Infinity - por favor investigar | C45: closed | D45: normal | E45: incident | F45: 46000.615 | G45: 46032.607 | H45: 14741593614363 | I45: 20254050947483 | J45: 19579474867355 | K45: acelerador_lineal, elekta, físico, infinity, linac, no, problema | L45: [{"id":22950764862363,"value":null},{"id":22951106310811,"value":"acelerador_lineal"},{"id":22986688179995,"value":"no"},{"id":23570126394907,"value":"problema"},{"id":34267608050075,"value":null},{"id":39065204608155,"value":null},{"id":40011436329115,"value":"01K2MWR2KCZK72HY0ZV2CSMFTN"},{"id":43011722643739,"value":null},{"id":43806479792155,"value":null},{"id":43806495652507,"value":null}]
A46: 9732 | B46: Falla XVI - Fault 33 - despejada gracias a FM Camilo de la Barra | C46: closed | D46: high | E46: incident | F46: 46000.58 | G46: 46011.634 | H46: 14741593614363 | I46: 20254050947483 | J46: 19579474867355 | K46: elekta, físico, infinity, integrity, iview, linac, no, problema, xvi | L46: [{"id":22950764862363,"value":null},{"id":22951106310811,"value":"integrity"},{"id":22986688179995,"value":"no"},{"id":23570126394907,"value":"problema"},{"id":34267608050075,"value":null},{"id":39065204608155,"value":null},{"id":40011436329115,"value":"01K2MWR2KCZK72HY0ZV2CSMFTN"},{"id":43011722643739,"value":null},{"id":43806479792155,"value":null},{"id":43806495652507,"value":null}]
A47: 9731 | B47: Falla en panel iview | C47: open | D47: urgent | E47: incident | F47: 46000.529 | G47: 46021.854 | H47: 14741318546075 | I47: 36182421530907 | K47: agility, elekta, hardware_y_software, monaco, mosaiq, no, problema, sinergy, suncheck, suncheck_machine, sunnuclear, supervisor_de_equipo_médicos, versahd | L47: [{"id":22950764862363,"value":null},{"id":22951106310811,"value":"suncheck"},{"id":22986688179995,"value":"no"},{"id":23570126394907,"value":"problema"},{"id":34267608050075,"value":null},{"id":39065204608155,"value":null},{"id":40011436329115,"value":"01K2MWJ4ARZRVMA1V6XFP5Y5E4"},{"id":43011722643739,"value":null},{"id":43806479792155,"value":null},{"id":43806495652507,"value":null}]
A48: 9724 | B48: falla intermitente del sistema de audio que dificulta oir al paciente del CL02 Infinity | C48: pending | D48: high | E48: incident | F48: 45995.568 | G48: 46000.627 | H48: 14741593614363 | I48: 20254050947483 | K48: citrix, elekta, físico, hardware_y_software, infinity, integrity, iview, linac, media, monaco, mosaiq, no, problema, storage, suncheck_machine, sunnuclear, xvi | L48: [{"id":22950764862363,"value":null},{"id":22951106310811,"value":"integrity"},{"id":22986688179995,"value":"no"},{"id":23570126394907,"value":"problema"},{"id":34267608050075,"value":null},{"id":39065204608155,"value":null},{"id":40011436329115,"value":"01K2MWR2KCZK72HY0ZV2CSMFTN"},{"id":43011722643739,"value":null},{"id":43806479792155,"value":null},{"id":43806495652507,"value":null}]
A49: 9723 | B49: Problemas MLC Infinity | C49: closed | D49: urgent | E49: incident | F49: 45995.465 | G49: 46011.676 | H49: 14741297259931 | I49: 23562920769947 | J49: 27816237178267 | K49: cabezal_agility, elekta, físico, infinity, problema, si | L49: [{"id":22950764862363,"value":null},{"id":22951106310811,"value":"cabezal_agility"},{"id":22986688179995,"value":"si"},{"id":23570126394907,"value":"problema"},{"id":34267608050075,"value":null},{"id":39065204608155,"value":null},{"id":40011436329115,"value":"01K2MWEACAGHS4HXG14TE1Y3QE"},{"id":43011722643739,"value":null},{"id":43806479792155,"value":null},{"id":43806495652507,"value":null}]
A50: 9716 | B50: Notebook de qa no carga | C50: closed | D50: normal | E50: incident | F50: 45993.492 | G50: 46025.845 | H50: 14741543428379 | I50: 26080982926747 | J50: 14481448391451 | K50: elekta, físico, hardware_y_software, hexapod, iview, linac, monaco, mosaiq, no, platform, requerimiento, suncheck, suncheck_machine, sunnuclear, versahd, xvi | L50: [{"id":22950764862363,"value":null},{"id":22951106310811,"value":"suncheck"},{"id":22986688179995,"value":"no"},{"id":23570126394907,"value":"requerimiento"},{"id":34267608050075,"value":null},{"id":39065204608155,"value":null},{"id":40011436329115,"value":null},{"id":43011722643739,"value":null},{"id":43806479792155,"value":null},{"id":43806495652507,"value":null}]
A51: 9709 | B51: Asunto: Artefacto de anillo en el XVI del Axesee | C51: pending | D51: high | E51: incident | F51: 45992.489 | G51: 46000.543 | H51: 14741297259931 | I51: 20254050952475 | K51: axesse, braquiterapia, clarity, elekta, físico, hardware_y_software, infinity, monaco, mosaiq, no, on_hold_1h, problema | L51: [{"id":22950764862363,"value":null},{"id":22951106310811,"value":"clarity"},{"id":22986688179995,"value":"no"},{"id":23570126394907,"value":"problema"},{"id":34267608050075,"value":null},{"id":39065204608155,"value":null},{"id":40011436329115,"value":"01K2MVY8Y64ADSZN89S82WQWXZ"},{"id":43011722643739,"value":null},{"id":43806479792155,"value":null},{"id":43806495652507,"value":null}]
A52: 9706 | B52: Problemas en posicionamiento de Hexapod | C52: closed | D52: high | E52: incident | F52: 45988.83 | G52: 46012.742 | H52: 14741318546075 | I52: 36182421530907 | J52: 20210900681499 | K52: agility, elekta, hardware_y_software, monaco, mosaiq, no, problema, sinergy, suncheck, suncheck_machine, sunnuclear, supervisor_de_equipo_médicos, versahd | L52: [{"id":22950764862363,"value":null},{"id":22951106310811,"value":"suncheck"},{"id":22986688179995,"value":"no"},{"id":23570126394907,"value":"problema"},{"id":34267608050075,"value":null},{"id":39065204608155,"value":null},{"id":40011436329115,"value":"01K2MWKNK7SBBFQAXJYFH5C7RR"},{"id":43011722643739,"value":null},{"id":43806479792155,"value":null},{"id":43806495652507,"value":null}]
A53: 9703 | B53: Maquina detenida por falla desconocida | C53: closed | D53: urgent | E53: incident | F53: 45988.477 | G53: 45993.708 | H53: 14742026913435 | I53: 38368479928987 | J53: 19579474867355 | K53: acelerador_lineal, compact, elekta, problema, si | L53: [{"id":22950764862363,"value":null},{"id":22951106310811,"value":"acelerador_lineal"},{"id":22986688179995,"value":"si"},{"id":23570126394907,"value":"problema"},{"id":34267608050075,"value":""},{"id":39065204608155,"value":null},{"id":40011436329115,"value":"01K2MXCF9WW205P1YQ3PCD50A9"},{"id":43011722643739,"value":null},{"id":43806479792155,"value":null},{"id":43806495652507,"value":null}]
A54: 9696 | B54: equipo detenido por problemas con magnetron | C54: closed | D54: urgent | E54: incident | F54: 45987.579 | G54: 45993.708 | H54: 14742026913435 | I54: 38368479928987 | J54: 19579474867355 | K54: acelerador_lineal, compact, elekta, problema, si, tcs | L54: [{"id":22950764862363,"value":null},{"id":22951106310811,"value":"acelerador_lineal"},{"id":22986688179995,"value":"si"},{"id":23570126394907,"value":"problema"},{"id":34267608050075,"value":"tcs"},{"id":39065204608155,"value":null},{"id":40011436329115,"value":"01K2MXCF9WW205P1YQ3PCD50A9"},{"id":43011722643739,"value":null},{"id":43806479792155,"value":null},{"id":43806495652507,"value":null}]
A55: 9695 | B55: Falla HEXAPOD VERSA 2 | C55: closed | D55: normal | E55: incident | F55: 45987.535 | G55: 46017.642 | H55: 14741389938587 | I55: 20254020292379 | J55: 19579474867355 | K55: acelerador_lineal, elekta, físico, hexapod, no, problema, versahd | L55: [{"id":22950764862363,"value":null},{"id":22951106310811,"value":"acelerador_lineal"},{"id":22986688179995,"value":"no"},{"id":23570126394907,"value":"problema"},{"id":34267608050075,"value":null},{"id":39065204608155,"value":null},{"id":40011436329115,"value":"01K2MX4Z0KY2MHPJMC4ZM7C8T1"},{"id":43011722643739,"value":null},{"id":43806479792155,"value":null},{"id":43806495652507,"value":null}]
A56: 9691 | B56: Interlock D1 | C56: closed | D56: high | E56: incident | F56: 45986.475 | G56: 45990.52 | H56: 14741597726619 | I56: 20254020299547 | J56: 22297930568347 | K56: acelerador_lineal, elekta, físico, hardware_y_software, hexapod, iba, iguide, iview, monaco, monacosim, mosaiq, requerimiento, rtp99, si, tcs, versahd, xvi | L56: [{"id":22950764862363,"value":null},{"id":22951106310811,"value":"acelerador_lineal"},{"id":22986688179995,"value":"si"},{"id":23570126394907,"value":"requerimiento"},{"id":34267608050075,"value":"tcs"},{"id":39065204608155,"value":null},{"id":40011436329115,"value":"01K2MWN8SVJSHMJQM7F39XXN01"},{"id":43011722643739,"value":null},{"id":43806479792155,"value":null},{"id":43806495652507,"value":null}]
A57: 9690 | B57: 2T 15MeV electrones | C57: closed | D57: normal | E57: incident | F57: 45986.452 | G57: 46024.614 | H57: 14741297259931 | I57: 23562920769947 | J57: 19579474867355 | K57: acelerador_lineal, axesse, elekta, físico, no, problema | L57: [{"id":22950764862363,"value":null},{"id":22951106310811,"value":"acelerador_lineal"},{"id":22986688179995,"value":"no"},{"id":23570126394907,"value":"problema"},{"id":34267608050075,"value":null},{"id":39065204608155,"value":null},{"id":40011436329115,"value":"01K2MVY8Y64ADSZN89S82WQWXZ"},{"id":43011722643739,"value":null},{"id":43806479792155,"value":null},{"id":43806495652507,"value":null}]
A58: 9689 | B58: Inestabilidad de los haces de fotones VERSA 1 | C58: closed | D58: urgent | E58: incident | F58: 45985.648 | G58: 46011.676 | H58: 14741389938587 | I58: 20254020292379 | J58: 20210900681499 | K58: acelerador_lineal, elekta, físico, problema, si, versahd | L58: [{"id":22950764862363,"value":null},{"id":22951106310811,"value":"acelerador_lineal"},{"id":22986688179995,"value":"si"},{"id":23570126394907,"value":"problema"},{"id":34267608050075,"value":null},{"id":39065204608155,"value":null},{"id":40011436329115,"value":"01K2MWVQJ3DHXN1BYF1WF54DC4"},{"id":43011722643739,"value":null},{"id":43806479792155,"value":null},{"id":43806495652507,"value":null}]
A59: 9688 | B59: Falla telemetro VERSA 2 | C59: pending | D59: normal | E59: incident | F59: 45985.645 | G59: 45990.751 | H59: 14741389938587 | I59: 20254020292379 | K59: abc, elekta, físico, hardware_y_software, hexapod, media, monaco, mosaiq, no, problema, versahd | L59: [{"id":22950764862363,"value":null},{"id":22951106310811,"value":"abc"},{"id":22986688179995,"value":"no"},{"id":23570126394907,"value":"problema"},{"id":34267608050075,"value":null},{"id":39065204608155,"value":null},{"id":40011436329115,"value":"01K2MX4Z0KY2MHPJMC4ZM7C8T1"},{"id":43011722643739,"value":null},{"id":43806479792155,"value":null},{"id":43806495652507,"value":null}]
A60: 9685 | B60: Interlock Low Water Pressure VERSA 1 | C60: closed | D60: urgent | E60: incident | F60: 45985.511 | G60: 46011.676 | H60: 14741389938587 | I60: 20254020292379 | J60: 20210900681499 | K60: acelerador_lineal, elekta, físico, problema, si, versahd | L60: [{"id":22950764862363,"value":null},{"id":22951106310811,"value":"acelerador_lineal"},{"id":22986688179995,"value":"si"},{"id":23570126394907,"value":"problema"},{"id":34267608050075,"value":null},{"id":39065204608155,"value":null},{"id":40011436329115,"value":"01K2MWVQJ3DHXN1BYF1WF54DC4"},{"id":43011722643739,"value":null},{"id":43806479792155,"value":null},{"id":43806495652507,"value":null}]
A61: 9684 | B61: Interlock Memoria Acelerador Axesse | C61: closed | D61: normal | E61: incident | F61: 45985.478 | G61: 45991.663 | H61: 14741297259931 | I61: 20254050952347 | J61: 22297930568347 | K61: axesse, braquiterapia, clarity, elekta, físico, hardware_y_software, infinity, monaco, mosaiq, no, problema | L61: [{"id":22950764862363,"value":null},{"id":22951106310811,"value":"clarity"},{"id":22986688179995,"value":"no"},{"id":23570126394907,"value":"problema"},{"id":34267608050075,"value":null},{"id":39065204608155,"value":null},{"id":40011436329115,"value":"01K2MVY8Y64ADSZN89S82WQWXZ"},{"id":43011722643739,"value":null},{"id":43806479792155,"value":null},{"id":43806495652507,"value":null}]
A62: 9680 | B62: Interlock 10. Trp G | C62: closed | D62: high | E62: incident | F62: 45981.475 | G62: 45991.579 | H62: 14741297259931 | I62: 20254050952603 | J62: 19579474867355 | K62: acelerador_lineal, axesse, elekta, físico, hardware_y_software, infinity, requerimiento, si | L62: [{"id":22950764862363,"value":null},{"id":22951106310811,"value":"acelerador_lineal"},{"id":22986688179995,"value":"si"},{"id":23570126394907,"value":"requerimiento"},{"id":34267608050075,"value":null},{"id":39065204608155,"value":null},{"id":40011436329115,"value":"01K2MVY8Y64ADSZN89S82WQWXZ"},{"id":43011722643739,"value":null},{"id":43806479792155,"value":null},{"id":43806495652507,"value":null}]
A63: 9677 | B63: Problema Mosaiq | C63: closed | D63: normal | E63: incident | F63: 45980.807 | G63: 46025.845 | H63: 14741543428379 | I63: 40109334283675 | J63: 14481448391451 | K63: elekta, error, hardware_y_software, hexapod, iview, linac, monaco, mosaiq, mosaiq_workstation, no, platform, problema, suncheck_machine, sunnuclear, versahd, xvi | L63: [{"id":22950764862363,"value":null},{"id":22951106310811,"value":"mosaiq_workstation"},{"id":22986688179995,"value":"no"},{"id":23570126394907,"value":"problema"},{"id":34267608050075,"value":null},{"id":39065204608155,"value":null},{"id":40011436329115,"value":"01K2MWPZ0X0DMAW9P42PW6X6V4"},{"id":43011722643739,"value":null},{"id":43806479792155,"value":null},{"id":43806495652507,"value":null}]
A64: 9672 | B64: continua falla isocentro kV vs isocentro reticulo (luz de campo) y falla MLC test de hancock, post reparacion | C64: new | D64: urgent | E64: incident | F64: 45978.761 | G64: 45978.761 | H64: 14741593614363 | I64: 20254050947483 | K64: citrix, elekta, físico, hardware_y_software, infinity, integrity, iview, linac, media, monaco, mosaiq, no, problema, storage, suncheck_machine, sunnuclear, xvi | L64: [{"id":22950764862363,"value":null},{"id":22951106310811,"value":"integrity"},{"id":22986688179995,"value":"no"},{"id":23570126394907,"value":"problema"},{"id":34267608050075,"value":null},{"id":39065204608155,"value":null},{"id":40011436329115,"value":"01K2MWR2KCZK72HY0ZV2CSMFTN"},{"id":43011722643739,"value":null},{"id":43806479792155,"value":null},{"id":43806495652507,"value":null}]
A65: 9670 | B65: Dose Rate Mon 10FFF | C65: closed | D65: high | E65: incident | F65: 45975.685 | G65: 45991.579 | H65: 20265216319003 | I65: 20254050953243 | J65: 19579474867355 | K65: acelerador_lineal, elekta, físico, linac, no, requerimiento, versahd | L65: [{"id":22950764862363,"value":null},{"id":22951106310811,"value":"acelerador_lineal"},{"id":22986688179995,"value":"no"},{"id":23570126394907,"value":"requerimiento"},{"id":34267608050075,"value":null},{"id":39065204608155,"value":null},{"id":40011436329115,"value":"01K2MWGQVK5P8BZ4P54MS8055Q"},{"id":43011722643739,"value":null},{"id":43806479792155,"value":null},{"id":43806495652507,"value":null}]
A66: 9668 | B66: Falla MLC VERSA 1 | C66: closed | D66: urgent | E66: incident | F66: 45975.585 | G66: 45982.504 | H66: 14741389938587 | I66: 20254020292379 | J66: 31525538040603 | K66: abc, elekta, físico, hardware_y_software, hexapod, media, monaco, mosaiq, problema, si, versahd | L66: [{"id":22950764862363,"value":null},{"id":22951106310811,"value":"abc"},{"id":22986688179995,"value":"si"},{"id":23570126394907,"value":"problema"},{"id":34267608050075,"value":null},{"id":39065204608155,"value":null},{"id":40011436329115,"value":"01K2MWVQJ3DHXN1BYF1WF54DC4"},{"id":43011722643739,"value":null},{"id":43806479792155,"value":null},{"id":43806495652507,"value":null}]
A67: 9664 | B67: Audio funciona mal | C67: closed | D67: normal | E67: incident | F67: 45974.58 | G67: 45982.887 | H67: 14741543428379 | I67: 26080982926747 | J67: 19579468718875 | K67: consultas_rt, elekta, físico, hardware_y_software, hexapod, iview, linac, monaco, mosaiq, no, platform, problema, suncheck_machine, sunnuclear, versahd, xvi | L67: [{"id":22950764862363,"value":null},{"id":22951106310811,"value":"consultas_rt"},{"id":22986688179995,"value":"no"},{"id":23570126394907,"value":"problema"},{"id":34267608050075,"value":null},{"id":39065204608155,"value":null},{"id":40011436329115,"value":"01K2MWPZ0X0DMAW9P42PW6X6V4"},{"id":43011722643739,"value":null},{"id":43806479792155,"value":null},{"id":43806495652507,"value":null}]
A68: 9663 | B68: Comando se camilla suelto | C68: closed | D68: normal | E68: incident | F68: 45974.58 | G68: 45982.887 | H68: 14741543428379 | I68: 26080982926747 | J68: 19579468718875 | K68: elekta, físico, hardware_y_software, hexapod, iview, linac, monaco, mosaiq, no, platform, problema, suncheck, suncheck_machine, sunnuclear, versahd, xvi | L68: [{"id":22950764862363,"value":null},{"id":22951106310811,"value":"suncheck"},{"id":22986688179995,"value":"no"},{"id":23570126394907,"value":"problema"},{"id":34267608050075,"value":null},{"id":39065204608155,"value":null},{"id":40011436329115,"value":"01K2MWPZ0X0DMAW9P42PW6X6V4"},{"id":43011722643739,"value":null},{"id":43806479792155,"value":null},{"id":43806495652507,"value":null}]
A69: 9661 | B69: Interlock reflector MLC VERSA 1 | C69: closed | D69: high | E69: incident | F69: 45973.838 | G69: 46011.634 | H69: 14741389938587 | I69: 20254020292379 | J69: 19579474867355 | K69: cabezal_agility, elekta, físico, hexapod, no, problema, versahd | L69: [{"id":22950764862363,"value":null},{"id":22951106310811,"value":"cabezal_agility"},{"id":22986688179995,"value":"no"},{"id":23570126394907,"value":"problema"},{"id":34267608050075,"value":null},{"id":39065204608155,"value":null},{"id":40011436329115,"value":"01K2MWVQJ3DHXN1BYF1WF54DC4"},{"id":43011722643739,"value":null},{"id":43806479792155,"value":null},{"id":43806495652507,"value":null}]
A70: 9660 | B70: Falla MLC equipo detenido | C70: closed | D70: high | E70: incident | F70: 45972.684 | G70: 45990.52 | H70: 14741597726619 | I70: 20254020299547 | J70: 22297930568347 | K70: acelerador_lineal, elekta, físico, hardware_y_software, hexapod, iba, iguide, iview, monaco, monacosim, mosaiq, requerimiento, rtp99, si, tcs, versahd, xvi | L70: [{"id":22950764862363,"value":null},{"id":22951106310811,"value":"acelerador_lineal"},{"id":22986688179995,"value":"si"},{"id":23570126394907,"value":"requerimiento"},{"id":34267608050075,"value":"tcs"},{"id":39065204608155,"value":null},{"id":40011436329115,"value":"01K2MWN8SVJSHMJQM7F39XXN01"},{"id":43011722643739,"value":null},{"id":43806479792155,"value":null},{"id":43806495652507,"value":null}]
A71: 9654 | B71: El PANEL del XVI DEL AXESSE NO GUARDAR COMPLETAMENTE | C71: closed | D71: high | E71: incident | F71: 45967.859 | G71: 45989.63 | H71: 14741297259931 | I71: 20254050952475 | J71: 27816237178267 | K71: axesse, braquiterapia, clarity, elekta, físico, hardware_y_software, infinity, monaco, mosaiq, no, problema | L71: [{"id":22950764862363,"value":null},{"id":22951106310811,"value":"clarity"},{"id":22986688179995,"value":"no"},{"id":23570126394907,"value":"problema"},{"id":34267608050075,"value":null},{"id":39065204608155,"value":null},{"id":40011436329115,"value":"01K2MVY8Y64ADSZN89S82WQWXZ"},{"id":43011722643739,"value":null},{"id":43806479792155,"value":null},{"id":43806495652507,"value":null}]
A72: 9652 | B72: Linac sin pantallas | C72: closed | D72: normal | E72: incident | F72: 45967.497 | G72: 45975.51 | H72: 14741543428379 | I72: 26080982926747 | J72: 14481448391451 | K72: acelerador_lineal, elekta, físico, hardware_y_software, hexapod, iview, linac, monaco, mosaiq, no, platform, problema, suncheck_machine, sunnuclear, versahd, xvi | L72: [{"id":22950764862363,"value":null},{"id":22951106310811,"value":"acelerador_lineal"},{"id":22986688179995,"value":"no"},{"id":23570126394907,"value":"problema"},{"id":34267608050075,"value":null},{"id":39065204608155,"value":null},{"id":40011436329115,"value":"01K2MWPZ0X0DMAW9P42PW6X6V4"},{"id":43011722643739,"value":null},{"id":43806479792155,"value":null},{"id":43806495652507,"value":null}]
A73: 9630 | B73: Problema datos antiguos paciente | C73: closed | D73: normal | E73: incident | F73: 45958.485 | G73: 45977.666 | H73: 14741543428379 | I73: 40109334283675 | J73: 14481448391451 | K73: elekta, hardware_y_software, hexapod, iview, linac, monaco, monaco_tps, mosaiq, no, platform, suncheck_machine, sunnuclear, tarea, versahd, xvi | L73: [{"id":22950764862363,"value":null},{"id":22951106310811,"value":"monaco_tps"},{"id":22986688179995,"value":"no"},{"id":23570126394907,"value":"tarea"},{"id":34267608050075,"value":null},{"id":39065204608155,"value":null},{"id":40011436329115,"value":"01K2MWPZ0X0DMAW9P42PW6X6V4"},{"id":43011722643739,"value":null},{"id":43806479792155,"value":null},{"id":43806495652507,"value":null}]
A74: 9628 | B74: Equipo se detiene por problema en MLC | C74: closed | D74: urgent | E74: incident | F74: 45957.734 | G74: 45991.579 | H74: 14741318546075 | I74: 36182421530907 | J74: 20210900681499 | K74: agility, elekta, no, problema, sinergy, suncheck, versahd | L74: [{"id":22950764862363,"value":null},{"id":22951106310811,"value":"suncheck"},{"id":22986688179995,"value":"no"},{"id":23570126394907,"value":"problema"},{"id":34267608050075,"value":null},{"id":39065204608155,"value":null},{"id":40011436329115,"value":"01K2MWJ4ARZRVMA1V6XFP5Y5E4"},{"id":43011722643739,"value":null},{"id":43806479792155,"value":null},{"id":43806495652507,"value":null}]
A75: 9627 | B75: Asunto: consulta a elekta por comportamiento de DLG | C75: open | D75: high | E75: incident | F75: 45957.549 | G75: 46008.513 | H75: 14741597726619 | I75: 20254020299291 | K75: cabezal_agility, elekta, físico, hardware_y_software, hexapod, iba, iguide, iview, monaco, monacosim, mosaiq, no, problema, rtp99, tcs, versahd, xvi | L75: [{"id":22950764862363,"value":null},{"id":22951106310811,"value":"cabezal_agility"},{"id":22986688179995,"value":"no"},{"id":23570126394907,"value":"problema"},{"id":34267608050075,"value":"tcs"},{"id":39065204608155,"value":null},{"id":40011436329115,"value":"01K2MWN8SVJSHMJQM7F39XXN01"},{"id":43011722643739,"value":null},{"id":43806479792155,"value":null},{"id":43806495652507,"value":null}]
A76: 9626 | B76: Fan Detection Error en CCP VERSA 1 | C76: closed | D76: high | E76: incident | F76: 45957.528 | G76: 45958.878 | H76: 14741389938587 | I76: 20254020292379 | J76: 22968357015195 | K76: closed_by_merge, elekta, físico, hardware_y_software, hexapod, media, monaco, mosaiq, no, on_hold_1h, problema, versahd | L76: [{"id":22950764862363,"value":null},{"id":22951106310811,"value":""},{"id":22986688179995,"value":"no"},{"id":23570126394907,"value":"problema"},{"id":34267608050075,"value":null},{"id":39065204608155,"value":null},{"id":40011436329115,"value":"01K2MWVQJ3DHXN1BYF1WF54DC4"},{"id":43011722643739,"value":null},{"id":43806479792155,"value":null},{"id":43806495652507,"value":null}]
A77: 9624 | B77: Re: [E&G Medical Systems] Asunto: Xvi malo | C77: closed | D77: normal | E77: incident | F77: 45954.727 | G77: 45958.741 | H77: 14741543428379 | I77: 26080982926747 | J77: 14481448391451 | K77: elekta, físico, hardware_y_software, hexapod, iview, linac, monaco, mosaiq, no, platform, problema, suncheck, suncheck_machine, sunnuclear, versahd, xvi | L77: [{"id":22950764862363,"value":null},{"id":22951106310811,"value":"suncheck"},{"id":22986688179995,"value":"no"},{"id":23570126394907,"value":"problema"},{"id":34267608050075,"value":null},{"id":39065204608155,"value":null},{"id":40011436329115,"value":null},{"id":43011722643739,"value":null},{"id":43806479792155,"value":null},{"id":43806495652507,"value":null}]
A78: 9623 | B78: Falla en adquisición de CBCT | C78: closed | D78: normal | E78: incident | F78: 45954.639 | G78: 45961.785 | H78: 14741318546075 | I78: 36182421530907 | J78: 20210900681499 | K78: agility, elekta, problema, si, sinergy, sistema_camilla_precise, supervisor_de_equipo_médicos | L78: [{"id":22950764862363,"value":null},{"id":22951106310811,"value":"sistema_camilla_precise"},{"id":22986688179995,"value":"si"},{"id":23570126394907,"value":"problema"},{"id":34267608050075,"value":null},{"id":39065204608155,"value":null},{"id":40011436329115,"value":"01K2MWJ4ARZRVMA1V6XFP5Y5E4"},{"id":43011722643739,"value":null},{"id":43806479792155,"value":null},{"id":43806495652507,"value":null}]
A79: 9620 | B79: Problema almacenamiento XVI | C79: closed | D79: normal | E79: incident | F79: 45953.739 | G79: 45962.756 | H79: 14741543428379 | I79: 40109334283675 | J79: 14481448391451 | K79: elekta, hardware_y_software, hexapod, iview, linac, monaco, mosaiq, no, platform, requerimiento, sistema_de_imagen_cbct_xvi, suncheck_machine, sunnuclear, versahd, xvi | L79: [{"id":22950764862363,"value":null},{"id":22951106310811,"value":"sistema_de_imagen_cbct_xvi"},{"id":22986688179995,"value":"no"},{"id":23570126394907,"value":"requerimiento"},{"id":34267608050075,"value":null},{"id":39065204608155,"value":null},{"id":40011436329115,"value":"01K2MWPZ0X0DMAW9P42PW6X6V4"},{"id":43011722643739,"value":null},{"id":43806479792155,"value":null},{"id":43806495652507,"value":null}]
A80: 9617 | B80: Problemas en posición brazo de tubo de rx | C80: closed | D80: normal | E80: incident | F80: 45953.478 | G80: 45961.785 | H80: 14741318546075 | I80: 36182421530907 | J80: 20210900681499 | K80: acelerador_lineal, agility, elekta, no, problema, supervisor_de_equipo_médicos, versahd | L80: [{"id":22950764862363,"value":null},{"id":22951106310811,"value":"acelerador_lineal"},{"id":22986688179995,"value":"no"},{"id":23570126394907,"value":"problema"},{"id":34267608050075,"value":null},{"id":39065204608155,"value":null},{"id":40011436329115,"value":"01K2MWKNK7SBBFQAXJYFH5C7RR"},{"id":43011722643739,"value":null},{"id":43806479792155,"value":null},{"id":43806495652507,"value":null}]
A81: 9616 | B81: Equipo detenido por Table Clutch | C81: closed | D81: urgent | E81: incident | F81: 45953.423 | G81: 45958.651 | H81: 14741318546075 | I81: 36182421530907 | J81: 20210900681499 | K81: agility, elekta, hardware_y_software, monaco, mosaiq, problema, si, sinergy, suncheck, suncheck_machine, sunnuclear, supervisor_de_equipo_médicos, versahd | L81: [{"id":22950764862363,"value":null},{"id":22951106310811,"value":"suncheck"},{"id":22986688179995,"value":"si"},{"id":23570126394907,"value":"problema"},{"id":34267608050075,"value":null},{"id":39065204608155,"value":null},{"id":40011436329115,"value":"01K2MWJ4ARZRVMA1V6XFP5Y5E4"},{"id":43011722643739,"value":null},{"id":43806479792155,"value":null},{"id":43806495652507,"value":null}]
A82: 9607 | B82: Dose rate mon Infinity | C82: closed | D82: normal | E82: incident | F82: 45951.489 | G82: 45956.566 | H82: 14741297259931 | I82: 23562920769947 | J82: 20210900681499 | K82: acelerador_lineal, axesse, elekta, físico, infinity, no, problema | L82: [{"id":22950764862363,"value":null},{"id":22951106310811,"value":"acelerador_lineal"},{"id":22986688179995,"value":"no"},{"id":23570126394907,"value":"problema"},{"id":34267608050075,"value":null},{"id":39065204608155,"value":null},{"id":40011436329115,"value":"01K2MWEACAGHS4HXG14TE1Y3QE"},{"id":43011722643739,"value":null},{"id":43806479792155,"value":null},{"id":43806495652507,"value":null}]
A83: 9599 | B83: FALLA apagado automatico del Integrity - se requiere asistencia de ingeniero en terreno - Equipo Detenido | C83: closed | D83: urgent | E83: incident | F83: 45946.773 | G83: 45950.906 | H83: 14741593614363 | I83: 20254050947483 | J83: 19579474867355 | K83: elekta, físico, infinity, integrity, iview, linac, no, problema, xvi | L83: [{"id":22950764862363,"value":null},{"id":22951106310811,"value":"integrity"},{"id":22986688179995,"value":"no"},{"id":23570126394907,"value":"problema"},{"id":34267608050075,"value":null},{"id":39065204608155,"value":null},{"id":40011436329115,"value":"01K2MWR2KCZK72HY0ZV2CSMFTN"},{"id":43011722643739,"value":null},{"id":43806479792155,"value":null},{"id":43806495652507,"value":null}]
A84: 9598 | B84: Upgrade Monaco 6.2.3 Oncorad | C84: closed | D84: normal | E84: incident | F84: 45946.646 | G84: 45968.538 | H84: 14742056643483 | I84: 20254050950939 | J84: 28818463039515 | K84: brachy, comapact, compact, consultas, elekta, flexitron, físico, hardware_y_software, monaco, monaco_tps, no | L84: [{"id":22950764862363,"value":null},{"id":22951106310811,"value":"monaco_tps"},{"id":22986688179995,"value":"no"},{"id":23570126394907,"value":"consultas"},{"id":34267608050075,"value":"flexitron"},{"id":39065204608155,"value":null},{"id":40011436329115,"value":null},{"id":43011722643739,"value":null},{"id":43806479792155,"value":null},{"id":43806495652507,"value":null}]
A85: 9592 | B85: Interlock Table Long | C85: closed | D85: normal | E85: incident | F85: 45945.485 | G85: 46004.81 | H85: 14741543428379 | I85: 26080969273499 | J85: 19579468718875 | K85: elekta, físico, hardware_y_software, hexapod, iview, linac, monaco, mosaiq, no, platform, requerimiento, sistema_camilla_precise, suncheck_machine, sunnuclear, versahd, xvi | L85: [{"id":22950764862363,"value":null},{"id":22951106310811,"value":"sistema_camilla_precise"},{"id":22986688179995,"value":"no"},{"id":23570126394907,"value":"requerimiento"},{"id":34267608050075,"value":null},{"id":39065204608155,"value":null},{"id":40011436329115,"value":"01K2MWPZ0X0DMAW9P42PW6X6V4"},{"id":43011722643739,"value":null},{"id":43806479792155,"value":null},{"id":43806495652507,"value":null}]
A86: 9590 | B86: Derrame fluido sobre gantry | C86: closed | D86: normal | E86: incident | F86: 45944.588 | G86: 45948.84 | H86: 14741543428379 | I86: 26080969273499 | J86: 19579468718875 | K86: cabezal_agility, elekta, físico, hardware_y_software, hexapod, iview, linac, monaco, mosaiq, médico, no, platform, requerimiento, suncheck_machine, sunnuclear, versahd, xvi | L86: [{"id":22950764862363,"value":null},{"id":22951106310811,"value":"cabezal_agility"},{"id":22986688179995,"value":"no"},{"id":23570126394907,"value":"requerimiento"},{"id":34267608050075,"value":null},{"id":39065204608155,"value":null},{"id":40011436329115,"value":"01K2MWPZ0X0DMAW9P42PW6X6V4"},{"id":43011722643739,"value":null},{"id":43806479792155,"value":null},{"id":43806495652507,"value":null}]
A87: 9589 | B87: Equipo con error dose rate mon | C87: closed | D87: urgent | E87: incident | F87: 45944.578 | G87: 45950.906 | H87: 14741318546075 | I87: 36182421530907 | J87: 19579474867355 | K87: acelerador_lineal, agility, elekta, problema, si, sinergy, versahd | L87: [{"id":22950764862363,"value":null},{"id":22951106310811,"value":"acelerador_lineal"},{"id":22986688179995,"value":"si"},{"id":23570126394907,"value":"problema"},{"id":34267608050075,"value":null},{"id":39065204608155,"value":null},{"id":40011436329115,"value":"01K2MWJ4ARZRVMA1V6XFP5Y5E4"},{"id":43011722643739,"value":null},{"id":43806479792155,"value":null},{"id":43806495652507,"value":null}]
... A116: 9498 | B116: Problemas en 10fff | C116: closed | D116: normal | E116: incident | F116: 45905.585 | G116: 45933.83 | H116: 14741543428379 | I116: 26080982926747 | J116: 19579468718875 | K116: acelerador_lineal, elekta, físico, hardware_y_software, hexapod, incidente, iview, linac, monaco, mosaiq, no, platform, suncheck_machine, sunnuclear, versahd, xvi | L116: [{"id":22950764862363,"value":null},{"id":22951106310811,"value":"acelerador_lineal"},{"id":22986688179995,"value":"no"},{"id":23570126394907,"value":"incidente"},{"id":34267608050075,"value":null},{"id":39065204608155,"value":null},{"id":40011436329115,"value":"01K2MWPZ0X0DMAW9P42PW6X6V4"},{"id":43011722643739,"value":null},{"id":43806479792155,"value":null},{"id":43806495652507,"value":null}]
A117: 9496 | B117: otro apagado automático de consola | C117: open | D117: urgent | E117: incident | F117: 45905.536 | G117: 45952.029 | H117: 14741593614363 | I117: 20254050947483 | K117: citrix, elekta, físico, hardware_y_software, infinity, integrity, iview, linac, media, monaco, mosaiq, no, problema, storage, suncheck_machine, sunnuclear, xvi | L117: [{"id":22950764862363,"value":null},{"id":22951106310811,"value":"integrity"},{"id":22986688179995,"value":"no"},{"id":23570126394907,"value":"problema"},{"id":34267608050075,"value":null},{"id":39065204608155,"value":null},{"id":40011436329115,"value":"01K2MWR2KCZK72HY0ZV2CSMFTN"},{"id":43011722643739,"value":null},{"id":43806479792155,"value":null},{"id":43806495652507,"value":null}]
A118: 9484 | B118: Error en mosaiq repositorio temporal | C118: closed | D118: normal | E118: incident | F118: 45902.577 | G118: 45916.669 | H118: 14741543428379 | I118: 26080982926747 | J118: 14481448391451 | K118: elekta, físico, hardware_y_software, hexapod, iview, linac, monaco, mosaiq, mosaiq_workstation, no, platform, problema, suncheck_machine, sunnuclear, versahd, xvi | L118: [{"id":22950764862363,"value":null},{"id":22951106310811,"value":"mosaiq_workstation"},{"id":22986688179995,"value":"no"},{"id":23570126394907,"value":"problema"},{"id":34267608050075,"value":null},{"id":39065204608155,"value":null},{"id":40011436329115,"value":"01K2MWPZ0X0DMAW9P42PW6X6V4"},{"id":43011722643739,"value":null},{"id":43806479792155,"value":null},{"id":43806495652507,"value":null}]
A119: 9482 | B119: Conebeam no funciona | C119: closed | D119: urgent | E119: incident | F119: 45902.073 | G119: 45915.669 | H119: 14741318546075 | I119: 36182421530907 | J119: 19579474867355 | K119: agility, elekta, hardware_y_software, problema, si, sinergy, sistema_de_imagen_cbct_xvi, versahd | L119: [{"id":22950764862363,"value":null},{"id":22951106310811,"value":"sistema_de_imagen_cbct_xvi"},{"id":22986688179995,"value":"si"},{"id":23570126394907,"value":"problema"},{"id":34267608050075,"value":null},{"id":39065204608155,"value":null},{"id":40011436329115,"value":"01K2MWJ4ARZRVMA1V6XFP5Y5E4"},{"id":43011722643739,"value":null},{"id":43806479792155,"value":null},{"id":43806495652507,"value":null}]
A120: 9480 | B120: Cambio de Hora equipos APOTECA. | C120: closed | D120: low | E120: incident | F120: 45901.893 | G120: 45912.793 | H120: 15484666348187 | I120: 20254020295195 | J120: 14734559344539 | K120: achemo, apoteca, apoteca_manager, aps, full_risk_week___weekend_pack, hardware_y_software, loccioni, manager, media, meta, no, ps, requerimiento, robot, upi, upo, upo-r | L120: [{"id":22950764862363,"value":"apoteca_manager"},{"id":22951106310811,"value":null},{"id":22986688179995,"value":"no"},{"id":23570126394907,"value":"requerimiento"},{"id":34267608050075,"value":null},{"id":39065204608155,"value":null},{"id":40011436329115,"value":null},{"id":43011722643739,"value":null},{"id":43806479792155,"value":null},{"id":43806495652507,"value":null}]
A121: 9476 | B121: Table long | C121: closed | D121: high | E121: incident | F121: 45898.666 | G121: 45948.84 | H121: 14741543428379 | I121: 26080982926747 | J121: 19579468718875 | K121: elekta, físico, hardware_y_software, hexapod, iview, linac, monaco, mosaiq, no, platform, problema, sistema_camilla_precise, suncheck_machine, sunnuclear, versahd, xvi | L121: [{"id":22950764862363,"value":null},{"id":22951106310811,"value":"sistema_camilla_precise"},{"id":22986688179995,"value":"no"},{"id":23570126394907,"value":"problema"},{"id":34267608050075,"value":null},{"id":39065204608155,"value":null},{"id":40011436329115,"value":"01K2MWPZ0X0DMAW9P42PW6X6V4"},{"id":43011722643739,"value":null},{"id":43806479792155,"value":null},{"id":43806495652507,"value":null}]
A122: 9473 | B122: Problemas con láminas en Suragility | C122: closed | D122: high | E122: incident | F122: 45897.972 | G122: 45947.569 | H122: 14741318546075 | I122: 36182421530907 | J122: 19579474867355 | K122: acelerador_lineal, agility, elekta, no, problema, sinergy | L122: [{"id":22950764862363,"value":null},{"id":22951106310811,"value":"acelerador_lineal"},{"id":22986688179995,"value":"no"},{"id":23570126394907,"value":"problema"},{"id":34267608050075,"value":null},{"id":39065204608155,"value":null},{"id":40011436329115,"value":"01K2MWJ4ARZRVMA1V6XFP5Y5E4"},{"id":43011722643739,"value":null},{"id":43806479792155,"value":null},{"id":43806495652507,"value":null}]
A123: 9471 | B123: Coordinación cambio de hora sábado 06 de Septiembre | C123: closed | D123: normal | E123: incident | F123: 45897.629 | G123: 46007.576 | H123: 14740499786395 | I123: 20254020297371 | J123: 19579487161371 | K123: brachy, elekta, flexitron, hardware_y_software, media, monaco, mosaiq, no, requerimiento, sinergy, supervisor_de_radioterapía, synergy | L123: [{"id":22950764862363,"value":null},{"id":22951106310811,"value":null},{"id":22986688179995,"value":"no"},{"id":23570126394907,"value":"requerimiento"},{"id":34267608050075,"value":"flexitron"},{"id":39065204608155,"value":null},{"id":40011436329115,"value":null},{"id":43011722643739,"value":null},{"id":43806479792155,"value":null},{"id":43806495652507,"value":null}]
A124: 9468 | B124: Falla en panel iview | C124: closed | D124: high | E124: incident | F124: 45895.708 | G124: 45899.751 | H124: 14741318546075 | I124: 36182421530907 | J124: 19579504854939 | K124: agility, elekta, hardware_y_software, monaco, mosaiq, no, problema, sinergy, suncheck, suncheck_machine, sunnuclear, supervisor_de_equipo_médicos, versahd | L124: [{"id":22950764862363,"value":null},{"id":22951106310811,"value":"suncheck"},{"id":22986688179995,"value":"no"},{"id":23570126394907,"value":"problema"},{"id":34267608050075,"value":null},{"id":39065204608155,"value":null},{"id":40011436329115,"value":"01K2MWJ4ARZRVMA1V6XFP5Y5E4"},{"id":43011722643739,"value":null},{"id":43806479792155,"value":null},{"id":43806495652507,"value":null}]
A125: 9461 | B125: Desplazamiento de Tablero Principal del Detector de Area Ludlum - Braquiterapia | C125: closed | D125: low | E125: incident | F125: 45891.683 | G125: 45900.585 | H125: 14742056643483 | I125: 20254050950939 | J125: 19579486425499 | K125: brachy, comapact, compact, elekta, flexitron, físico, hardware_y_software, no, requerimiento | L125: [{"id":22950764862363,"value":null},{"id":22951106310811,"value":null},{"id":22986688179995,"value":"no"},{"id":23570126394907,"value":"requerimiento"},{"id":34267608050075,"value":"flexitron"},{"id":39065204608155,"value":null},{"id":40011436329115,"value":null},{"id":43011722643739,"value":null},{"id":43806479792155,"value":null},{"id":43806495652507,"value":null}]
A126: 9451 | B126: Intermitencia de operación del Suargility | C126: closed | D126: high | E126: incident | F126: 45888.536 | G126: 45895.71 | H126: 14741318546075 | I126: 20254011642523 | J126: 31525538040603 | K126: agility, elekta, hardware_y_software, incidente, monaco, mosaiq, no, sinergy, suncheck, suncheck_machine, sunnuclear, versahd | L126: [{"id":22950764862363,"value":null},{"id":22951106310811,"value":"suncheck"},{"id":22986688179995,"value":"no"},{"id":23570126394907,"value":"incidente"},{"id":34267608050075,"value":null},{"id":39065204608155,"value":null},{"id":40011436329115,"value":"01K2MWJ4ARZRVMA1V6XFP5Y5E4"},{"id":43011722643739,"value":null},{"id":43806479792155,"value":null},{"id":43806495652507,"value":null}]
A127: 9448 | B127: Falla intermitente en adquisición de imágenes CBCT (XVI) | C127: closed | E127: incident | F127: 45887.645 | G127: 45887.648 | H127: 14741543428379 | I127: 40109334283675 | J127: 14481448391451 | K127: closed_by_merge, elekta, error, hardware_y_software, hexapod, iview, linac, monaco, mosaiq, platform, problema, suncheck, suncheck_machine, sunnuclear, versahd, xvi | L127: [{"id":22950764862363,"value":null},{"id":22951106310811,"value":"suncheck"},{"id":22986688179995,"value":null},{"id":23570126394907,"value":"problema"},{"id":34267608050075,"value":null},{"id":39065204608155,"value":null},{"id":40011436329115,"value":null},{"id":43011722643739,"value":null},{"id":43806479792155,"value":null},{"id":43806495652507,"value":null}]
A128: 9447 | B128: RE: Falla intermitente en adquisición de imágenes CBCT (XVI) | C128: closed | D128: normal | E128: incident | F128: 45887.635 | G128: 45914.668 | H128: 14741543428379 | I128: 26080969273499 | J128: 14481448391451 | K128: elekta, error, físico, hardware_y_software, hexapod, iview, linac, monaco, mosaiq, no, platform, problema, sistema_de_imagen_cbct_xvi, suncheck_machine, sunnuclear, versahd, xvi | L128: [{"id":22950764862363,"value":null},{"id":22951106310811,"value":"sistema_de_imagen_cbct_xvi"},{"id":22986688179995,"value":"no"},{"id":23570126394907,"value":"problema"},{"id":34267608050075,"value":null},{"id":39065204608155,"value":null},{"id":40011436329115,"value":"01K2MWPZ0X0DMAW9P42PW6X6V4"},{"id":43011722643739,"value":null},{"id":43806479792155,"value":null},{"id":43806495652507,"value":null}]
A129: 9444 | B129: Dose rate mon | C129: closed | D129: high | E129: incident | F129: 45883.904 | G129: 45895.71 | H129: 20265216319003 | I129: 20254050952987 | J129: 31525538040603 | K129: axesse, barcoding, braquiterapia, dosisoft, elekta, físico, hardware_y_software, infinity, iview, linac, monaco, monacosim, mosaiq, no, problema, storage, versahd, xvi | L129: [{"id":22950764862363,"value":null},{"id":22951106310811,"value":"dosisoft"},{"id":22986688179995,"value":"no"},{"id":23570126394907,"value":"problema"},{"id":34267608050075,"value":null},{"id":39065204608155,"value":null},{"id":40011436329115,"value":"01K2MWGQVK5P8BZ4P54MS8055Q"},{"id":43011722643739,"value":null},{"id":43806479792155,"value":null},{"id":43806495652507,"value":null}]
...

Sheet Tickets_Data
A1: url | B1: id | C1: {=IF( ISNUMBER(MATCH(B2, Reporte_Tickets_Detallado!C:C, 0)), "Vinculado (" & INDEX(Reporte_Tickets_Detallado!B:B, MATCH(B2, Reporte_Tickets_Detallado!C:C, 0)) & ")", "Sin Tarea" )} -> Sin Tarea | D1: created_at | E1: updated_at | F1: generated_timestamp | G1: type | H1: subject | I1: raw_subject | J1: description | K1: priority | L1: status | M1: requester_id | N1: submitter_id | O1: assignee_id | P1: organization_id | Q1: group_id | R1: has_incidents | S1: is_public | T1: custom_status_id | U1: encoded_id | V1: ticket_form_id | W1: brand_id | X1: allow_channelback | Y1: allow_attachments | Z1: from_messaging_channel | AA1: support_type | AB1: via_channel | AC1: satisfaction_score | AD1: tags_list | AE1: CF_22950764862363 | AF1: CF_22951106310811 | AG1: CF_22986688179995 | AH1: CF_23570126394907 | AI1: CF_34267608050075 | AJ1: CF_39065204608155 | AK1: CF_40011436329115 | AL1: CF_43011722643739 | AM1: CF_43806479792155 | AN1: CF_43806495652507
A2: https://eygmedicalsystems.zendesk.com/api/v2/tickets/9805.json | B2: 9805 | C2: {=IF( ISNUMBER(MATCH(B2, Reporte_Tickets_Detallado!C:C, 0)), "Vinculado (" & INDEX(Reporte_Tickets_Detallado!B:B, MATCH(B2, Reporte_Tickets_Detallado!C:C, 0)) & ")", "Sin Tarea" )} -> Sin Tarea | D2: 46034.468 | E2: 46034.689 | F2: 1768235516 | G2: incident | H2: System on water temp | I2: System on water temp | J2: Maquina cae a system on por water temp | K2: high | L2: new | M2: 26080982926747 | N2: 26080982926747 | P2: 14741543428379 | Q2: 14481465021595 | R2: FALSE | S2: TRUE | T2: 14481427193115 | U2: 7RX32G-PJ479 | V2: 20427286020763 | W2: 14481427110299 | X2: FALSE | Y2: TRUE | Z2: FALSE | AA2: agent | AB2: email | AC2: unoffered | AD2: elekta, físico, hardware_y_software, hexapod, iview, linac, monaco, mosaiq, no, platform, problema, suncheck, suncheck_machine, sunnuclear, versahd, xvi | AF2: suncheck | AG2: no | AH2: problema | AK2: 01K2MWPZ0X0DMAW9P42PW6X6V4
A3: https://eygmedicalsystems.zendesk.com/api/v2/tickets/9804.json | B3: 9804 | C3: {=IF( ISNUMBER(MATCH(B3, Reporte_Tickets_Detallado!C:C, 0)), "Vinculado (" & INDEX(Reporte_Tickets_Detallado!B:B, MATCH(B3, Reporte_Tickets_Detallado!C:C, 0)) & ")", "Sin Tarea" )} -> Sin Tarea | D3: 46031.721 | E3: 46034.753 | F3: 1768241069 | G3: incident | H3: Calibración hexapod | I3: Calibración hexapod | J3: Estimados, Les escribo ya que la prueba diaria de la hexapod esta presentando una desviación respecto a los láseres. Cuando podrían venir para realizar la calibración? Nosotros proponemos el que sea el día martes 13 de enero. Quedamos atentos. Muchas gracias. | K3: high | L3: pending | M3: 20254050952987 | N3: 20254050952987 | P3: 20265216319003 | Q3: 14481465021595 | R3: FALSE | S3: TRUE | T3: 14952899745563 | U3: Z4W9K5-JDDWP | V3: 20427286020763 | W3: 14481427110299 | X3: FALSE | Y3: TRUE | Z3: FALSE | AA3: agent | AB3: web | AC3: unoffered | AD3: axesse, barcoding, braquiterapia, dosisoft, elekta, físico, hardware_y_software, infinity, iview, linac, monaco, monacosim, mosaiq, no, problema, storage, versahd, xvi | AF3: dosisoft | AG3: no | AH3: problema | AK3: 01K2MWGQVK5P8BZ4P54MS8055Q
A4: https://eygmedicalsystems.zendesk.com/api/v2/tickets/9801.json | B4: 9801 | C4: {=IF( ISNUMBER(MATCH(B4, Reporte_Tickets_Detallado!C:C, 0)), "Vinculado (" & INDEX(Reporte_Tickets_Detallado!B:B, MATCH(B4, Reporte_Tickets_Detallado!C:C, 0)) & ")", "Sin Tarea" )} -> Vinculado (3459) | D4: 46030.804 | E4: 46032.543 | F4: 1768050106 | G4: incident | H4: Gantry Stop-Infinity detenido - se requiere atencion en terreno lo antes posible | I4: Gantry Stop-Infinity detenido - se requiere atencion en terreno lo antes posible | J4: Gantry Stop, Infinity detenido - se requiere atencion en terreno lo antes posible. Los esperamos. Gracias ! | K4: urgent | L4: solved | M4: 20254050947483 | N4: 20254050947483 | O4: 22297930568347 | P4: 14741593614363 | Q4: 14481465021595 | R4: FALSE | S4: TRUE | T4: 14481439499675 | U4: PWR9K5-G59ML | V4: 20427286020763 | W4: 14481427110299 | X4: FALSE | Y4: TRUE | Z4: FALSE | AA4: agent | AB4: web | AC4: offered | AD4: citrix, elekta, físico, hardware_y_software, infinity, integrity, iview, linac, media, monaco, mosaiq, problema, si, storage, suncheck_machine, sunnuclear, xvi | AF4: integrity | AG4: si | AH4: problema | AK4: 01K2MWR2KCZK72HY0ZV2CSMFTN
A5: https://eygmedicalsystems.zendesk.com/api/v2/tickets/9800.json | B5: 9800 | C5: {=IF( ISNUMBER(MATCH(B5, Reporte_Tickets_Detallado!C:C, 0)), "Vinculado (" & INDEX(Reporte_Tickets_Detallado!B:B, MATCH(B5, Reporte_Tickets_Detallado!C:C, 0)) & ")", "Sin Tarea" )} -> Sin Tarea | D5: 46030.601 | E5: 46030.601 | F5: 1767882303 | G5: incident | H5: Solicitud de actualizacion de licencias productos Sunnuclear | I5: Solicitud de actualizacion de licencias productos Sunnuclear | J5: Estimados, Junto con saludar, solicitamos que se realice de manera urgente la actualizacion de las licencias de los productos de Sunnuclear adquiridos en sede norte correspondientes al contrato asociado al equipo Elekta Infinity. Adjuntamos imagenes de los productos asociados. Quedamos atentos, Saludos cordiales. | K5: urgent | L5: new | M5: 20254050948123 | N5: 20254050948123 | P5: 14741593614363 | Q5: 14481465021595 | R5: FALSE | S5: TRUE | T5: 14481427193115 | U5: Z4RPWR-MNWPP | V5: 20427286020763 | W5: 14481427110299 | X5: FALSE | Y5: TRUE | Z5: FALSE | AA5: agent | AB5: web | AC5: unoffered | AD5: citrix, elekta, físico, hardware_y_software, infinity, integrity, iview, linac, media, monaco, mosaiq, no, problema, storage, suncheck_machine, sunnuclear, xvi | AF5: integrity | AG5: no | AH5: problema | AK5: 01K2MWR2KCZK72HY0ZV2CSMFTN
A6: https://eygmedicalsystems.zendesk.com/api/v2/tickets/9799.json | B6: 9799 | C6: {=IF( ISNUMBER(MATCH(B6, Reporte_Tickets_Detallado!C:C, 0)), "Vinculado (" & INDEX(Reporte_Tickets_Detallado!B:B, MATCH(B6, Reporte_Tickets_Detallado!C:C, 0)) & ")", "Sin Tarea" )} -> Sin Tarea | D6: 46029.469 | E6: 46029.475 | F6: 1767785031 | G6: incident | H6: Interlocks MLC VERSA 1 | I6: Interlocks MLC VERSA 1 | J6: Estimados, Se requiere revision del MLC del VERSA 1 por alta frecuencia de aparicion de interlocks asociados a reflector. Saludos, Manuel. | K6: high | L6: new | M6: 20254020292379 | N6: 20254020292379 | P6: 14741389938587 | Q6: 14481465021595 | R6: FALSE | S6: TRUE | T6: 14481427193115 | U6: 7RK4D2-4MLRX | V6: 20427286020763 | W6: 14481427110299 | X6: FALSE | Y6: TRUE | Z6: FALSE | AA6: agent | AB6: web | AC6: unoffered | AD6: abc, elekta, físico, hardware_y_software, hexapod, media, monaco, mosaiq, no, problema, versahd | AF6: abc | AG6: no | AH6: problema | AK6: 01K2MWVQJ3DHXN1BYF1WF54DC4
A7: https://eygmedicalsystems.zendesk.com/api/v2/tickets/9796.json | B7: 9796 | C7: {=IF( ISNUMBER(MATCH(B7, Reporte_Tickets_Detallado!C:C, 0)), "Vinculado (" & INDEX(Reporte_Tickets_Detallado!B:B, MATCH(B7, Reporte_Tickets_Detallado!C:C, 0)) & ")", "Sin Tarea" )} -> Sin Tarea | D7: 46028.564 | E7: 46032.644 | F7: 1768058884 | G7: incident | H7: Gantry Stop aleatorio en CL2 Infinity | I7: Gantry Stop aleatorio en CL2 Infinity | J7: Buenos dias, Sigue dando Gantry Stop aleatorio, a veces ha dado hasta 8 veces por paciente. Por favor revisar/reparar este viernes 9 de enero a partir de las 7 pm. Muchas gracias ! | K7: urgent | L7: solved | M7: 20254050947483 | N7: 20254050947483 | O7: 22297930568347 | P7: 14741593614363 | Q7: 14481465021595 | R7: FALSE | S7: TRUE | T7: 14481439499675 | U7: 21EL4N-NWWWV | V7: 20427286020763 | W7: 14481427110299 | X7: FALSE | Y7: TRUE | Z7: FALSE | AA7: agent | AB7: web | AC7: good | AD7: citrix, elekta, físico, hardware_y_software, infinity, integrity, iview, linac, media, monaco, mosaiq, no, problema, storage, suncheck_machine, sunnuclear, xvi | AF7: integrity | AG7: no | AH7: problema | AK7: 01K2MWR2KCZK72HY0ZV2CSMFTN
A8: https://eygmedicalsystems.zendesk.com/api/v2/tickets/9795.json | B8: 9795 | C8: {=IF( ISNUMBER(MATCH(B8, Reporte_Tickets_Detallado!C:C, 0)), "Vinculado (" & INDEX(Reporte_Tickets_Detallado!B:B, MATCH(B8, Reporte_Tickets_Detallado!C:C, 0)) & ")", "Sin Tarea" )} -> Sin Tarea | D8: 46028.478 | E8: 46028.478 | F8: 1767698878 | G8: incident | H8: Infinity se apaga solo | I8: Infinity se apaga solo | J8: Infinity se apaga solo, entrega aviso que en 5 min se apagara... luego se tiene que esperar el Time Delay 15 min y volver a efectuar control dosimetrico... esto significa un atraso de 20 minutos aprox. Esta es una falla antigua que se repite cada cierto tiempo, esta pendiente el reemplazo de la UPS de la consola por parte de EyG. Adjunto imagenes de falla. | K8: urgent | L8: new | M8: 20254050947483 | N8: 20254050947483 | P8: 14741593614363 | Q8: 14481465021595 | R8: FALSE | S8: TRUE | T8: 14481427193115 | U8: PW76XJ-1RNLL | V8: 20427286020763 | W8: 14481427110299 | X8: FALSE | Y8: TRUE | Z8: FALSE | AA8: agent | AB8: web | AC8: unoffered | AD8: citrix, elekta, físico, hardware_y_software, infinity, integrity, iview, linac, media, monaco, mosaiq, no, problema, storage, suncheck_machine, sunnuclear, xvi | AF8: integrity | AG8: no | AH8: problema | AK8: 01K2MWR2KCZK72HY0ZV2CSMFTN
A9: https://eygmedicalsystems.zendesk.com/api/v2/tickets/9792.json | B9: 9792 | C9: {=IF( ISNUMBER(MATCH(B9, Reporte_Tickets_Detallado!C:C, 0)), "Vinculado (" & INDEX(Reporte_Tickets_Detallado!B:B, MATCH(B9, Reporte_Tickets_Detallado!C:C, 0)) & ")", "Sin Tarea" )} -> Sin Tarea | D9: 46027.589 | E9: 46027.589 | F9: 1767622111 | G9: incident | H9: Perdida conexión Axesse | I9: Perdida conexión Axesse | J9: Estimados, junto con saludar, escribimos este ticket ya que hemos tenido el problema, de forma intermitente, de una perdida de conexión en el equipo Axesse sin previo aviso, al suceder esto se pierde la conexión con XVI, iView, Hexapod, MLC, etc. La forma en la que lo estamos solucionando es el reinicio completo del equipo. Adjunto una foto con los inhibits que aparecen | K9: normal | L9: new | M9: 23562920769947 | N9: 23562920769947 | P9: 14741297259931 | Q9: 14481465021595 | R9: FALSE | S9: TRUE | T9: 14481427193115 | U9: MWG0G5-GEY4V | V9: 20427286020763 | W9: 14481427110299 | X9: FALSE | Y9: TRUE | Z9: FALSE | AA9: agent | AB9: web | AC9: unoffered | AD9: axesse, braquiterapia, clarity, elekta, físico, hardware_y_software, infinity, monaco, mosaiq, no, problema | AF9: clarity | AG9: no | AH9: problema | AK9: 01K2MVY8Y64ADSZN89S82WQWXZ
A10: https://eygmedicalsystems.zendesk.com/api/v2/tickets/9785.json | B10: 9785 | C10: {=IF( ISNUMBER(MATCH(B10, Reporte_Tickets_Detallado!C:C, 0)), "Vinculado (" & INDEX(Reporte_Tickets_Detallado!B:B, MATCH(B10, Reporte_Tickets_Detallado!C:C, 0)) & ")", "Sin Tarea" )} -> Sin Tarea | D10: 46021.599 | E10: 46032.691 | F10: 1768062910 | G10: incident | H10: Maquina se reinicia sola | I10: Maquina se reinicia sola | J10: Versa se reinicia solo, dos veces. Una al intentar irradiar y la otra al terminar el mismo tratamiento. 20251230_105921.jpg 20251230_105838.jpg 20251230_105805.jpg 20251230_105746.jpg | K10: normal | L10: closed | M10: 26080982926747 | N10: 26080982926747 | O10: 19579468718875 | P10: 14741543428379 | Q10: 14481465021595 | R10: FALSE | S10: TRUE | T10: 14953031074331 | U10: MWLP62-63PW4 | V10: 20427286020763 | W10: 14481427110299 | X10: FALSE | Y10: TRUE | Z10: FALSE | AA10: agent | AB10: email | AC10: offered | AD10: acelerador_lineal, elekta, físico, hardware_y_software, hexapod, iview, linac, monaco, mosaiq, no, platform, problema, suncheck_machine, sunnuclear, versahd, xvi | AF10: acelerador_lineal | AG10: no | AH10: problema | AK10: 01K2MWPZ0X0DMAW9P42PW6X6V4
A11: https://eygmedicalsystems.zendesk.com/api/v2/tickets/9783.json | B11: 9783 | C11: {=IF( ISNUMBER(MATCH(B11, Reporte_Tickets_Detallado!C:C, 0)), "Vinculado (" & INDEX(Reporte_Tickets_Detallado!B:B, MATCH(B11, Reporte_Tickets_Detallado!C:C, 0)) & ")", "Sin Tarea" )} -> Sin Tarea | D11: 46021.533 | E11: 46029.793 | F11: 1767812506 | G11: incident | H11: advertencia Replace Filter - SunSCAN | I11: advertencia Replace Filter - SunSCAN | J11: Estimados EyG: Al usar el SunSCAN, el Reservorio de agua despliega la advertencia: "Replace Filter". Por favor efectuar el reemplazo de este filtro que no fue efectuado en la mantencion recien efectuada por Federico y Franklyn. Adjunto imagen de la advertencia indicada por el Reservorio de agua del SunSCAN. Atte. Andres Perez Veloso | K11: high | L11: pending | M11: 20254050947483 | N11: 20254050947483 | O11: 14734559344539 | P11: 14741593614363 | Q11: 14481465021595 | R11: FALSE | S11: TRUE | T11: 14481437571483 | U11: 7RM077-1XK39 | V11: 20427286020763 | W11: 14481427110299 | X11: FALSE | Y11: TRUE | Z11: FALSE | AA11: agent | AB11: web | AC11: unoffered | AD11: citrix, elekta, físico, hardware_y_software, infinity, iview, linac, media, monaco, mosaiq, no, on_hold_1h, problema, storage, suncheck, suncheck_machine, sunnuclear, xvi | AF11: suncheck | AG11: no | AH11: problema | AK11: 01K2MWR2KCZK72HY0ZV2CSMFTN
A12: https://eygmedicalsystems.zendesk.com/api/v2/tickets/9782.json | B12: 9782 | C12: {=IF( ISNUMBER(MATCH(B12, Reporte_Tickets_Detallado!C:C, 0)), "Vinculado (" & INDEX(Reporte_Tickets_Detallado!B:B, MATCH(B12, Reporte_Tickets_Detallado!C:C, 0)) & ")", "Sin Tarea" )} -> Sin Tarea | D12: 46021.512 | E12: 46028.724 | F12: 1767720180 | G12: incident | H12: falla humidificador y AACC del bunker del Infinity | I12: falla humidificador y AACC del bunker del Infinity | J12: Estimados EyG, Fallo el sistema de aire acondicionado y el humidificador del bunker del Infinity. La sala se encuentra ya en 24 grados Celcius. Por favor atender lo antes posible en terreno. Muchas gracias. | K12: low | L12: closed | M12: 20254050947483 | N12: 20254050947483 | O12: 19579474867355 | P12: 14741593614363 | Q12: 14481465021595 | R12: FALSE | S12: TRUE | T12: 14481439499675 | U12: 056NX1-NY9MX | V12: 20427286020763 | W12: 14481427110299 | X12: FALSE | Y12: TRUE | Z12: FALSE | AA12: agent | AB12: web | AC12: good | AD12: acelerador_lineal, elekta, físico, linac, no, problema | AF12: acelerador_lineal | AG12: no | AH12: problema | AK12: 01K2MWR2KCZK72HY0ZV2CSMFTN
A13: https://eygmedicalsystems.zendesk.com/api/v2/tickets/9781.json | B13: 9781 | C13: {=IF( ISNUMBER(MATCH(B13, Reporte_Tickets_Detallado!C:C, 0)), "Vinculado (" & INDEX(Reporte_Tickets_Detallado!B:B, MATCH(B13, Reporte_Tickets_Detallado!C:C, 0)) & ")", "Sin Tarea" )} -> Vinculado (3453) | D13: 46020.746 | E13: 46026.043 | F13: 1767488485 | G13: incident | H13: Equipo detenido por Problema con "Tasa de dosis baja Canal A" y B | I13: Equipo detenido por Problema con "Tasa de dosis baja Canal A" y B | J13: Tras accionamiento accidental de un botón de parada de emergencia del equipo, al hacer el control diario arroja "Tasa dosis Baja canal A" y lo mismo para el B. Se realiza recalibración de las cámaras de UM del cabezal, pero problema persiste. Se requiere asistencia urgente, ya que el equipo se encuentra detenido. | K13: urgent | L13: pending | M13: 38368479928987 | N13: 38368479928987 | P13: 14742026913435 | Q13: 14481465021595 | R13: FALSE | S13: TRUE | T13: 14481437571483 | U13: PEDLX3-MGYYM | V13: 20427286020763 | W13: 14481427110299 | X13: FALSE | Y13: TRUE | Z13: FALSE | AA13: agent | AB13: web | AC13: unoffered | AD13: acelerador_lineal, braquiterapia, compact, elekta, hardware_y_software, monaco, monacosim, mosaiq, requerimiento, si, tcs, xio | AF13: acelerador_lineal | AG13: si | AH13: requerimiento | AI13: tcs | AK13: 01K2MXCF9WW205P1YQ3PCD50A9
A14: https://eygmedicalsystems.zendesk.com/api/v2/tickets/9778.json | B14: 9778 | C14: {=IF( ISNUMBER(MATCH(B14, Reporte_Tickets_Detallado!C:C, 0)), "Vinculado (" & INDEX(Reporte_Tickets_Detallado!B:B, MATCH(B14, Reporte_Tickets_Detallado!C:C, 0)) & ")", "Sin Tarea" )} -> Vinculado (3451) | D14: 46020.709 | E14: 46032.607 | F14: 1768055609 | G14: incident | H14: Reaparición falla “Gantry Stop” – CL02 Infinity / Ticket 9774 | I14: Reaparición falla “Gantry Stop” – CL02 Infinity / Ticket 9774 | J14: Estimados EyG, Junto con saludar cordialmente, informo que, tal como ocurrió el miércoles 24, ha vuelto a presentarse la falla **“Gantry Stop”** en el acelerador **Infinity**, la cual **detiene la entrega** y requiere **despeje manual desde consola**, para luego **recargar al paciente** y reanudar el tratamiento. La ocurrencia está siendo **aleatoria** en algunos pacientes; dichos casos están siendo copiados como **“Copy to Service”** para su análisis. Cabe señalar que el día miércoles, en el marco del **Ticket 9774**, EyG realizó un proceso de **Learning**, además de **lubricación, limpieza y ajustes**. No obstante, se mantiene **pendiente** la intervención correctiva principal: el **cambio del motor de gantry previamente diagnosticado con falla**. En este contexto, y considerando que estas anomalías podrían estar relacionadas, reitero nuestra disponibilidad para **entregar el equipo a partir del mediodía del próximo miércoles 31 de diciembre**, con el objetivo de **abordar integralmente los problemas asociados al gantry** y concretar la acción correctiva pendiente. Agradeceré confirmar **a la brevedad**: 1. si la intervención del **31/12 desde 12:00** queda **agendada y confirmada**, y 2. el **plan de trabajo** y recursos/partes requeridas (incluyendo confirmación del **motor**), para asegurar la resolución definitiva. Adjunto imagen de esta falla y quedo atento a su respuesta. Saludos cordiales, Andres Perez Veloso | K14: urgent | L14: closed | M14: 20254050947483 | N14: 20254050947483 | O14: 19579474867355 | P14: 14741593614363 | Q14: 14481465021595 | R14: FALSE | S14: TRUE | T14: 14481439499675 | U14: 04R016-RNRK0 | V14: 20427286020763 | W14: 14481427110299 | X14: FALSE | Y14: TRUE | Z14: FALSE | AA14: agent | AB14: web | AC14: offered | AD14: acelerador_lineal, elekta, físico, hardware_y_software, infinity, linac, no, problema | AF14: acelerador_lineal | AG14: no | AH14: problema | AK14: 01K2MWR2KCZK72HY0ZV2CSMFTN
A15: https://eygmedicalsystems.zendesk.com/api/v2/tickets/9775.json | B15: 9775 | C15: {=IF( ISNUMBER(MATCH(B15, Reporte_Tickets_Detallado!C:C, 0)), "Vinculado (" & INDEX(Reporte_Tickets_Detallado!B:B, MATCH(B15, Reporte_Tickets_Detallado!C:C, 0)) & ")", "Sin Tarea" )} -> Vinculado (3442) | D15: 46015.737 | E15: 46024.614 | F15: 1767365049 | G15: incident | H15: DOSE RATE MON 6MeV INFINITY | I15: DOSE RATE MON 6MeV INFINITY | J15: TASA DE DOSIS DE 6MeV SE CAE EN MODO CLINICO IMPOSIBILITANDO IRRADIAR A LOS PACIENTES, SERA UN SINTOMA DE CAMBIO DE GUN DEL LINAC? Quedo atento. | K15: normal | L15: closed | M15: 20254050952347 | N15: 20254050952347 | O15: 19579474867355 | P15: 14741297259931 | Q15: 14481465021595 | R15: FALSE | S15: TRUE | T15: 14481439499675 | U15: PE9WNV-2Z5YM | V15: 20427286020763 | W15: 14481427110299 | X15: FALSE | Y15: TRUE | Z15: FALSE | AA15: agent | AB15: web | AC15: offered | AD15: acelerador_lineal, elekta, físico, infinity, no, problema | AF15: acelerador_lineal | AG15: no | AH15: problema | AK15: 01K2MWEACAGHS4HXG14TE1Y3QE
A16: https://eygmedicalsystems.zendesk.com/api/v2/tickets/9774.json | B16: 9774 | C16: {=IF( ISNUMBER(MATCH(B16, Reporte_Tickets_Detallado!C:C, 0)), "Vinculado (" & INDEX(Reporte_Tickets_Detallado!B:B, MATCH(B16, Reporte_Tickets_Detallado!C:C, 0)) & ")", "Sin Tarea" )} -> Vinculado (3441) | D16: 46015.736 | E16: 46019.908 | F16: 1766958409 | G16: incident | H16: falla Gantry Stop - no puedo hacer QA de paciente - Equipo detenido | I16: falla Gantry Stop - no puedo hacer QA de paciente - Equipo detenido | J16: Falla Gantry Stop que impide terminar de irradiar paciente que necesito efectuar control QA especifico. Equipo CL2 Infinity detenido. Se requiere la asistencia en terreno lo antes posible. Por favor indicar llegada del ingeniero a terreno, lo puedo esperar (estoy de turno hasta las 20 horas de hoy, haciendo mediciones, QA, y también colaborando con los ingenieros que están trabajando en el otro acelerador del INC ). Nota = adjunto dos imágenes describiendo esta falla, indica que el gantry esta fuera de tolerancia o fallo en alcanzar el valor de parada en el arco. Podría tener relación con el motor del gantry que se tiene que reemplazar, para que por favor traigan este repuesto también. | K16: urgent | L16: closed | M16: 20254050947483 | N16: 20254050947483 | O16: 20210900681499 | P16: 14741593614363 | Q16: 14481465021595 | R16: FALSE | S16: TRUE | T16: 14481439499675 | U16: PE9WRL-LDWLL | V16: 20427286020763 | W16: 14481427110299 | X16: FALSE | Y16: TRUE | Z16: FALSE | AA16: agent | AB16: web | AC16: good | AD16: citrix, elekta, físico, hardware_y_software, infinity, integrity, iview, linac, media, monaco, mosaiq, problema, si, storage, suncheck_machine, sunnuclear, xvi | AF16: integrity | AG16: si | AH16: problema | AK16: 01K2MWR2KCZK72HY0ZV2CSMFTN
A17: https://eygmedicalsystems.zendesk.com/api/v2/tickets/9770.json | B17: 9770 | C17: {=IF( ISNUMBER(MATCH(B17, Reporte_Tickets_Detallado!C:C, 0)), "Vinculado (" & INDEX(Reporte_Tickets_Detallado!B:B, MATCH(B17, Reporte_Tickets_Detallado!C:C, 0)) & ")", "Sin Tarea" )} -> Sin Tarea | D17: 46013.655 | E17: 46033.618 | F17: 1768142987 | G17: incident | H17: Water Temp | I17: Water Temp | J17: Estimados, tenemos máquina detenida por water temp. No es posible realizar ningún movimiento en la máquina. El chiller funciona correctamente. Esperamos su asistencia. Saludos | K17: urgent | L17: closed | M17: 20254050953243 | N17: 20254050953243 | O17: 20210900681499 | P17: 20265216319003 | Q17: 14481465021595 | R17: FALSE | S17: TRUE | T17: 14481439499675 | U17: ZELMX9-KXPZ1 | V17: 20427286020763 | W17: 14481427110299 | X17: FALSE | Y17: TRUE | Z17: FALSE | AA17: agent | AB17: web | AC17: offered | AD17: axesse, barcoding, braquiterapia, dosisoft, elekta, físico, hardware_y_software, infinity, iview, linac, monaco, monacosim, mosaiq, problema, si, storage, versahd, xvi | AF17: dosisoft | AG17: si | AH17: problema | AK17: 01K2MWGQVK5P8BZ4P54MS8055Q
A18: https://eygmedicalsystems.zendesk.com/api/v2/tickets/9768.json | B18: 9768 | C18: {=IF( ISNUMBER(MATCH(B18, Reporte_Tickets_Detallado!C:C, 0)), "Vinculado (" & INDEX(Reporte_Tickets_Detallado!B:B, MATCH(B18, Reporte_Tickets_Detallado!C:C, 0)) & ")", "Sin Tarea" )} -> Sin Tarea | D18: 46013.482 | E18: 46018.543 | F18: 1766840484 | G18: incident | H18: Ruido intermitente en el rack del Versa | I18: Ruido intermitente en el rack del Versa | J18: Hola: Escribo porque en los últimos días a veces se ha escuchado un sonido intermitente en el rack. Ruido como del ventilador de un pc pero más fuerte, aparece solo a veces durante los tratamientos y desaparece de la nada. No sabemos exactamente de qué computador en específico. Quedo atenta, ¡Saludos! Constanza | K18: normal | L18: pending | M18: 20254020299547 | N18: 20254020299547 | O18: 22297930568347 | P18: 14741597726619 | Q18: 14481465021595 | R18: FALSE | S18: TRUE | T18: 14481437571483 | U18: 04LLNK-Z97WX | V18: 20427286020763 | W18: 14481427110299 | X18: FALSE | Y18: TRUE | Z18: FALSE | AA18: agent | AB18: web | AC18: unoffered | AD18: consultas, elekta, físico, hardware_y_software, hexapod, iba, iguide, iview, monaco, monacosim, mosaiq, no, on_hold_1h, rtp99, tcs, versahd, xvi | AG18: no | AH18: consultas | AI18: tcs | AK18: 01K2MWN8SVJSHMJQM7F39XXN01
A19: https://eygmedicalsystems.zendesk.com/api/v2/tickets/9764.json | B19: 9764 | C19: {=IF( ISNUMBER(MATCH(B19, Reporte_Tickets_Detallado!C:C, 0)), "Vinculado (" & INDEX(Reporte_Tickets_Detallado!B:B, MATCH(B19, Reporte_Tickets_Detallado!C:C, 0)) & ")", "Sin Tarea" )} -> Vinculado (3438) | D19: 46010.494 | E19: 46017.642 | F19: 1766762704 | G19: incident | H19: Multiples interlocks mas charco de agua en sala de maquinas de origen desconocido | I19: Multiples interlocks mas charco de agua en sala de maquinas de origen desconocido | J19: Estimados, Se requiere revision del VERSA 1 por interlocks: Facility 1 State, Temp Diff, Pressure Diff, Diap Rot. Además, el equipo amaneció con un charco de agua de origen desconocido en la sala de máquinas. Equipo detenido. Saludos, Manuel Castrillón. | K19: urgent | L19: closed | M19: 20254020292379 | N19: 20254020292379 | O19: 19579474867355 | P19: 14741389938587 | Q19: 14481465021595 | R19: FALSE | S19: TRUE | T19: 14481439499675 | U19: 76YK5D-M2RX5 | V19: 20427286020763 | W19: 14481427110299 | X19: FALSE | Y19: TRUE | Z19: FALSE | AA19: agent | AB19: web | AC19: offered | AD19: acelerador_lineal, elekta, físico, hexapod, problema, si, versahd | AF19: acelerador_lineal | AG19: si | AH19: problema | AK19: 01K2MWVQJ3DHXN1BYF1WF54DC4
A20: https://eygmedicalsystems.zendesk.com/api/v2/tickets/9762.json | B20: 9762 | C20: {=IF( ISNUMBER(MATCH(B20, Reporte_Tickets_Detallado!C:C, 0)), "Vinculado (" & INDEX(Reporte_Tickets_Detallado!B:B, MATCH(B20, Reporte_Tickets_Detallado!C:C, 0)) & ")", "Sin Tarea" )} -> Sin Tarea | D20: 46009.542 | E20: 46009.542 | F20: 1766062803 | G20: incident | H20: Solicitud de MP Flexitro | I20: Solicitud de MP Flexitro | J20: Estimados a través de este ticket solicito se pueda hacer una MP sin fuente el viernes 16/01/2026. Saludos. | K20: normal | L20: new | M20: 20254050952347 | N20: 20254050952347 | P20: 14741297259931 | Q20: 14481465021595 | R20: FALSE | S20: TRUE | T20: 14481427193115 | U20: ZE64YV-EZMGW | V20: 34266025952155 | W20: 14481427110299 | X20: FALSE | Y20: TRUE | Z20: FALSE | AA20: agent | AB20: web | AC20: unoffered | AD20: axesse, braquiterapia, clarity, elekta, flexitron, físico, hardware_y_software, infinity, monaco, mosaiq, no, requerimiento | AF20: clarity | AG20: no | AH20: requerimiento | AI20: flexitron
A21: https://eygmedicalsystems.zendesk.com/api/v2/tickets/9751.json | B21: 9751 | C21: {=IF( ISNUMBER(MATCH(B21, Reporte_Tickets_Detallado!C:C, 0)), "Vinculado (" & INDEX(Reporte_Tickets_Detallado!B:B, MATCH(B21, Reporte_Tickets_Detallado!C:C, 0)) & ")", "Sin Tarea" )} -> Sin Tarea | D21: 46006.519 | E21: 46006.86 | F21: 1765831147 | G21: incident | H21: Table long | I21: Table long | J21: Table long intermitente | L21: closed | M21: 26080982926747 | N21: 26080982926747 | O21: 19579468718875 | P21: 14741543428379 | Q21: 14481465021595 | R21: FALSE | S21: TRUE | T21: 14481439499675 | U21: 040G0M-XMGX0 | V21: 20427286020763 | W21: 14481427110299 | X21: FALSE | Y21: TRUE | Z21: FALSE | AA21: agent | AB21: email | AC21: unoffered | AD21: closed_by_merge, elekta, físico, hardware_y_software, hexapod, iview, linac, monaco, mosaiq, platform, suncheck, suncheck_machine, sunnuclear, versahd, xvi | AF21: suncheck
A22: https://eygmedicalsystems.zendesk.com/api/v2/tickets/9749.json | B22: 9749 | C22: {=IF( ISNUMBER(MATCH(B22, Reporte_Tickets_Detallado!C:C, 0)), "Vinculado (" & INDEX(Reporte_Tickets_Detallado!B:B, MATCH(B22, Reporte_Tickets_Detallado!C:C, 0)) & ")", "Sin Tarea" )} -> Vinculado (3431) | D22: 46003.519 | E22: 46011.676 | F22: 1766247190 | G22: incident | H22: Dose rate mon | I22: Dose rate mon | J22: Hola José Según conversado, informo que el equipo presenta interlock Dose rate Mon con 6FFF, interrumpiendo tratamientos. Saludos | K22: urgent | L22: closed | M22: 20254020299291 | N22: 20254020299291 | O22: 22297930568347 | P22: 14741597726619 | Q22: 14481465021595 | R22: FALSE | S22: TRUE | T22: 14481439499675 | U22: PE4EN7-XVN0M | V22: 20427286020763 | W22: 14481427110299 | X22: FALSE | Y22: TRUE | Z22: FALSE | AA22: agent | AB22: web | AC22: offered | AD22: acelerador_lineal, elekta, físico, hexapod, iview, no, problema, versahd, xvi | AF22: acelerador_lineal | AG22: no | AH22: problema | AK22: 01K2MWN8SVJSHMJQM7F39XXN01
A23: https://eygmedicalsystems.zendesk.com/api/v2/tickets/9748.json | B23: 9748 | C23: {=IF( ISNUMBER(MATCH(B23, Reporte_Tickets_Detallado!C:C, 0)), "Vinculado (" & INDEX(Reporte_Tickets_Detallado!B:B, MATCH(B23, Reporte_Tickets_Detallado!C:C, 0)) & ")", "Sin Tarea" )} -> Sin Tarea | D23: 46003.493 | E23: 46017.514 | F23: 1766751629 | G23: incident | H23: Importación plan respalado | I23: Importación plan respalado | J23: Buen día, Con gusto de saludar me comunico con usted para solicitar la importación a Monaco de plan previamente respaldado de Jose Gonzalez Yañez (4.278.986-0), plan de prueba en el que se cuantificaba solo 1 sesión Saludos! Sebastián Flores Acuña TM Radioterapia HCM | K23: low | L23: closed | M23: 40109334283675 | N23: 40109334283675 | O23: 14481448391451 | P23: 14741543428379 | Q23: 14481465021595 | R23: FALSE | S23: TRUE | T23: 14953031074331 | U23: 20P4LG-3GDR9 | V23: 20427286020763 | W23: 14481427110299 | X23: FALSE | Y23: TRUE | Z23: FALSE | AA23: agent | AB23: email | AC23: offered | AD23: elekta, hardware_y_software, hexapod, iview, linac, monaco, monaco_tps, mosaiq, no, platform, requerimiento, suncheck_machine, sunnuclear, versahd, xvi | AF23: monaco_tps | AG23: no | AH23: requerimiento | AK23: 01K2MWPZ0X0DMAW9P42PW6X6V4
A24: https://eygmedicalsystems.zendesk.com/api/v2/tickets/9747.json | B24: 9747 | C24: {=IF( ISNUMBER(MATCH(B24, Reporte_Tickets_Detallado!C:C, 0)), "Vinculado (" & INDEX(Reporte_Tickets_Detallado!B:B, MATCH(B24, Reporte_Tickets_Detallado!C:C, 0)) & ")", "Sin Tarea" )} -> Sin Tarea | D24: 46003.49 | E24: 46034.548 | F24: 1768223343 | G24: incident | H24: Error durante tratamiento | I24: Error durante tratamiento | J24: Estimado Gonzalo, buenos días. Junto saludar, informo que durante tratamiento se observó indicación de error en TCC. Código de error 533 " La TCC no está lista para la administración del tratamiento". Esto ocurrió mientras la fuente estaba entregando tratamiento. Para poder continuar se reemplazó el tubo de transferencia y se dio reanudar. Se adjunta fotografía. Seria importante que lo puedas analizar el lunes 15/12 PM. Saludos cordiales, | K24: high | L24: new | M24: 20254020297371 | N24: 20254020297371 | P24: 14740499786395 | Q24: 14481465021595 | R24: FALSE | S24: TRUE | T24: 14481427193115 | U24: 20P4LX-X371V | V24: 34266025952155 | W24: 14481427110299 | X24: FALSE | Y24: TRUE | Z24: FALSE | AA24: agent | AB24: web | AC24: unoffered | AD24: brachy, elekta, hardware_y_software, media, monaco, mosaiq, no, problema, sinergy, supervisor_de_radioterapía, synergy, tcc | AG24: no | AH24: problema | AI24: tcc
A25: https://eygmedicalsystems.zendesk.com/api/v2/tickets/9746.json | B25: 9746 | C25: {=IF( ISNUMBER(MATCH(B25, Reporte_Tickets_Detallado!C:C, 0)), "Vinculado (" & INDEX(Reporte_Tickets_Detallado!B:B, MATCH(B25, Reporte_Tickets_Detallado!C:C, 0)) & ")", "Sin Tarea" )} -> Vinculado (3428) | D25: 46002.736 | E25: 46007.663 | F25: 1765900464 | G25: incident | H25: Panel de control lateral de camilla está suelto | I25: Panel de control lateral de camilla está suelto | J25: Panel de control lateral izquierdo de camilla está suelto. [cid:74f446dc-37bc-4f2b-b834-82b81d41f4a3] | K25: normal | L25: closed | M25: 26080969273499 | N25: 26080969273499 | O25: 19579468718875 | P25: 14741543428379 | Q25: 14481465021595 | R25: FALSE | S25: TRUE | T25: 14953031074331 | U25: ZE7GNG-L031P | V25: 20427286020763 | W25: 14481427110299 | X25: FALSE | Y25: TRUE | Z25: FALSE | AA25: agent | AB25: email | AC25: offered | AD25: elekta, físico, hardware_y_software, hexapod, iview, linac, monaco, mosaiq, no, platform, requerimiento, sistema_camilla_precise, suncheck_machine, sunnuclear, versahd, xvi | AF25: sistema_camilla_precise | AG25: no | AH25: requerimiento | AK25: 01K2MWPZ0X0DMAW9P42PW6X6V4
A26: https://eygmedicalsystems.zendesk.com/api/v2/tickets/9745.json | B26: 9745 | C26: {=IF( ISNUMBER(MATCH(B26, Reporte_Tickets_Detallado!C:C, 0)), "Vinculado (" & INDEX(Reporte_Tickets_Detallado!B:B, MATCH(B26, Reporte_Tickets_Detallado!C:C, 0)) & ")", "Sin Tarea" )} -> Sin Tarea | D26: 46002.626 | E26: 46032.691 | F26: 1768062910 | G26: incident | H26: Interlock Table Long | I26: Interlock Table Long | J26: Para dejar constancia, se presentó interlock Table long previo a tratamiento de un paciente, alrededor de las 11:00 horas, se logró sacar realizando movimientos suaves de la camilla en longitudinal. se informará de cualquier otro evento relacionado. Saludos [cid:dfc9d19c-3919-4bd9-9614-c55d6d994223] | K26: normal | L26: closed | M26: 26080969273499 | N26: 26080969273499 | O26: 19579468718875 | P26: 14741543428379 | Q26: 14481465021595 | R26: FALSE | S26: TRUE | T26: 14953031074331 | U26: PE4PVZ-WNRYM | V26: 20427286020763 | W26: 14481427110299 | X26: FALSE | Y26: TRUE | Z26: FALSE | AA26: agent | AB26: email | AC26: offered | AD26: elekta, físico, hardware_y_software, hexapod, iview, linac, monaco, mosaiq, no, platform, problema, sistema_camilla_precise, suncheck_machine, sunnuclear, versahd, xvi | AF26: sistema_camilla_precise | AG26: no | AH26: problema | AK26: 01K2MWPZ0X0DMAW9P42PW6X6V4
A27: https://eygmedicalsystems.zendesk.com/api/v2/tickets/9743.json | B27: 9743 | C27: {=IF( ISNUMBER(MATCH(B27, Reporte_Tickets_Detallado!C:C, 0)), "Vinculado (" & INDEX(Reporte_Tickets_Detallado!B:B, MATCH(B27, Reporte_Tickets_Detallado!C:C, 0)) & ")", "Sin Tarea" )} -> Sin Tarea | D27: 46002.542 | E27: 46017.514 | F27: 1766751630 | G27: incident | H27: Switches sin luz | I27: Switches sin luz | J27: Hola! Recien tuvimos un corte de luz, y si bien todas las upc funcionaron bien, se cayo la red en planning y eso botó medio servicio. Evaluar una upc en la cajita de switches u otra solucion. Saludos JL | K27: low | L27: closed | M27: 26080982926747 | N27: 26080982926747 | O27: 14481448391451 | P27: 14741543428379 | Q27: 14481465021595 | R27: FALSE | S27: TRUE | T27: 14953031074331 | U27: 20PKLD-0YE7R | V27: 20427286020763 | W27: 14481427110299 | X27: FALSE | Y27: TRUE | Z27: FALSE | AA27: agent | AB27: email | AC27: offered | AD27: elekta, físico, hardware_y_software, hexapod, incidente, iview, linac, monaco, mosaiq, mosaiq_workstation, no, platform, suncheck_machine, sunnuclear, versahd, xvi | AF27: mosaiq_workstation | AG27: no | AH27: incidente | AK27: 01K2MWPZ0X0DMAW9P42PW6X6V4
A28: https://eygmedicalsystems.zendesk.com/api/v2/tickets/9742.json | B28: 9742 | C28: {=IF( ISNUMBER(MATCH(B28, Reporte_Tickets_Detallado!C:C, 0)), "Vinculado (" & INDEX(Reporte_Tickets_Detallado!B:B, MATCH(B28, Reporte_Tickets_Detallado!C:C, 0)) & ")", "Sin Tarea" )} -> Sin Tarea | D28: 46001.851 | E28: 46012.742 | F28: 1766339281 | G28: incident | H28: Conebeam presenta artefacto | I28: Conebeam presenta artefacto | J28: Conebeam presenta artefacto | K28: high | L28: closed | M28: 36182421530907 | N28: 36182421530907 | O28: 20210900681499 | P28: 14741318546075 | Q28: 14481465021595 | R28: FALSE | S28: TRUE | T28: 14953031074331 | U28: 20PJJ1-NK1WV | V28: 20427286020763 | W28: 14481427110299 | X28: FALSE | Y28: TRUE | Z28: FALSE | AA28: agent | AB28: web | AC28: offered | AD28: agility, elekta, hardware_y_software, monaco, mosaiq, no, problema, sinergy, suncheck, suncheck_machine, sunnuclear, supervisor_de_equipo_médicos, versahd | AF28: suncheck | AG28: no | AH28: problema | AK28: 01K2MWKNK7SBBFQAXJYFH5C7RR
A29: https://eygmedicalsystems.zendesk.com/api/v2/tickets/9740.json | B29: 9740 | C29: {=IF( ISNUMBER(MATCH(B29, Reporte_Tickets_Detallado!C:C, 0)), "Vinculado (" & INDEX(Reporte_Tickets_Detallado!B:B, MATCH(B29, Reporte_Tickets_Detallado!C:C, 0)) & ")", "Sin Tarea" )} -> Sin Tarea | D29: 46001.651 | E29: 46028.664 | F29: 1767714988 | G29: incident | H29: verificacion configuracion del Baseline del test de Hancock MLC Suncheck del Infinity | I29: verificacion configuracion del Baseline del test de Hancock MLC Suncheck del Infinity | J29: Se solicita ayuda de un especialista de SunNuclear para revisar la configuracion del Baseline del Test de Hancock MLC QA del SunCheck para el Infinity, ya que este Test da fuera de tolerancia para SRS/SBRT (mayor a 1 mm) y se quiere descartar que se trate de un problema de configuracion. Adjunto imagenes de resultados del Test con Gantry en 180 grados efectuado en diferentes fechas. (La persona que configuro este Test de SunNuclear fue Thiago Schimitberger a quien copio). | K29: urgent | L29: open | M29: 20254050947483 | N29: 20254050947483 | O29: 19579474867355 | P29: 14741593614363 | Q29: 14481465021595 | R29: FALSE | S29: TRUE | T29: 14481439466779 | U29: 201L9M-ZVKR9 | V29: 20427286020763 | W29: 14481427110299 | X29: FALSE | Y29: TRUE | Z29: FALSE | AA29: agent | AB29: web | AC29: unoffered | AD29: citrix, elekta, físico, hardware_y_software, infinity, iview, linac, media, monaco, mosaiq, no, on_hold_1h, requerimiento, storage, suncheck_machine, sunnuclear, xvi | AG29: no | AH29: requerimiento | AK29: 01K2MWR2KCZK72HY0ZV2CSMFTN
A30: https://eygmedicalsystems.zendesk.com/api/v2/tickets/9739.json | B30: 9739 | C30: {=IF( ISNUMBER(MATCH(B30, Reporte_Tickets_Detallado!C:C, 0)), "Vinculado (" & INDEX(Reporte_Tickets_Detallado!B:B, MATCH(B30, Reporte_Tickets_Detallado!C:C, 0)) & ")", "Sin Tarea" )} -> Sin Tarea | D30: 46001.623 | E30: 46005.656 | F30: 1765727095 | G30: incident | H30: Pantalla de acelerador sin señal | I30: Pantalla de acelerador sin señal | J30: Estimados Repentinamente las pantallas del acelerador quedaron sin señal, se reinició el TRM sin resultado positivo. equipo detenido Saludos [cid:d98360ef-657a-4fcf-9205-a2548d94f5e9] | K30: high | L30: closed | M30: 26080969273499 | N30: 26080969273499 | O30: 19579468718875 | P30: 14741543428379 | Q30: 14481465021595 | R30: FALSE | S30: TRUE | T30: 14953031074331 | U30: ZE42GX-J0KWP | V30: 20427286020763 | W30: 14481427110299 | X30: FALSE | Y30: TRUE | Z30: FALSE | AA30: agent | AB30: email | AC30: offered | AD30: elekta, físico, hardware_y_software, hexapod, iview, linac, monaco, mosaiq, no, platform, problema, sistema_ccp, suncheck_machine, sunnuclear, versahd, xvi | AF30: sistema_ccp | AG30: no | AH30: problema | AK30: 01K2MWPZ0X0DMAW9P42PW6X6V4
A31: https://eygmedicalsystems.zendesk.com/api/v2/tickets/9737.json | B31: 9737 | C31: {=IF( ISNUMBER(MATCH(B31, Reporte_Tickets_Detallado!C:C, 0)), "Vinculado (" & INDEX(Reporte_Tickets_Detallado!B:B, MATCH(B31, Reporte_Tickets_Detallado!C:C, 0)) & ")", "Sin Tarea" )} -> Vinculado (3422) | D31: 46000.798 | E31: 46005.656 | F31: 1765727095 | G31: incident | H31: Versa se apaga de forma espontanea | I31: Versa se apaga de forma espontanea | J31: Estimados, el Versa se apagó de forma espontánea. Al intentar encenderlo vuelve a apagarse antes de completar el proceso de encendido. Tenemos equipo detenido. Esperamos por su asistencia | K31: urgent | L31: closed | M31: 20254050953243 | N31: 20254050953243 | O31: 19579474867355 | P31: 20265216319003 | Q31: 14481465021595 | R31: FALSE | S31: TRUE | T31: 14481439499675 | U31: 20147R-YJ9V9 | V31: 20427286020763 | W31: 14481427110299 | X31: FALSE | Y31: TRUE | Z31: FALSE | AA31: agent | AB31: web | AC31: good | AD31: acelerador_lineal, elekta, físico, linac, problema, si, versahd | AF31: acelerador_lineal | AG31: si | AH31: problema | AK31: 01K2MWGQVK5P8BZ4P54MS8055Q
A32: https://eygmedicalsystems.zendesk.com/api/v2/tickets/9734.json | B32: 9734 | C32: {=IF( ISNUMBER(MATCH(B32, Reporte_Tickets_Detallado!C:C, 0)), "Vinculado (" & INDEX(Reporte_Tickets_Detallado!B:B, MATCH(B32, Reporte_Tickets_Detallado!C:C, 0)) & ")", "Sin Tarea" )} -> Vinculado (3429) | D32: 46000.727 | E32: 46007.663 | F32: 1765900464 | G32: incident | H32: Solicitud de colaboración para prueba de interruptores de emergencia del acelerador lineal | I32: Solicitud de colaboración para prueba de interruptores de emergencia del acelerador lineal | J32: Estimados señores de EyG, Espero se encuentren muy bien. Por medio del presente, solicito vuestra colaboración, mediante la participación del Ing. Roberto A., para la realización de la prueba de los interruptores de emergencia asociados al acelerador lineal. Su presencia es necesaria debido a que, como ingeniero de servicio, cuenta con la capacitación y autorización para ejecutar estas pruebas de manera segura y sin riesgo para la integridad del equipo. Propongo llevar a cabo esta actividad el viernes 12, una vez concluidos los tratamientos clínicos del día, con el fin de no interferir con la operación habitual del equipo. Agradezco confirmar su disponibilidad para esa fecha. Quedo atento a cualquier comentario o requerimiento adicional para la correcta realización de la prueba. Saludos cordiales, [cid:38dc7681-b102-4285-a998-259652993560] | K32: normal | L32: closed | M32: 26080969273499 | N32: 26080969273499 | O32: 19579468718875 | P32: 14741543428379 | Q32: 14481465021595 | R32: FALSE | S32: TRUE | T32: 14953031074331 | U32: 0457EZ-JDVWX | V32: 20427286020763 | W32: 14481427110299 | X32: FALSE | Y32: TRUE | Z32: FALSE | AA32: agent | AB32: email | AC32: offered | AD32: acelerador_lineal, elekta, físico, hardware_y_software, hexapod, iview, linac, monaco, mosaiq, no, platform, requerimiento, suncheck_machine, sunnuclear, versahd, xvi | AF32: acelerador_lineal | AG32: no | AH32: requerimiento | AK32: 01K2MWPZ0X0DMAW9P42PW6X6V4
A33: https://eygmedicalsystems.zendesk.com/api/v2/tickets/9733.json | B33: 9733 | C33: {=IF( ISNUMBER(MATCH(B33, Reporte_Tickets_Detallado!C:C, 0)), "Vinculado (" & INDEX(Reporte_Tickets_Detallado!B:B, MATCH(B33, Reporte_Tickets_Detallado!C:C, 0)) & ")", "Sin Tarea" )} -> Sin Tarea | D33: 46000.615 | E33: 46032.607 | F33: 1768055608 | G33: incident | H33: ruido muy fuerte al girar el gantry del Infinity - por favor investigar | I33: ruido muy fuerte al girar el gantry del Infinity - por favor investigar | J33: Al rotar el gantry del Infinity se escucha un ruido muy fuerte y atipico. Parece un roce mecanico, o falta de lubricacion. Por favor investigar cuanto antes en terreno, para despejar dudas si este ruido esta dentro de lo normal o no. | K33: normal | L33: closed | M33: 20254050947483 | N33: 20254050947483 | O33: 19579474867355 | P33: 14741593614363 | Q33: 14481465021595 | R33: FALSE | S33: TRUE | T33: 14481439499675 | U33: 045P72-RV7MX | V33: 20427286020763 | W33: 14481427110299 | X33: FALSE | Y33: TRUE | Z33: FALSE | AA33: agent | AB33: web | AC33: offered | AD33: acelerador_lineal, elekta, físico, infinity, linac, no, problema | AF33: acelerador_lineal | AG33: no | AH33: problema | AK33: 01K2MWR2KCZK72HY0ZV2CSMFTN
A34: https://eygmedicalsystems.zendesk.com/api/v2/tickets/9732.json | B34: 9732 | C34: {=IF( ISNUMBER(MATCH(B34, Reporte_Tickets_Detallado!C:C, 0)), "Vinculado (" & INDEX(Reporte_Tickets_Detallado!B:B, MATCH(B34, Reporte_Tickets_Detallado!C:C, 0)) & ")", "Sin Tarea" )} -> Sin Tarea | D34: 46000.58 | E34: 46011.634 | F34: 1766243577 | G34: incident | H34: Falla XVI - Fault 33 - despejada gracias a FM Camilo de la Barra | I34: Falla XVI - Fault 33 - despejada gracias a FM Camilo de la Barra | J34: Falla XVI - Fault 33 - despejada gracias a accion del FM Camilo de la Barra Olate (aprendido de fallas anteriores) Se encontro abajo el interruptor K2 GEN Rayos X, del tablero Principal (se veia en posicion intermedia). Por lo que se bajo este interruptor automatico, a continuacion se bajo tambien el interruptor de palanca (OFF) de K2 GEN Rayos X, encendiendo luz roja (apagado). Luego se espero 5 segundos y se subio el interruptor automatico K@ GEN Rayos de arriba, y finalmente se subio el interruptor de palanca (ON), encienciendo luz verde (energizado). Nota: se deja esta constancia para registro de falla ocurrida y despejada antes de las 08:00 am, para seguimiento en el caso de que vuelva a ocurrir. | K34: high | L34: closed | M34: 20254050947483 | N34: 20254050947483 | O34: 19579474867355 | P34: 14741593614363 | Q34: 14481465021595 | R34: FALSE | S34: TRUE | T34: 14481439499675 | U34: ZE4VWX-3MYWP | V34: 20427286020763 | W34: 14481427110299 | X34: FALSE | Y34: TRUE | Z34: FALSE | AA34: agent | AB34: web | AC34: offered | AD34: elekta, físico, infinity, integrity, iview, linac, no, problema, xvi | AF34: integrity | AG34: no | AH34: problema | AK34: 01K2MWR2KCZK72HY0ZV2CSMFTN
A35: https://eygmedicalsystems.zendesk.com/api/v2/tickets/9731.json | B35: 9731 | C35: {=IF( ISNUMBER(MATCH(B35, Reporte_Tickets_Detallado!C:C, 0)), "Vinculado (" & INDEX(Reporte_Tickets_Detallado!B:B, MATCH(B35, Reporte_Tickets_Detallado!C:C, 0)) & ")", "Sin Tarea" )} -> Vinculado (3444) | D35: 46000.529 | E35: 46021.854 | F35: 1767126579 | G35: incident | H35: Falla en panel iview | I35: Falla en panel iview | J35: A estado fallando el panel del XVI del sur Agility, a veces se tranca o queda parpadeando, y a veces hay que reiniciarlo para poder seguir usándolo. Favor si es posible la revisión hoy a partir de las 17:00 hrs ya que el equipo estará sin pacientes | K35: urgent | L35: open | M35: 36182421530907 | N35: 36182421530907 | P35: 14741318546075 | Q35: 14481465021595 | R35: FALSE | S35: TRUE | T35: 14481439466779 | U35: MEWKR4-1YXKV | V35: 20427286020763 | W35: 14481427110299 | X35: FALSE | Y35: TRUE | Z35: FALSE | AA35: agent | AB35: web | AC35: unoffered | AD35: agility, elekta, hardware_y_software, monaco, mosaiq, no, problema, sinergy, suncheck, suncheck_machine, sunnuclear, supervisor_de_equipo_médicos, versahd | AF35: suncheck | AG35: no | AH35: problema | AK35: 01K2MWJ4ARZRVMA1V6XFP5Y5E4
A36: https://eygmedicalsystems.zendesk.com/api/v2/tickets/9724.json | B36: 9724 | C36: {=IF( ISNUMBER(MATCH(B36, Reporte_Tickets_Detallado!C:C, 0)), "Vinculado (" & INDEX(Reporte_Tickets_Detallado!B:B, MATCH(B36, Reporte_Tickets_Detallado!C:C, 0)) & ")", "Sin Tarea" )} -> Sin Tarea | D36: 45995.568 | E36: 46000.627 | F36: 1765292609 | G36: incident | H36: falla intermitente del sistema de audio que dificulta oir al paciente del CL02 Infinity | I36: falla intermitente del sistema de audio que dificulta oir al paciente del CL02 Infinity | J36: Estimados EyG, Hay una falla intermitente del intercomunicador o sistema de audio, que dificulta oir bien al paciente que se encuentra al interior del bunker del CL02 Infinity. Se solicita por favor reparar este problema en la mantencion de mañana viernes 5 de diciembre del 2025. Muchas gracias por su gentil ayuda y colaboracion. | K36: high | L36: pending | M36: 20254050947483 | N36: 20254050947483 | P36: 14741593614363 | Q36: 14481465021595 | R36: FALSE | S36: TRUE | T36: 14481437571483 | U36: 204L10-9JNWV | V36: 20427286020763 | W36: 14481427110299 | X36: FALSE | Y36: TRUE | Z36: FALSE | AA36: agent | AB36: web | AC36: unoffered | AD36: citrix, elekta, físico, hardware_y_software, infinity, integrity, iview, linac, media, monaco, mosaiq, no, problema, storage, suncheck_machine, sunnuclear, xvi | AF36: integrity | AG36: no | AH36: problema | AK36: 01K2MWR2KCZK72HY0ZV2CSMFTN
A37: https://eygmedicalsystems.zendesk.com/api/v2/tickets/9723.json | B37: 9723 | C37: {=IF( ISNUMBER(MATCH(B37, Reporte_Tickets_Detallado!C:C, 0)), "Vinculado (" & INDEX(Reporte_Tickets_Detallado!B:B, MATCH(B37, Reporte_Tickets_Detallado!C:C, 0)) & ")", "Sin Tarea" )} -> Vinculado (3423) | D37: 45995.465 | E37: 46011.676 | F37: 1766247191 | G37: incident | H37: Problemas MLC Infinity | I37: Problemas MLC Infinity | J37: Estimados, buen día, El día de hoy no fue posible cargar campos en el equipo Infinity, adjunto errores, equipo detenido | K37: urgent | L37: closed | M37: 23562920769947 | N37: 23562920769947 | O37: 27816237178267 | P37: 14741297259931 | Q37: 14481465021595 | R37: FALSE | S37: TRUE | T37: 14481439499675 | U37: ZENL2J-N3791 | V37: 20427286020763 | W37: 14481427110299 | X37: FALSE | Y37: TRUE | Z37: FALSE | AA37: agent | AB37: web | AC37: offered | AD37: cabezal_agility, elekta, físico, infinity, problema, si | AF37: cabezal_agility | AG37: si | AH37: problema | AK37: 01K2MWEACAGHS4HXG14TE1Y3QE
A38: https://eygmedicalsystems.zendesk.com/api/v2/tickets/9716.json | B38: 9716 | C38: {=IF( ISNUMBER(MATCH(B38, Reporte_Tickets_Detallado!C:C, 0)), "Vinculado (" & INDEX(Reporte_Tickets_Detallado!B:B, MATCH(B38, Reporte_Tickets_Detallado!C:C, 0)) & ")", "Sin Tarea" )} -> Sin Tarea | D38: 45993.492 | E38: 46025.845 | F38: 1767471397 | G38: incident | H38: Notebook de qa no carga | I38: Notebook de qa no carga | J38: He probado cambiando el cargador (tenemos dos iguales), reseteando la bateria desde la bios, reseteando desde el botoncito oculto de abajo, de todo. Ni prende (se quedo sin bat) ni carga (dejo de cargar en algun momento) Entiendo que estan en garantia. Quedo atento, saludos JL | K38: normal | L38: closed | M38: 26080982926747 | N38: 26080982926747 | O38: 14481448391451 | P38: 14741543428379 | Q38: 14481465021595 | R38: FALSE | S38: TRUE | T38: 14481439499675 | U38: PE1REK-WR6GN | V38: 20427286020763 | W38: 14481427110299 | X38: FALSE | Y38: TRUE | Z38: FALSE | AA38: agent | AB38: email | AC38: offered | AD38: elekta, físico, hardware_y_software, hexapod, iview, linac, monaco, mosaiq, no, platform, requerimiento, suncheck, suncheck_machine, sunnuclear, versahd, xvi | AF38: suncheck | AG38: no | AH38: requerimiento
A39: https://eygmedicalsystems.zendesk.com/api/v2/tickets/9709.json | B39: 9709 | C39: {=IF( ISNUMBER(MATCH(B39, Reporte_Tickets_Detallado!C:C, 0)), "Vinculado (" & INDEX(Reporte_Tickets_Detallado!B:B, MATCH(B39, Reporte_Tickets_Detallado!C:C, 0)) & ")", "Sin Tarea" )} -> Sin Tarea | D39: 45992.489 | E39: 46000.543 | F39: 1765285321 | G39: incident | H39: Asunto: Artefacto de anillo en el XVI del Axesee | I39: Asunto: Artefacto de anillo en el XVI del Axesee | J39: Este es un seguimiento de su solicitud anterior #9635 "Artefacto de anillo en el XVI del Axesee". Estimados, Buenos días, el artefacto sigue igual visualizándose, se realizaron pruebas en modo servicio y no se puede ver, pero en modo clínico se visualiza. Adjunto imágenes para su revisión. | K39: high | L39: pending | M39: 20254050952475 | N39: 20254050952475 | P39: 14741297259931 | Q39: 14481465021595 | R39: FALSE | S39: TRUE | T39: 14481437571483 | U39: 767J52-MZD95 | V39: 20427286020763 | W39: 14481427110299 | X39: FALSE | Y39: TRUE | Z39: FALSE | AA39: agent | AB39: web | AC39: unoffered | AD39: axesse, braquiterapia, clarity, elekta, físico, hardware_y_software, infinity, monaco, mosaiq, no, on_hold_1h, problema | AF39: clarity | AG39: no | AH39: problema | AK39: 01K2MVY8Y64ADSZN89S82WQWXZ
A40: https://eygmedicalsystems.zendesk.com/api/v2/tickets/9706.json | B40: 9706 | C40: {=IF( ISNUMBER(MATCH(B40, Reporte_Tickets_Detallado!C:C, 0)), "Vinculado (" & INDEX(Reporte_Tickets_Detallado!B:B, MATCH(B40, Reporte_Tickets_Detallado!C:C, 0)) & ")", "Sin Tarea" )} -> Vinculado (3425) | D40: 45988.83 | E40: 46012.742 | F40: 1766339280 | G40: incident | H40: Problemas en posicionamiento de Hexapod | I40: Problemas en posicionamiento de Hexapod | J40: Inconsistencia en los resultados esperados para las pruebas de posicionamiento con la camilla Hexapod | K40: high | L40: closed | M40: 36182421530907 | N40: 36182421530907 | O40: 20210900681499 | P40: 14741318546075 | Q40: 14481465021595 | R40: FALSE | S40: TRUE | T40: 14481439499675 | U40: 0420ZG-1R57X | V40: 20427286020763 | W40: 14481427110299 | X40: FALSE | Y40: TRUE | Z40: FALSE | AA40: agent | AB40: web | AC40: offered | AD40: agility, elekta, hardware_y_software, monaco, mosaiq, no, problema, sinergy, suncheck, suncheck_machine, sunnuclear, supervisor_de_equipo_médicos, versahd | AF40: suncheck | AG40: no | AH40: problema | AK40: 01K2MWKNK7SBBFQAXJYFH5C7RR
A41: https://eygmedicalsystems.zendesk.com/api/v2/tickets/9703.json | B41: 9703 | C41: {=IF( ISNUMBER(MATCH(B41, Reporte_Tickets_Detallado!C:C, 0)), "Vinculado (" & INDEX(Reporte_Tickets_Detallado!B:B, MATCH(B41, Reporte_Tickets_Detallado!C:C, 0)) & ")", "Sin Tarea" )} -> Sin Tarea | D41: 45988.477 | E41: 45993.708 | F41: 1764694793 | G41: incident | H41: Maquina detenida por falla desconocida | I41: Maquina detenida por falla desconocida | J41: El Linac arroja un error sin descripción que no permite tatar pacientes se requiere asistencia inmediata por favor. | K41: urgent | L41: closed | M41: 38368479928987 | N41: 38368479928987 | O41: 19579474867355 | P41: 14742026913435 | Q41: 14481465021595 | R41: FALSE | S41: TRUE | T41: 14481439499675 | U41: ME0216-Z1YVV | V41: 20427286020763 | W41: 14481427110299 | X41: FALSE | Y41: TRUE | Z41: FALSE | AA41: agent | AB41: web | AC41: offered | AD41: acelerador_lineal, compact, elekta, problema, si | AF41: acelerador_lineal | AG41: si | AH41: problema | AK41: 01K2MXCF9WW205P1YQ3PCD50A9
A42: https://eygmedicalsystems.zendesk.com/api/v2/tickets/9696.json | B42: 9696 | C42: {=IF( ISNUMBER(MATCH(B42, Reporte_Tickets_Detallado!C:C, 0)), "Vinculado (" & INDEX(Reporte_Tickets_Detallado!B:B, MATCH(B42, Reporte_Tickets_Detallado!C:C, 0)) & ")", "Sin Tarea" )} -> Sin Tarea | D42: 45987.579 | E42: 45993.708 | F42: 1764694793 | G42: incident | H42: equipo detenido por problemas con magnetron | I42: equipo detenido por problemas con magnetron | J42: El equipo se encuentra detenido por problemas en el magnetron tras el cambio realizado recientemente. se requiere con urgencia asistencia para volver al magnetron anterior. De forma adicional, se solicita una cotización para un magnetron nuevo, para organizar una compra en el futuro | K42: urgent | L42: closed | M42: 38368479928987 | N42: 38368479928987 | O42: 19579474867355 | P42: 14742026913435 | Q42: 14481465021595 | R42: FALSE | S42: TRUE | T42: 14481439499675 | U42: ZE0KLV-LGVDW | V42: 20427286020763 | W42: 14481427110299 | X42: FALSE | Y42: TRUE | Z42: FALSE | AA42: agent | AB42: web | AC42: offered | AD42: acelerador_lineal, compact, elekta, problema, si, tcs | AF42: acelerador_lineal | AG42: si | AH42: problema | AI42: tcs | AK42: 01K2MXCF9WW205P1YQ3PCD50A9
A43: https://eygmedicalsystems.zendesk.com/api/v2/tickets/9695.json | B43: 9695 | C43: {=IF( ISNUMBER(MATCH(B43, Reporte_Tickets_Detallado!C:C, 0)), "Vinculado (" & INDEX(Reporte_Tickets_Detallado!B:B, MATCH(B43, Reporte_Tickets_Detallado!C:C, 0)) & ")", "Sin Tarea" )} -> Sin Tarea | D43: 45987.535 | E43: 46017.642 | F43: 1766762704 | G43: incident | H43: Falla HEXAPOD VERSA 2 | I43: Falla HEXAPOD VERSA 2 | J43: Estimados, Se requiere revision del HEXAPOD del VERSA 2 porque no alcanza la posicion de referencia durante chequeo diario. Saludos, Manuel. | K43: normal | L43: closed | M43: 20254020292379 | N43: 20254020292379 | O43: 19579474867355 | P43: 14741389938587 | Q43: 14481465021595 | R43: FALSE | S43: TRUE | T43: 14481439499675 | U43: 0421GG-EXR7X | V43: 20427286020763 | W43: 14481427110299 | X43: FALSE | Y43: TRUE | Z43: FALSE | AA43: agent | AB43: web | AC43: offered | AD43: acelerador_lineal, elekta, físico, hexapod, no, problema, versahd | AF43: acelerador_lineal | AG43: no | AH43: problema | AK43: 01K2MX4Z0KY2MHPJMC4ZM7C8T1
A44: https://eygmedicalsystems.zendesk.com/api/v2/tickets/9691.json | B44: 9691 | C44: {=IF( ISNUMBER(MATCH(B44, Reporte_Tickets_Detallado!C:C, 0)), "Vinculado (" & INDEX(Reporte_Tickets_Detallado!B:B, MATCH(B44, Reporte_Tickets_Detallado!C:C, 0)) & ")", "Sin Tarea" )} -> Sin Tarea | D44: 45986.475 | E44: 45990.52 | F44: 1764419305 | G44: incident | H44: Interlock D1 | I44: Interlock D1 | J44: Hola: Ayer lunes 24 aparecieron los interlocks: D1 rly off y D1 supply durante los tratamientos, en la mañana aparecía "aleatoriamente" y ya después no pudimos sacarlo. Al comienzo lo sacábamos cargando otro plan o pasando a modo servicio. La semana pasada el miércoles apareció al final de dos tratamientos (con distintas energías), y se ajustó output y lectura de MU1 y MU2. No volvió a salir hasta ayer que solicitamos apoyo al servicio técnico. ¡Saludos! ![](https://eygmedicalsystems.zendesk.com/attachments/token/NtLChNvohcKkEGXZDxrPKiCWf/?name=blobid0.jpg) ![](https://eygmedicalsystems.zendesk.com/attachments/token/O6YH1mMwluonqzlMHWyycd6IW/?name=blobid1.jpg) ![](https://eygmedicalsystems.zendesk.com/attachments/token/TexPbLkIOfjSjo0Pf52X2fzRN/?name=blobid2.jpg) | K44: high | L44: closed | M44: 20254020299547 | N44: 20254020299547 | O44: 22297930568347 | P44: 14741597726619 | Q44: 14481465021595 | R44: FALSE | S44: TRUE | T44: 14481439499675 | U44: 20DZVP-DR9V9 | V44: 20427286020763 | W44: 14481427110299 | X44: FALSE | Y44: TRUE | Z44: FALSE | AA44: agent | AB44: web | AC44: offered | AD44: acelerador_lineal, elekta, físico, hardware_y_software, hexapod, iba, iguide, iview, monaco, monacosim, mosaiq, requerimiento, rtp99, si, tcs, versahd, xvi | AF44: acelerador_lineal | AG44: si | AH44: requerimiento | AI44: tcs | AK44: 01K2MWN8SVJSHMJQM7F39XXN01
A45: https://eygmedicalsystems.zendesk.com/api/v2/tickets/9690.json | B45: 9690 | C45: {=IF( ISNUMBER(MATCH(B45, Reporte_Tickets_Detallado!C:C, 0)), "Vinculado (" & INDEX(Reporte_Tickets_Detallado!B:B, MATCH(B45, Reporte_Tickets_Detallado!C:C, 0)) & ")", "Sin Tarea" )} -> Vinculado (3443) | D45: 45986.452 | E45: 46024.614 | F45: 1767365049 | G45: incident | H45: 2T 15MeV electrones | I45: 2T 15MeV electrones | J45: Buen día estimados, Equipo Axesse no permitió irradiar el campo del control diario en la energía de 15MeV, marca 2T error | K45: normal | L45: closed | M45: 23562920769947 | N45: 23562920769947 | O45: 19579474867355 | P45: 14741297259931 | Q45: 14481465021595 | R45: FALSE | S45: TRUE | T45: 14481439499675 | U45: ME59LR-K524V | V45: 20427286020763 | W45: 14481427110299 | X45: FALSE | Y45: TRUE | Z45: FALSE | AA45: agent | AB45: web | AC45: good | AD45: acelerador_lineal, axesse, elekta, físico, no, problema | AF45: acelerador_lineal | AG45: no | AH45: problema | AK45: 01K2MVY8Y64ADSZN89S82WQWXZ
A46: https://eygmedicalsystems.zendesk.com/api/v2/tickets/9689.json | B46: 9689 | C46: {=IF( ISNUMBER(MATCH(B46, Reporte_Tickets_Detallado!C:C, 0)), "Vinculado (" & INDEX(Reporte_Tickets_Detallado!B:B, MATCH(B46, Reporte_Tickets_Detallado!C:C, 0)) & ")", "Sin Tarea" )} -> Sin Tarea | D46: 45985.648 | E46: 46011.676 | F46: 1766247191 | G46: incident | H46: Inestabilidad de los haces de fotones VERSA 1 | I46: Inestabilidad de los haces de fotones VERSA 1 | J46: Estimados, Se requiere revisión de haces de fotones del VERSA 1 por inestabilidad de la tasa de dosis y energía. Equipo no operativo clínicamente. Saludos, Manuel. | K46: urgent | L46: closed | M46: 20254020292379 | N46: 20254020292379 | O46: 20210900681499 | P46: 14741389938587 | Q46: 14481465021595 | R46: FALSE | S46: TRUE | T46: 14481439499675 | U46: ZEV0VK-MX0PP | V46: 20427286020763 | W46: 14481427110299 | X46: FALSE | Y46: TRUE | Z46: FALSE | AA46: agent | AB46: web | AC46: offered | AD46: acelerador_lineal, elekta, físico, problema, si, versahd | AF46: acelerador_lineal | AG46: si | AH46: problema | AK46: 01K2MWVQJ3DHXN1BYF1WF54DC4
A47: https://eygmedicalsystems.zendesk.com/api/v2/tickets/9688.json | B47: 9688 | C47: {=IF( ISNUMBER(MATCH(B47, Reporte_Tickets_Detallado!C:C, 0)), "Vinculado (" & INDEX(Reporte_Tickets_Detallado!B:B, MATCH(B47, Reporte_Tickets_Detallado!C:C, 0)) & ")", "Sin Tarea" )} -> Sin Tarea | D47: 45985.645 | E47: 45990.751 | F47: 1764439307 | G47: incident | H47: Falla telemetro VERSA 2 | I47: Falla telemetro VERSA 2 | J47: Estimados, Se requiere revisión del telemetro del VERSA 2 porque no enciende. Saludos, Manuel. | K47: normal | L47: pending | M47: 20254020292379 | N47: 20254020292379 | P47: 14741389938587 | Q47: 14481465021595 | R47: FALSE | S47: TRUE | T47: 14952899745563 | U47: ME50KD-7VN4V | V47: 20427286020763 | W47: 14481427110299 | X47: FALSE | Y47: TRUE | Z47: FALSE | AA47: agent | AB47: web | AC47: unoffered | AD47: abc, elekta, físico, hardware_y_software, hexapod, media, monaco, mosaiq, no, problema, versahd | AF47: abc | AG47: no | AH47: problema | AK47: 01K2MX4Z0KY2MHPJMC4ZM7C8T1
A48: https://eygmedicalsystems.zendesk.com/api/v2/tickets/9685.json | B48: 9685 | C48: {=IF( ISNUMBER(MATCH(B48, Reporte_Tickets_Detallado!C:C, 0)), "Vinculado (" & INDEX(Reporte_Tickets_Detallado!B:B, MATCH(B48, Reporte_Tickets_Detallado!C:C, 0)) & ")", "Sin Tarea" )} -> Sin Tarea | D48: 45985.511 | E48: 46011.676 | F48: 1766247190 | G48: incident | H48: Interlock Low Water Pressure VERSA 1 | I48: Interlock Low Water Pressure VERSA 1 | J48: Estimados, Se requiere revision del VERSA 1 por interlock Low Water Pressure y no permite irradiar. Saludos, Manuel. | K48: urgent | L48: closed | M48: 20254020292379 | N48: 20254020292379 | O48: 20210900681499 | P48: 14741389938587 | Q48: 14481465021595 | R48: FALSE | S48: TRUE | T48: 14481439499675 | U48: PE5M4J-Z009M | V48: 20427286020763 | W48: 14481427110299 | X48: FALSE | Y48: TRUE | Z48: FALSE | AA48: agent | AB48: web | AC48: offered | AD48: acelerador_lineal, elekta, físico, problema, si, versahd | AF48: acelerador_lineal | AG48: si | AH48: problema | AK48: 01K2MWVQJ3DHXN1BYF1WF54DC4
A49: https://eygmedicalsystems.zendesk.com/api/v2/tickets/9684.json | B49: 9684 | C49: {=IF( ISNUMBER(MATCH(B49, Reporte_Tickets_Detallado!C:C, 0)), "Vinculado (" & INDEX(Reporte_Tickets_Detallado!B:B, MATCH(B49, Reporte_Tickets_Detallado!C:C, 0)) & ")", "Sin Tarea" )} -> Sin Tarea | D49: 45985.478 | E49: 45991.663 | F49: 1764518102 | G49: incident | H49: Interlock Memoria Acelerador Axesse | I49: Interlock Memoria Acelerador Axesse | J49: Estimados al llegar esta mañana encontré un mensaje extraño en el Linac, dejo fotos. | K49: normal | L49: closed | M49: 20254050952347 | N49: 20254050952347 | O49: 22297930568347 | P49: 14741297259931 | Q49: 14481465021595 | R49: FALSE | S49: TRUE | T49: 14481439499675 | U49: 04PXP9-JDEX0 | V49: 20427286020763 | W49: 14481427110299 | X49: FALSE | Y49: TRUE | Z49: FALSE | AA49: agent | AB49: web | AC49: offered | AD49: axesse, braquiterapia, clarity, elekta, físico, hardware_y_software, infinity, monaco, mosaiq, no, problema | AF49: clarity | AG49: no | AH49: problema | AK49: 01K2MVY8Y64ADSZN89S82WQWXZ
